Workbook

Sheet Appendix_Trace
A1: Requirement ID | B1: Citation role | C1: BibTeX key | D1: Literature Code | E1: Candidate path nodes | F1: Linked Evidence IDs | G1: Other observations from same source
A2: OCPS-R1.1 | B2: BPS/general | C2: van2010business | D2: FND-003 | E2: Adapted:OCPS-CF-001; BPS:LR-CF1 | F2: EV-F-0002 | G2: EV-F-0006; EV-F-0009; EV-F-0035
A3: OCPS-R1.1 | B3: BPS/general | C3: dumas2018fundamentals | D3: FND-001 | E3: Adapted:OCPS-CF-001; BPS:LR-CF1 | F3: EV-F-0003 | G3: EV-F-0007; TP-E011; TP-E012; TP-E013; TP-E014; TP-E014-B
A4: OCPS-R1.1 | B4: BPS/general | C4: van2015business | D4: FND-004 | E4: Adapted:OCPS-CF-001; BPS:LR-CF1 | F4: EV-F-0004 | G4: EV-F-0012; EV-F-0024; EV-F-0028
A5: OCPS-R1.1 | B5: BPS/general | C5: chapela2025simod | D5: BPS-013 | E5: Adapted:OCPS-CF-001; BPS:LR-CF1 | F5: EV-S-0002 | G5: EV-AUD-0038; EV-AUD-0047; EV-AUD-0055; EV-S-0010; EV-S-0021; EV-S-0025; EV-S-0031; EV-S-0041; EV-S-0045; EV-S-0068; R5-FE-004; R5-FE-020; R5-FE-032; R5-FE-044; R5-FE-055; R5-FE-062; R5-FE-069; R5-FE-075; TP-E026; TP-E027; TP-E028
A6: OCPS-R1.1 | B6: BPS/general | C6: martin2016use | D6: FND-002 | E6: Adapted:OCPS-CF-001; BPS:LR-CF1 | F6: EV-F-0005 | G6: EV-F-0008; EV-F-0011; EV-F-0013; EV-F-0015; EV-F-0017; EV-F-0019; EV-F-0021; EV-F-0025; EV-F-0026; EV-F-0029; EV-F-0030; EV-F-0032; R5-FE-002; R5-FE-012; R5-FE-015; R5-FE-025; R5-FE-030; R5-FE-053; R5-FE-058; R5-FE-065; R5-FE-066; R5-FE-072; R5-FE-074; TP-E015; TP-E016; TP-E017
A7: OCPS-R1.1 | B7: Object-centric | C7: berti2024ocel | D7: SUP-001 | E7: Adapted:OCPS-CF-001; OCPM:OCPM-DR-001 | F7: EV-AUD-0001; EV-O-0002 | G7: EV-AUD-0002; EV-AUD-0003; EV-AUD-0004; EV-AUD-0007; EV-AUD-0008; EV-AUD-0009; EV-AUD-0012; EV-AUD-0014; EV-O-0003; EV-O-0004; EV-O-0036; EV-O-0042; EV-O-0045; EV-O-0049; EV-O-0052; EV-O-0055; EV-O-0057; EV-O-0076
A8: OCPS-R1.1 | B8: Object-centric | C8: fahland2024oced | D8: SUP-002 | E8: Adapted:OCPS-CF-001; OCPM:OCPM-DR-001 | F8: EV-O-0005 | G8: EV-O-0043; EV-O-0046
A9: OCPS-R1.1 | B9: Object-centric | C9: van2023object | D9: SUP-010 | E9: Adapted:OCPS-CF-001; OCPM:OCPM-DR-001 | F9: EV-O-0016
A10: OCPS-R1.1 | B10: Object-centric | C10: adams2025 | D10: SUP-011 | E10: Adapted:OCPS-CF-001; OCPM:OCPM-DR-001 | F10: EV-O-0017 | G10: EV-O-0053; EV-O-0058
A11: OCPS-R1.1 | B11: Object-centric | C11: esser2021multidimensional | D11: SUP-013 | E11: Adapted:OCPS-CF-001; OCPM:OCPM-DR-001 | F11: EV-O-0019 | G11: EV-O-0079
A12: OCPS-R1.2 | B12: BPS/general | C12: van2010business | D12: FND-003 | E12: BPS:LR-CF1 | F12: EV-F-0002 | G12: EV-F-0006; EV-F-0009; EV-F-0035
A13: OCPS-R1.2 | B13: BPS/general | C13: dumas2018fundamentals | D13: FND-001 | E13: BPS:LR-CF1; BPS:LR-TS1 | F13: EV-F-0003 | G13: EV-F-0007; TP-E011; TP-E012; TP-E013; TP-E014; TP-E014-B
A14: OCPS-R1.2 | B14: BPS/general | C14: van2015business | D14: FND-004 | E14: BPS:LR-CF1 | F14: EV-F-0004 | G14: EV-F-0012; EV-F-0024; EV-F-0028
A15: OCPS-R1.2 | B15: BPS/general | C15: chapela2025simod | D15: BPS-013 | E15: BPS:LR-CF1; BPS:LR-TS1 | F15: EV-S-0002 | G15: EV-AUD-0038; EV-AUD-0047; EV-AUD-0055; EV-S-0010; EV-S-0021; EV-S-0025; EV-S-0031; EV-S-0041; EV-S-0045; EV-S-0068; R5-FE-004; R5-FE-020; R5-FE-032; R5-FE-044; R5-FE-055; R5-FE-062; R5-FE-069; R5-FE-075; TP-E026; TP-E027; TP-E028
A16: OCPS-R1.2 | B16: BPS/general | C16: martin2016use | D16: FND-002 | E16: Adapted:OCPS-DR-003; BPS:LR-CF1; BPS:LR-TS1 | F16: EV-F-0005; EV-F-0029 | G16: EV-F-0008; EV-F-0011; EV-F-0013; EV-F-0015; EV-F-0017; EV-F-0019; EV-F-0021; EV-F-0025; EV-F-0026; EV-F-0030; EV-F-0032; R5-FE-002; R5-FE-012; R5-FE-015; R5-FE-025; R5-FE-030; R5-FE-053; R5-FE-058; R5-FE-065; R5-FE-066; R5-FE-072; R5-FE-074; TP-E015; TP-E016; TP-E017
A17: OCPS-R1.2 | B17: Object-centric | C17: berti2024ocel | D17: SUP-001 | E17: Adapted:OCPS-DR-003; Direct:DATA-01; Direct:DATA-02; OCPM:OCPM-DR-001 | F17: EV-AUD-0002; EV-O-0002 | G17: EV-AUD-0001; EV-AUD-0003; EV-AUD-0004; EV-AUD-0007; EV-AUD-0008; EV-AUD-0009; EV-AUD-0012; EV-AUD-0014; EV-O-0003; EV-O-0004; EV-O-0036; EV-O-0042; EV-O-0045; EV-O-0049; EV-O-0052; EV-O-0055; EV-O-0057; EV-O-0076
A18: OCPS-R1.2 | B18: Object-centric | C18: fahland2024oced | D18: SUP-002 | E18: Adapted:OCPS-DR-003; OCPM:OCPM-DR-001 | F18: EV-O-0005 | G18: EV-O-0043; EV-O-0046
A19: OCPS-R1.2 | B19: Object-centric | C19: van2023object | D19: SUP-010 | E19: Adapted:OCPS-DR-003; OCPM:OCPM-DR-001 | F19: EV-O-0016
A20: OCPS-R1.2 | B20: Object-centric | C20: adams2025 | D20: SUP-011 | E20: Adapted:OCPS-DR-003; OCPM:OCPM-DR-001 | F20: EV-O-0017 | G20: EV-O-0053; EV-O-0058
A21: OCPS-R1.2 | B21: Object-centric | C21: esser2021multidimensional | D21: SUP-013 | E21: Adapted:OCPS-DR-003; OCPM:OCPM-DR-001 | F21: EV-O-0019 | G21: EV-O-0079
A22: OCPS-R1.2 | B22: Object-centric | C22: van2023toward | D22: SUP-006 | E22: Adapted:OCPS-DR-003; Direct:DATA-01; Direct:DATA-02 | F22: EV-AUD-0072 | G22: EV-AUD-0073; EV-AUD-0074; EV-AUD-0075; EV-O-0010; EV-O-0011; EV-O-0024; EV-O-0029; EV-O-0033; EV-O-0039; EV-O-0061; EV-O-0069; EV-O-0082
A23: OCPS-R1.2 | B23: Object-centric | C23: knopp2023discovering | D23: SUP-003 | E23: Adapted:OCPS-DR-003; Direct:DATA-01; Direct:DATA-02 | F23: EV-AUD-0056 | G23: EV-AUD-0005; EV-AUD-0006; EV-AUD-0015; EV-AUD-0020; EV-AUD-0021; EV-AUD-0027; EV-AUD-0032; EV-AUD-0033; EV-AUD-0034; EV-AUD-0035; EV-AUD-0039; EV-AUD-0057; EV-AUD-0058; EV-AUD-0059; EV-AUD-0060; EV-AUD-0061; EV-AUD-0062; EV-AUD-0063; EV-O-0006; EV-O-0032; EV-O-0034; EV-O-0037; EV-O-0048; EV-O-0051; EV-O-0054; EV-O-0056; EV-O-0063; EV-O-0064; EV-O-0066; EV-O-0067; EV-O-0068; EV-O-0072; EV-O-0073
A24: OCPS-R1.3 | B24: BPS/general | C24: van2010business | D24: FND-003 | E24: BPS:LR-CF1 | F24: EV-F-0002 | G24: EV-F-0006; EV-F-0009; EV-F-0035
A25: OCPS-R1.3 | B25: BPS/general | C25: van2015business | D25: FND-004 | E25: BPS:LR-CF1 | F25: EV-F-0004 | G25: EV-F-0012; EV-F-0024; EV-F-0028
A26: OCPS-R1.3 | B26: BPS/general | C26: dumas2018fundamentals | D26: FND-001 | E26: BPS:LR-CF1 | F26: EV-F-0003 | G26: EV-F-0007; TP-E011; TP-E012; TP-E013; TP-E014; TP-E014-B
A27: OCPS-R1.3 | B27: BPS/general | C27: martin2016use | D27: FND-002 | E27: BPS:LR-CF1; BPS:LR-DR1 | F27: EV-F-0005; EV-F-0013 | G27: EV-F-0008; EV-F-0011; EV-F-0015; EV-F-0017; EV-F-0019; EV-F-0021; EV-F-0025; EV-F-0026; EV-F-0029; EV-F-0030; EV-F-0032; R5-FE-002; R5-FE-012; R5-FE-015; R5-FE-025; R5-FE-030; R5-FE-053; R5-FE-058; R5-FE-065; R5-FE-066; R5-FE-072; R5-FE-074; TP-E015; TP-E016; TP-E017
A28: OCPS-R1.3 | B28: BPS/general | C28: jadric2020process | D28: BPS-034 | E28: BPS:LR-DR1 | F28: EV-S-0012 | G28: EV-S-0004; EV-S-0022; EV-S-0042
A29: OCPS-R1.3 | B29: BPS/general | C29: savickas2018approach | D29: BPS-038 | E29: BPS:LR-DR1 | F29: EV-S-0013 | G29: EV-S-0008
A30: OCPS-R1.3 | B30: BPS/general | C30: pourbafrani2022system | D30: BPS-012 | E30: BPS:LR-DR1 | F30: EV-S-0014
A31: OCPS-R1.3 | B31: BPS/general | C31: chapela2025simod | D31: BPS-013 | E31: BPS:LR-CF1 | F31: EV-S-0002 | G31: EV-AUD-0038; EV-AUD-0047; EV-AUD-0055; EV-S-0010; EV-S-0021; EV-S-0025; EV-S-0031; EV-S-0041; EV-S-0045; EV-S-0068; R5-FE-004; R5-FE-020; R5-FE-032; R5-FE-044; R5-FE-055; R5-FE-062; R5-FE-069; R5-FE-075; TP-E026; TP-E027; TP-E028
A32: OCPS-R1.3 | B32: BPS/general | C32: camargo2020automated | D32: BPS-030 | F32: EV-AUD-0064 | G32: EV-S-0006; EV-S-0011; EV-S-0020; EV-S-0030; EV-S-0040; EV-S-0052; EV-S-0054; EV-S-0058; R5-FE-003; R5-FE-019; R5-FE-035; R5-FE-042; R5-FE-060; TP-E018; TP-E019
A33: OCPS-R1.3 | B33: Object-centric | C33: berti2024ocel | D33: SUP-001 | E33: Direct:DATA-01; Direct:DATA-02; OCPM:OCPM-DR-001 | F33: EV-AUD-0003; EV-O-0002 | G33: EV-AUD-0001; EV-AUD-0002; EV-AUD-0004; EV-AUD-0007; EV-AUD-0008; EV-AUD-0009; EV-AUD-0012; EV-AUD-0014; EV-O-0003; EV-O-0004; EV-O-0036; EV-O-0042; EV-O-0045; EV-O-0049; EV-O-0052; EV-O-0055; EV-O-0057; EV-O-0076
A34: OCPS-R1.3 | B34: Object-centric | C34: fahland2024oced | D34: SUP-002 | E34: OCPM:OCPM-DR-001 | F34: EV-O-0005 | G34: EV-O-0043; EV-O-0046
A35: OCPS-R1.3 | B35: Object-centric | C35: van2023object | D35: SUP-010 | E35: OCPM:OCPM-DR-001 | F35: EV-O-0016
A36: OCPS-R1.3 | B36: Object-centric | C36: adams2025 | D36: SUP-011 | E36: OCPM:OCPM-DR-001 | F36: EV-O-0017 | G36: EV-O-0053; EV-O-0058
A37: OCPS-R1.3 | B37: Object-centric | C37: esser2021multidimensional | D37: SUP-013 | E37: OCPM:OCPM-DR-001 | F37: EV-O-0019 | G37: EV-O-0079
A38: OCPS-R1.3 | B38: Object-centric | C38: van2023toward | D38: SUP-006 | E38: Direct:DATA-01; Direct:DATA-02 | F38: EV-AUD-0073 | G38: EV-AUD-0072; EV-AUD-0074; EV-AUD-0075; EV-O-0010; EV-O-0011; EV-O-0024; EV-O-0029; EV-O-0033; EV-O-0039; EV-O-0061; EV-O-0069; EV-O-0082
A39: OCPS-R1.3 | B39: Object-centric | C39: knopp2023discovering | D39: SUP-003 | E39: Direct:DATA-01; Direct:DATA-02 | F39: EV-AUD-0057 | G39: EV-AUD-0005; EV-AUD-0006; EV-AUD-0015; EV-AUD-0020; EV-AUD-0021; EV-AUD-0027; EV-AUD-0032; EV-AUD-0033; EV-AUD-0034; EV-AUD-0035; EV-AUD-0039; EV-AUD-0056; EV-AUD-0058; EV-AUD-0059; EV-AUD-0060; EV-AUD-0061; EV-AUD-0062; EV-AUD-0063; EV-O-0006; EV-O-0032; EV-O-0034; EV-O-0037; EV-O-0048; EV-O-0051; EV-O-0054; EV-O-0056; EV-O-0063; EV-O-0064; EV-O-0066; EV-O-0067; EV-O-0068; EV-O-0072; EV-O-0073
A40: OCPS-R1.4 | B40: BPS/general | C40: van2010business | D40: FND-003 | E40: Adapted:OCPS-CF-005; BPS:LR-CF1 | F40: EV-F-0002 | G40: EV-F-0006; EV-F-0009; EV-F-0035
A41: OCPS-R1.4 | B41: BPS/general | C41: dumas2018fundamentals | D41: FND-001 | E41: Adapted:OCPS-CF-005; BPS:LR-CF1 | F41: EV-F-0003 | G41: EV-F-0007; TP-E011; TP-E012; TP-E013; TP-E014; TP-E014-B
A42: OCPS-R1.4 | B42: BPS/general | C42: van2015business | D42: FND-004 | E42: Adapted:OCPS-CF-005; BPS:LR-CF1 | F42: EV-F-0004 | G42: EV-F-0012; EV-F-0024; EV-F-0028
A43: OCPS-R1.4 | B43: BPS/general | C43: chapela2025simod | D43: BPS-013 | E43: Adapted:OCPS-CF-005; BPS:LR-CF1 | F43: EV-S-0002 | G43: EV-AUD-0038; EV-AUD-0047; EV-AUD-0055; EV-S-0010; EV-S-0021; EV-S-0025; EV-S-0031; EV-S-0041; EV-S-0045; EV-S-0068; R5-FE-004; R5-FE-020; R5-FE-032; R5-FE-044; R5-FE-055; R5-FE-062; R5-FE-069; R5-FE-075; TP-E026; TP-E027; TP-E028
A44: OCPS-R1.4 | B44: BPS/general | C44: martin2016use | D44: FND-002 | E44: Adapted:OCPS-CF-005; BPS:LR-CF1 | F44: EV-F-0005 | G44: EV-F-0008; EV-F-0011; EV-F-0013; EV-F-0015; EV-F-0017; EV-F-0019; EV-F-0021; EV-F-0025; EV-F-0026; EV-F-0029; EV-F-0030; EV-F-0032; R5-FE-002; R5-FE-012; R5-FE-015; R5-FE-025; R5-FE-030; R5-FE-053; R5-FE-058; R5-FE-065; R5-FE-066; R5-FE-072; R5-FE-074; TP-E015; TP-E016; TP-E017
A45: OCPS-R1.4 | B45: Object-centric | C45: berti2024ocel | D45: SUP-001 | E45: Adapted:OCPS-CF-005; Direct:DATA-06; OCPM:OCPM-CF-002 | F45: EV-AUD-0004; EV-O-0002 | G45: EV-AUD-0001; EV-AUD-0002; EV-AUD-0003; EV-AUD-0007; EV-AUD-0008; EV-AUD-0009; EV-AUD-0012; EV-AUD-0014; EV-O-0003; EV-O-0004; EV-O-0036; EV-O-0042; EV-O-0045; EV-O-0049; EV-O-0052; EV-O-0055; EV-O-0057; EV-O-0076
A46: OCPS-R1.4 | B46: Object-centric | C46: fahland2024oced | D46: SUP-002 | E46: Adapted:OCPS-CF-005; OCPM:OCPM-CF-002 | F46: EV-O-0005 | G46: EV-O-0043; EV-O-0046
A47: OCPS-R1.4 | B47: Object-centric | C47: knopp2023discovering | D47: SUP-003 | E47: Adapted:OCPS-CF-005; Direct:DATA-06; OCPM:OCPM-CF-002 | F47: EV-O-0006 | G47: EV-AUD-0005; EV-AUD-0006; EV-AUD-0015; EV-AUD-0020; EV-AUD-0021; EV-AUD-0027; EV-AUD-0032; EV-AUD-0033; EV-AUD-0034; EV-AUD-0035; EV-AUD-0039; EV-AUD-0056; EV-AUD-0057; EV-AUD-0058; EV-AUD-0059; EV-AUD-0060; EV-AUD-0061; EV-AUD-0062; EV-AUD-0063; EV-O-0032; EV-O-0034; EV-O-0037; EV-O-0048; EV-O-0051; EV-O-0054; EV-O-0056; EV-O-0063; EV-O-0064; EV-O-0066; EV-O-0067; EV-O-0068; EV-O-0072; EV-O-0073
... A61: OCPS-R1.5.1 | B61: Object-centric | C61: van2023toward | D61: SUP-006 | E61: OCPM:OCPM-CF-002 | F61: EV-O-0024 | G61: EV-AUD-0072; EV-AUD-0073; EV-AUD-0074; EV-AUD-0075; EV-O-0010; EV-O-0011; EV-O-0029; EV-O-0033; EV-O-0039; EV-O-0061; EV-O-0069; EV-O-0082
A62: OCPS-R1.5.1 | B62: Object-centric | C62: van2023object | D62: SUP-010 | E62: OCPM:OCPM-DR-001 | F62: EV-O-0016
A63: OCPS-R1.5.1 | B63: Object-centric | C63: adams2025 | D63: SUP-011 | E63: OCPM:OCPM-DR-001 | F63: EV-O-0017 | G63: EV-O-0053; EV-O-0058
A64: OCPS-R1.5.1 | B64: Object-centric | C64: esser2021multidimensional | D64: SUP-013 | E64: OCPM:OCPM-DR-001 | F64: EV-O-0019 | G64: EV-O-0079
A65: OCPS-R1.5.2 | B65: BPS/general | C65: van2010business | D65: FND-003 | E65: BPS:LR-CF1 | F65: EV-F-0002 | G65: EV-F-0006; EV-F-0009; EV-F-0035
A66: OCPS-R1.5.2 | B66: BPS/general | C66: dumas2018fundamentals | D66: FND-001 | E66: BPS:LR-CF1 | F66: EV-F-0003 | G66: EV-F-0007; TP-E011; TP-E012; TP-E013; TP-E014; TP-E014-B
A67: OCPS-R1.5.2 | B67: BPS/general | C67: van2015business | D67: FND-004 | E67: BPS:LR-CF1 | F67: EV-F-0004 | G67: EV-F-0012; EV-F-0024; EV-F-0028
A68: OCPS-R1.5.2 | B68: BPS/general | C68: chapela2025simod | D68: BPS-013 | E68: BPS:LR-CF1 | F68: EV-S-0002 | G68: EV-AUD-0038; EV-AUD-0047; EV-AUD-0055; EV-S-0010; EV-S-0021; EV-S-0025; EV-S-0031; EV-S-0041; EV-S-0045; EV-S-0068; R5-FE-004; R5-FE-020; R5-FE-032; R5-FE-044; R5-FE-055; R5-FE-062; R5-FE-069; R5-FE-075; TP-E026; TP-E027; TP-E028
A69: OCPS-R1.5.2 | B69: BPS/general | C69: martin2016use | D69: FND-002 | E69: BPS:LR-CF1 | F69: EV-F-0005 | G69: EV-F-0008; EV-F-0011; EV-F-0013; EV-F-0015; EV-F-0017; EV-F-0019; EV-F-0021; EV-F-0025; EV-F-0026; EV-F-0029; EV-F-0030; EV-F-0032; R5-FE-002; R5-FE-012; R5-FE-015; R5-FE-025; R5-FE-030; R5-FE-053; R5-FE-058; R5-FE-065; R5-FE-066; R5-FE-072; R5-FE-074; TP-E015; TP-E016; TP-E017
A70: OCPS-R1.5.2 | B70: Object-centric | C70: berti2024ocel | D70: SUP-001 | E70: OCPM:OCPM-CF-002; OCPM:OCPM-DR-001 | F70: EV-O-0002 | G70: EV-AUD-0001; EV-AUD-0002; EV-AUD-0003; EV-AUD-0004; EV-AUD-0007; EV-AUD-0008; EV-AUD-0009; EV-AUD-0012; EV-AUD-0014; EV-O-0003; EV-O-0004; EV-O-0036; EV-O-0042; EV-O-0045; EV-O-0049; EV-O-0052; EV-O-0055; EV-O-0057; EV-O-0076
A71: OCPS-R1.5.2 | B71: Object-centric | C71: fahland2024oced | D71: SUP-002 | E71: OCPM:OCPM-CF-002; OCPM:OCPM-DR-001 | F71: EV-O-0005 | G71: EV-O-0043; EV-O-0046
A72: OCPS-R1.5.2 | B72: Object-centric | C72: knopp2023discovering | D72: SUP-003 | E72: Direct:BIND-01.2; OCPM:OCPM-CF-002 | F72: EV-AUD-0006; EV-O-0006 | G72: EV-AUD-0005; EV-AUD-0015; EV-AUD-0020; EV-AUD-0021; EV-AUD-0027; EV-AUD-0032; EV-AUD-0033; EV-AUD-0034; EV-AUD-0035; EV-AUD-0039; EV-AUD-0056; EV-AUD-0057; EV-AUD-0058; EV-AUD-0059; EV-AUD-0060; EV-AUD-0061; EV-AUD-0062; EV-AUD-0063; EV-O-0032; EV-O-0034; EV-O-0037; EV-O-0048; EV-O-0051; EV-O-0054; EV-O-0056; EV-O-0063; EV-O-0064; EV-O-0066; EV-O-0067; EV-O-0068; EV-O-0072; EV-O-0073
A73: OCPS-R1.5.2 | B73: Object-centric | C73: van2020discovering | D73: SUP-004 | E73: OCPM:OCPM-CF-002 | F73: EV-O-0008 | G73: EV-AUD-0022; EV-AUD-0023; EV-AUD-0024; EV-AUD-0025; EV-AUD-0026; EV-O-0007; EV-O-0025; EV-O-0028; EV-O-0031; EV-O-0040
A74: OCPS-R1.5.2 | B74: Object-centric | C74: knopp2023towards | D74: SUP-007 | E74: OCPM:OCPM-CF-002 | F74: EV-O-0023 | G74: EV-AUD-0016; EV-AUD-0017; EV-AUD-0018; EV-AUD-0019; EV-AUD-0031; EV-AUD-0037; EV-O-0012; EV-O-0020; EV-O-0021; EV-O-0022; EV-O-0035; EV-O-0038; EV-O-0062; EV-O-0070; EV-O-0071; EV-O-0074; EV-O-0080; EV-O-0083
A75: OCPS-R1.5.2 | B75: Object-centric | C75: van2023toward | D75: SUP-006 | E75: OCPM:OCPM-CF-002 | F75: EV-O-0024 | G75: EV-AUD-0072; EV-AUD-0073; EV-AUD-0074; EV-AUD-0075; EV-O-0010; EV-O-0011; EV-O-0029; EV-O-0033; EV-O-0039; EV-O-0061; EV-O-0069; EV-O-0082
A76: OCPS-R1.5.2 | B76: Object-centric | C76: van2023object | D76: SUP-010 | E76: OCPM:OCPM-DR-001 | F76: EV-O-0016
A77: OCPS-R1.5.2 | B77: Object-centric | C77: adams2025 | D77: SUP-011 | E77: OCPM:OCPM-DR-001 | F77: EV-O-0017 | G77: EV-O-0053; EV-O-0058
A78: OCPS-R1.5.2 | B78: Object-centric | C78: esser2021multidimensional | D78: SUP-013 | E78: OCPM:OCPM-DR-001 | F78: EV-O-0019 | G78: EV-O-0079
A79: OCPS-R1.6 | B79: BPS/general | C79: martin2016use | D79: FND-002 | E79: Adapted:OCPS-CF-007; BPS:LR-DR1 | F79: EV-F-0013 | G79: EV-F-0005; EV-F-0008; EV-F-0011; EV-F-0015; EV-F-0017; EV-F-0019; EV-F-0021; EV-F-0025; EV-F-0026; EV-F-0029; EV-F-0030; EV-F-0032; R5-FE-002; R5-FE-012; R5-FE-015; R5-FE-025; R5-FE-030; R5-FE-053; R5-FE-058; R5-FE-065; R5-FE-066; R5-FE-072; R5-FE-074; TP-E015; TP-E016; TP-E017
A80: OCPS-R1.6 | B80: BPS/general | C80: jadric2020process | D80: BPS-034 | E80: Adapted:OCPS-CF-007; BPS:LR-DR1 | F80: EV-S-0012 | G80: EV-S-0004; EV-S-0022; EV-S-0042
A81: OCPS-R1.6 | B81: BPS/general | C81: savickas2018approach | D81: BPS-038 | E81: Adapted:OCPS-CF-007; BPS:LR-DR1 | F81: EV-S-0013 | G81: EV-S-0008
A82: OCPS-R1.6 | B82: BPS/general | C82: pourbafrani2022system | D82: BPS-012 | E82: Adapted:OCPS-CF-007; BPS:LR-DR1 | F82: EV-S-0014
A83: OCPS-R1.6 | B83: Object-centric | C83: berti2024ocel | D83: SUP-001 | E83: Adapted:OCPS-CF-007; OCPM:OCPM-CF-002; OCPM:OCPM-DR-001 | F83: EV-AUD-0007; EV-O-0002 | G83: EV-AUD-0001; EV-AUD-0002; EV-AUD-0003; EV-AUD-0004; EV-AUD-0008; EV-AUD-0009; EV-AUD-0012; EV-AUD-0014; EV-O-0003; EV-O-0004; EV-O-0036; EV-O-0042; EV-O-0045; EV-O-0049; EV-O-0052; EV-O-0055; EV-O-0057; EV-O-0076
A84: OCPS-R1.6 | B84: Object-centric | C84: fahland2024oced | D84: SUP-002 | E84: Adapted:OCPS-CF-007; OCPM:OCPM-CF-002; OCPM:OCPM-DR-001 | F84: EV-O-0005 | G84: EV-O-0043; EV-O-0046
A85: OCPS-R1.6 | B85: Object-centric | C85: van2023object | D85: SUP-010 | E85: Adapted:OCPS-CF-007; OCPM:OCPM-DR-001 | F85: EV-O-0016
A86: OCPS-R1.6 | B86: Object-centric | C86: adams2025 | D86: SUP-011 | E86: Adapted:OCPS-CF-007; OCPM:OCPM-DR-001 | F86: EV-O-0017 | G86: EV-O-0053; EV-O-0058
A87: OCPS-R1.6 | B87: Object-centric | C87: esser2021multidimensional | D87: SUP-013 | E87: Adapted:OCPS-CF-007; OCPM:OCPM-DR-001 | F87: EV-O-0019 | G87: EV-O-0079
A88: OCPS-R1.6 | B88: Object-centric | C88: knopp2023discovering | D88: SUP-003 | E88: Adapted:OCPS-CF-007; OCPM:OCPM-CF-002 | F88: EV-O-0006 | G88: EV-AUD-0005; EV-AUD-0006; EV-AUD-0015; EV-AUD-0020; EV-AUD-0021; EV-AUD-0027; EV-AUD-0032; EV-AUD-0033; EV-AUD-0034; EV-AUD-0035; EV-AUD-0039; EV-AUD-0056; EV-AUD-0057; EV-AUD-0058; EV-AUD-0059; EV-AUD-0060; EV-AUD-0061; EV-AUD-0062; EV-AUD-0063; EV-O-0032; EV-O-0034; EV-O-0037; EV-O-0048; EV-O-0051; EV-O-0054; EV-O-0056; EV-O-0063; EV-O-0064; EV-O-0066; EV-O-0067; EV-O-0068; EV-O-0072; EV-O-0073
A89: OCPS-R1.6 | B89: Object-centric | C89: van2020discovering | D89: SUP-004 | E89: Adapted:OCPS-CF-007; OCPM:OCPM-CF-002 | F89: EV-O-0008 | G89: EV-AUD-0022; EV-AUD-0023; EV-AUD-0024; EV-AUD-0025; EV-AUD-0026; EV-O-0007; EV-O-0025; EV-O-0028; EV-O-0031; EV-O-0040
A90: OCPS-R1.6 | B90: Object-centric | C90: knopp2023towards | D90: SUP-007 | E90: Adapted:OCPS-CF-007; OCPM:OCPM-CF-002 | F90: EV-O-0023 | G90: EV-AUD-0016; EV-AUD-0017; EV-AUD-0018; EV-AUD-0019; EV-AUD-0031; EV-AUD-0037; EV-O-0012; EV-O-0020; EV-O-0021; EV-O-0022; EV-O-0035; EV-O-0038; EV-O-0062; EV-O-0070; EV-O-0071; EV-O-0074; EV-O-0080; EV-O-0083
A91: OCPS-R1.6 | B91: Object-centric | C91: van2023toward | D91: SUP-006 | E91: Adapted:OCPS-CF-007; OCPM:OCPM-CF-002 | F91: EV-O-0024 | G91: EV-AUD-0072; EV-AUD-0073; EV-AUD-0074; EV-AUD-0075; EV-O-0010; EV-O-0011; EV-O-0029; EV-O-0033; EV-O-0039; EV-O-0061; EV-O-0069; EV-O-0082
A92: OCPS-R1.7.1 | B92: BPS/general | C92: martin2016use | D92: FND-002 | E92: BPS:LR-DR1 | F92: EV-F-0013 | G92: EV-F-0005; EV-F-0008; EV-F-0011; EV-F-0015; EV-F-0017; EV-F-0019; EV-F-0021; EV-F-0025; EV-F-0026; EV-F-0029; EV-F-0030; EV-F-0032; R5-FE-002; R5-FE-012; R5-FE-015; R5-FE-025; R5-FE-030; R5-FE-053; R5-FE-058; R5-FE-065; R5-FE-066; R5-FE-072; R5-FE-074; TP-E015; TP-E016; TP-E017
A93: OCPS-R1.7.1 | B93: BPS/general | C93: jadric2020process | D93: BPS-034 | E93: BPS:LR-DR1 | F93: EV-S-0012 | G93: EV-S-0004; EV-S-0022; EV-S-0042
A94: OCPS-R1.7.1 | B94: BPS/general | C94: savickas2018approach | D94: BPS-038 | E94: BPS:LR-DR1 | F94: EV-S-0013 | G94: EV-S-0008
A95: OCPS-R1.7.1 | B95: BPS/general | C95: pourbafrani2022system | D95: BPS-012 | E95: BPS:LR-DR1 | F95: EV-S-0014
A96: OCPS-R1.7.1 | B96: Object-centric | C96: berti2024ocel | D96: SUP-001 | E96: OCPM:OCPM-DR-001 | F96: EV-AUD-0008; EV-O-0002 | G96: EV-AUD-0001; EV-AUD-0002; EV-AUD-0003; EV-AUD-0004; EV-AUD-0007; EV-AUD-0009; EV-AUD-0012; EV-AUD-0014; EV-O-0003; EV-O-0004; EV-O-0036; EV-O-0042; EV-O-0045; EV-O-0049; EV-O-0052; EV-O-0055; EV-O-0057; EV-O-0076
A97: OCPS-R1.7.1 | B97: Object-centric | C97: fahland2024oced | D97: SUP-002 | E97: OCPM:OCPM-DR-001 | F97: EV-O-0005 | G97: EV-O-0043; EV-O-0046
A98: OCPS-R1.7.1 | B98: Object-centric | C98: van2023object | D98: SUP-010 | E98: OCPM:OCPM-DR-001 | F98: EV-O-0016
A99: OCPS-R1.7.1 | B99: Object-centric | C99: adams2025 | D99: SUP-011 | E99: OCPM:OCPM-DR-001 | F99: EV-O-0017 | G99: EV-O-0053; EV-O-0058
A100: OCPS-R1.7.1 | B100: Object-centric | C100: esser2021multidimensional | D100: SUP-013 | E100: OCPM:OCPM-DR-001 | F100: EV-O-0019 | G100: EV-O-0079
A101: OCPS-R1.7.2 | B101: BPS/general | C101: martin2016use | D101: FND-002 | E101: Adapted:OCPS-DR-002; BPS:LR-DR1 | F101: EV-F-0013 | G101: EV-F-0005; EV-F-0008; EV-F-0011; EV-F-0015; EV-F-0017; EV-F-0019; EV-F-0021; EV-F-0025; EV-F-0026; EV-F-0029; EV-F-0030; EV-F-0032; R5-FE-002; R5-FE-012; R5-FE-015; R5-FE-025; R5-FE-030; R5-FE-053; R5-FE-058; R5-FE-065; R5-FE-066; R5-FE-072; R5-FE-074; TP-E015; TP-E016; TP-E017
A102: OCPS-R1.7.2 | B102: BPS/general | C102: jadric2020process | D102: BPS-034 | E102: Adapted:OCPS-DR-002; BPS:LR-DR1 | F102: EV-S-0012 | G102: EV-S-0004; EV-S-0022; EV-S-0042
A103: OCPS-R1.7.2 | B103: BPS/general | C103: savickas2018approach | D103: BPS-038 | E103: Adapted:OCPS-DR-002; BPS:LR-DR1 | F103: EV-S-0013 | G103: EV-S-0008
A104: OCPS-R1.7.2 | B104: BPS/general | C104: pourbafrani2022system | D104: BPS-012 | E104: Adapted:OCPS-DR-002; BPS:LR-DR1 | F104: EV-S-0014
A105: OCPS-R1.7.2 | B105: Object-centric | C105: berti2024ocel | D105: SUP-001 | E105: Adapted:OCPS-DR-002; Adapted:OCPS-DR-004; OCPM:OCPM-DR-001; OCPM:OCPM-DR-003 | F105: EV-AUD-0009; EV-O-0002; EV-O-0004 | G105: EV-AUD-0001; EV-AUD-0002; EV-AUD-0003; EV-AUD-0004; EV-AUD-0007; EV-AUD-0008; EV-AUD-0012; EV-AUD-0014; EV-O-0003; EV-O-0036; EV-O-0042; EV-O-0045; EV-O-0049; EV-O-0052; EV-O-0055; EV-O-0057; EV-O-0076
A106: OCPS-R1.7.2 | B106: Object-centric | C106: fahland2024oced | D106: SUP-002 | E106: Adapted:OCPS-DR-002; Adapted:OCPS-DR-004; OCPM:OCPM-DR-001 | F106: EV-O-0005 | G106: EV-O-0043; EV-O-0046
A107: OCPS-R1.7.2 | B107: Object-centric | C107: van2023object | D107: SUP-010 | E107: Adapted:OCPS-DR-002; OCPM:OCPM-DR-001 | F107: EV-O-0016
A108: OCPS-R1.7.2 | B108: Object-centric | C108: adams2025 | D108: SUP-011 | E108: Adapted:OCPS-DR-002; OCPM:OCPM-DR-001; OCPM:OCPM-DR-003 | F108: EV-O-0017 | G108: EV-O-0053; EV-O-0058
A109: OCPS-R1.7.2 | B109: Object-centric | C109: esser2021multidimensional | D109: SUP-013 | E109: Adapted:OCPS-DR-002; OCPM:OCPM-DR-001; OCPM:OCPM-DR-003 | F109: EV-O-0019 | G109: EV-O-0079
A110: OCPS-R1.7.2 | B110: Object-centric | C110: wei2025dirigo | D110: SUP-008 | E110: OCPM:OCPM-DR-001; OCPM:OCPM-DR-003 | F110: EV-O-0013; EV-O-0014 | G110: EV-AUD-0011; EV-O-0077
A111: OCPS-R1.7.2 | B111: Object-centric | C111: kretzschmann2026stateaware | D111: SUP-009 | E111: OCPM:OCPM-DR-003 | F111: EV-O-0015 | G111: EV-AUD-0013; EV-O-0078
A112: OCPS-R1.7.2 | B112: Object-centric | C112: knopp2023discovering | D112: SUP-003 | E112: Adapted:OCPS-DR-004; Direct:DATA-04 | F112: EV-AUD-0058 | G112: EV-AUD-0005; EV-AUD-0006; EV-AUD-0015; EV-AUD-0020; EV-AUD-0021; EV-AUD-0027; EV-AUD-0032; EV-AUD-0033; EV-AUD-0034; EV-AUD-0035; EV-AUD-0039; EV-AUD-0056; EV-AUD-0057; EV-AUD-0059; EV-AUD-0060; EV-AUD-0061; EV-AUD-0062; EV-AUD-0063; EV-O-0006; EV-O-0032; EV-O-0034; EV-O-0037; EV-O-0048; EV-O-0051; EV-O-0054; EV-O-0056; EV-O-0063; EV-O-0064; EV-O-0066; EV-O-0067; EV-O-0068; EV-O-0072; EV-O-0073
A113: OCPS-R1.8 | B113: BPS/general | C113: martin2016use | D113: FND-002 | E113: Adapted:OCPS-DR-008; BPS:LR-DR1 | F113: EV-F-0013 | G113: EV-F-0005; EV-F-0008; EV-F-0011; EV-F-0015; EV-F-0017; EV-F-0019; EV-F-0021; EV-F-0025; EV-F-0026; EV-F-0029; EV-F-0030; EV-F-0032; R5-FE-002; R5-FE-012; R5-FE-015; R5-FE-025; R5-FE-030; R5-FE-053; R5-FE-058; R5-FE-065; R5-FE-066; R5-FE-072; R5-FE-074; TP-E015; TP-E016; TP-E017
...

Sheet Catalogue
A1: Requirement ID | B1: Parent ID | C1: Hierarchy level | D1: Perspective | E1: Class | F1: Normative statement | G1: Description / acceptance criterion | H1: Synthesis rationale | I1: Candidate nodes | J1: BPS/general citation keys | K1: Object-centric citation keys
A2: OCPS-R1 | C2: Parent | D2: Data/rules | F2: The OCPS simulation model shall represent the object-centric event-data structure needed for simulation. | G2: This parent groups the data requirements needed to distinguish event types, object types, object instances, attributes, event-object bindings, and object-object relations. | H2: Created as a hierarchy parent to avoid repeating the same OCED/OCEL foundation in every child. | I2: Adapted:OCPS-DR-001; Direct:DATA-01; Direct:DATA-02; Direct:DATA-03
A3: OCPS-R1.1 | B3: OCPS-R1 | C3: Atomic child | D3: Data/rules | E3: M | F3: The OCPS model shall explicitly define the event types to be simulated. | G3: Each simulated event occurrence can be assigned to exactly one defined event type or activity label. | H3: Merged the case-centric activity requirement with OCEL/OCED event-type terminology. | I3: Adapted:OCPS-CF-001; BPS:LR-CF1; OCPM:OCPM-DR-001 | J3: FND-003; FND-001; FND-004; BPS-013; FND-002 | K3: SUP-001; SUP-002; SUP-010; SUP-011; SUP-013
A4: OCPS-R1.2 | B4: OCPS-R1 | C4: Atomic child | D4: Data/rules | E4: M | F4: The OCPS model shall define the object types to be simulated. | G4: The requirement is satisfied if each simulated object type has a unique name and all event-object relations, object-object relations, generation rules, and activity bindings refer only to defined object types. | H4: Object-type definitions are specified here; object-instance identity is specified separately in OCPS-R1.3. | I4: Adapted:OCPS-DR-003; BPS:LR-CF1; Direct:DATA-01; Direct:DATA-02; OCPM:OCPM-DR-001 | J4: FND-003; FND-001; FND-004; BPS-013; FND-002 | K4: SUP-001; SUP-002; SUP-010; SUP-011; SUP-013; SUP-006; SUP-003
A5: OCPS-R1.3 | B5: OCPS-R1 | C5: Atomic child | D5: Data/rules | E5: M | F5: The OCPS model shall assign and preserve an identifier and object type for each generated object instance. | G5: Each generated object instance must have a unique identifier and exactly one defined object type, both preserved in the simulation state and generated OCED/OCEL output. | I5: BPS:LR-CF1; BPS:LR-DR1; Direct:DATA-01; Direct:DATA-02; OCPM:OCPM-DR-001 | J5: FND-003; FND-004; FND-001; FND-002; BPS-034; BPS-038; BPS-012; BPS-013; BPS-030 | K5: SUP-001; SUP-002; SUP-010; SUP-011; SUP-013; SUP-006; SUP-003
A6: OCPS-R1.4 | B6: OCPS-R1 | C6: Atomic child | D6: Data/rules | E6: M | F6: The OCPS model shall relate each simulated event occurrence to its participating object instance(s). | G6: Each generated event relates to the object set involved in that event so that the event can later be interpreted as an event-to-object relation. | H6: Retained as the event-to-object association requirement. Activity preconditions and object generation are specified separately under R3.4 and R2.1. | I6: Adapted:OCPS-CF-005; BPS:LR-CF1; Direct:DATA-06; OCPM:OCPM-CF-002 | J6: FND-003; FND-001; FND-004; BPS-013; FND-002 | K6: SUP-001; SUP-002; SUP-003; SUP-004; SUP-007; SUP-006
A7: OCPS-R1.5 | B7: OCPS-R1 | C7: Parent/decomposed | D7: Data/rules | F7: The OCPS simulation model shall define the object participation requirements for each event type. | G7: For each event type, the model states which object types may or must participate and the required number or range of objects when cardinality matters. | H7: Merged eligible object-type and cardinality requirements; separated from runtime binding selection to avoid redundancy. | I7: Adapted:OCPS-CF-006; BPS:LR-CF1; Direct:BIND-01.1; Direct:BIND-01.2; OCPM:OCPM-CF-002; OCPM:OCPM-DR-001
A8: OCPS-R1.5.1 | B8: OCPS-R1.5 | C8: Atomic child | D8: Data/rules | E8: M | F8: The OCPS model shall define the participating object types for each event type. | G8: For each event type, the specification identifies required and outcome-dependent participating object types. It distinguishes objects required before execution from objects created by the activity; both may appear in the resulting event-to-object relations. | I8: BPS:LR-CF1; Direct:BIND-01.1; OCPM:OCPM-CF-002; OCPM:OCPM-DR-001 | J8: FND-003; FND-001; FND-004; BPS-013; FND-002 | K8: SUP-001; SUP-002; SUP-003; SUP-004; SUP-007; SUP-006; SUP-010; SUP-011; SUP-013
A9: OCPS-R1.5.2 | B9: OCPS-R1.5 | C9: Atomic child | D9: Data/rules | E9: C | F9: For each event type subject to an object-participation cardinality constraint, the OCPS model shall specify the applicable cardinality. | G9: For each constrained event type, the specification gives the minimum, maximum, or exact number of instances per participating object type and role. It states whether the constraint applies before execution or to the resulting event participation, including outcome-dependent participation. | I9: BPS:LR-CF1; Direct:BIND-01.2; OCPM:OCPM-CF-002; OCPM:OCPM-DR-001 | J9: FND-003; FND-001; FND-004; BPS-013; FND-002 | K9: SUP-001; SUP-002; SUP-003; SUP-004; SUP-007; SUP-006; SUP-010; SUP-011; SUP-013
A10: OCPS-R1.6 | B10: OCPS-R1 | C10: Atomic child | D10: Data/rules | E10: C | F10: If different object roles are possible for an event-to-object binding, the OCPS simulation model shall specify the applicable qualifier or role. | G10: Where role distinctions are needed, each event-to-object binding has a defined role, such as prerequisite, created, updated, consumed, or resource. The role distinguishes pre-existing participants from objects produced by execution when this affects enablement or interpretation. | H10: Kept as a conditional child because qualifiers are not needed for every event-object relation. | I10: Adapted:OCPS-CF-007; BPS:LR-DR1; OCPM:OCPM-CF-002; OCPM:OCPM-DR-001 | J10: FND-002; BPS-034; BPS-038; BPS-012 | K10: SUP-001; SUP-002; SUP-010; SUP-011; SUP-013; SUP-003; SUP-004; SUP-007; SUP-006
A11: OCPS-R1.7 | B11: OCPS-R1 | C11: Parent/decomposed | D11: Data/rules | F11: The OCPS simulation model shall define value domains for behaviour-relevant event and object attributes. | G11: This parent groups requirements for specifying possible values of event attributes and object attributes that affect simulated behaviour or analysis.
A12: OCPS-R1.7.1 | B12: OCPS-R1.7 | C12: Atomic child | D12: Data/rules | E12: C | F12: For each event attribute referenced by simulation logic or analysis rules, the OCPS model shall specify an allowed value domain. | G12: The requirement is satisfied if every event attribute referenced by simulation logic or analysis rules has a defined data type and, where applicable, an explicit set or range of permitted values. | I12: BPS:LR-DR1; OCPM:OCPM-DR-001 | J12: FND-002; BPS-034; BPS-038; BPS-012 | K12: SUP-001; SUP-002; SUP-010; SUP-011; SUP-013
A13: OCPS-R1.7.2 | B13: OCPS-R1.7 | C13: Atomic child | D13: Data/rules | E13: C | F13: For each object attribute referenced by simulation logic or analysis rules, the OCPS model shall specify an allowed value domain. | G13: The requirement is satisfied if each object attribute referenced by simulation logic or analysis rules has a defined data type and, where applicable, an explicit set or range of permitted values. | H13: Kept separate from event attributes following the OCEL distinction between event and object attributes. | I13: Adapted:OCPS-DR-002; Adapted:OCPS-DR-004; BPS:LR-DR1; Direct:DATA-04; OCPM:OCPM-DR-001; OCPM:OCPM-DR-003 | J13: FND-002; BPS-034; BPS-038; BPS-012 | K13: SUP-001; SUP-002; SUP-010; SUP-011; SUP-013; SUP-008; SUP-009; SUP-003
A14: OCPS-R1.8 | B14: OCPS-R1 | C14: Atomic child | D14: Data/rules | E14: C | F14: For each object-to-object relation required by simulation behaviour or analysis, the OCPS model shall define its meaning and permitted source and target object types. | G14: Each required relation has a defined meaning and source and target object types. Links between object instances can be stored and referenced according to that definition. Rules for creating, modifying, or terminating links are specified under R1.8.1. | H14: Relation definitions and instance links are specified here; dynamic relation-change rules refine this requirement under R1.8.1. | I14: Adapted:OCPS-DR-008; Adapted:OCPS-DR-009; BPS:LR-DR1; Direct:DATA-03; Direct:STATE-02; OCPM:OCPM-DR-002 | J14: FND-002; BPS-034; BPS-038; BPS-012 | K14: SUP-001; BPS-018; BPS-037; SUP-008; SUP-013; SUP-007; SUP-003; SUP-006
A15: OCPS-R1.8.1 | B15: OCPS-R1.8 | C15: Atomic child | D15: Data/rules | E15: C | F15: For each object-to-object relation that may change during simulation, the OCPS model shall specify the rule governing its creation, modification, or termination. | G15: The requirement is satisfied if each dynamic object-to-object relation in the declared simulation scope identifies the affected object types or instances, the applicable creation, modification or termination operation, its triggering event, lifecycle stage or condition, and the resulting relation state and time of effect. The rule must make clear when the relation is expected to hold before and after the change; only operations applicable to that relation are required. | H15: Retained as a conditional relation-change requirement. Applicability follows the simulation scope, not implementation difficulty. | I15: Adapted:OCPS-DR-010; OCPM:OCPM-DR-002; OCPM:OCPM-DR-003 | K15: SUP-001; SUP-008; SUP-009; SUP-013; BPS-018; BPS-037; SUP-007
A16: OCPS-R1.9 | B16: OCPS-R1 | C16: Parent/decomposed | D16: Data/rules | F16: The OCPS simulation model shall represent dynamic object state and attribute values relevant to simulation behaviour or analysis. | G16: This parent groups requirements for current object state/value, object state transitions, and time-dependent object attribute values. | H16: Added parent node to group dynamic object-state/value requirements. | I16: BPS:LR-CF3; BPS:LR-DR1; Direct:DATA-04; Direct:DATA-05; OCPM:OCPM-DR-003
A17: OCPS-R1.9.1 | B17: OCPS-R1.9 | C17: Atomic child | D17: Data/rules | E17: C | F17: For each object state or object attribute referenced by simulation logic or required output analysis, the OCPS model shall maintain its current value for each applicable object instance. | G17: Current object state and attribute values used as data can be retrieved by routing, timing, binding, generation, or output logic. Object control-flow positions used for execution enablement are specified separately under R3.2. | H17: Merged object state and state variable requirements while keeping state updates separate. | I17: Adapted:OCPS-DR-004; Adapted:OCPS-DR-006; BPS:LR-CF3; BPS:LR-DR1; Direct:DATA-04; OCPM:OCPM-DR-003 | J17: FND-003; BPS-006; FND-006; FND-002; FND-004; BPS-038; BPS-042; BPS-013; BPS-030; BPS-034; BPS-012 | K17: SUP-001; SUP-008; SUP-009; SUP-013; SUP-003
A18: OCPS-R1.9.2 | B18: OCPS-R1.9 | C18: Atomic child | D18: Data/rules | E18: C | F18: For each modelled object-state transition, the OCPS model shall specify the affected object type, source state, target state, and triggering event or condition. | G18: The requirement is satisfied if each object-state transition identifies the applicable object instances, the state before the transition, the state after the transition, and the event or condition that causes the transition. | H18: Merged state update and timestamped state-transition requirements. | I18: Adapted:OCPS-DR-007; BPS:LR-CF3; BPS:LR-DR1; Direct:DATA-05; OCPM:OCPM-DR-003 | J18: FND-003; BPS-006; FND-006; FND-002; FND-004; BPS-038; BPS-042; BPS-013; BPS-030; BPS-034; BPS-012 | K18: SUP-001; SUP-008; SUP-009; SUP-013; SUP-003
A19: OCPS-R1.9.3 | B19: OCPS-R1.9 | C19: Atomic child | D19: Data/rules | E19: C | F19: For each object attribute whose value may change during simulation, the OCPS model shall represent its value changes over simulation time. | G19: The requirement is satisfied if each object-attribute value change identifies the affected object instance, the attribute definition, the resulting value, and the simulation time or validity interval for which that value applies. | H19: Kept separate from object state transitions because attribute values and state variables may be modeled differently. | I19: Adapted:OCPS-DR-005; BPS:LR-CF3; BPS:LR-DR1; OCPM:OCPM-DR-003 | J19: FND-003; BPS-006; FND-006; FND-002; FND-004; BPS-038; BPS-042; BPS-013; BPS-030; BPS-034; BPS-012 | K19: SUP-001; SUP-008; SUP-009; SUP-013
A20: OCPS-R2 | C20: Parent | D20: Data/rules; Temporal/stochastic | F20: The OCPS simulation model shall define object-generation rules for simulated object types. | G20: This parent groups requirements that create objects or related object sets and define when they enter the simulation. | H20: Created to separate generation/arrival from control-flow execution. | I20: Adapted:OCPS-DR-011; Adapted:OCPS-TS-001; Direct:ARR-01; Direct:OG-01
A21: OCPS-R2.1 | B21: OCPS-R2 | C21: Parent/decomposed | D21: Data/rules | F21: The OCPS simulation model shall define object-generation rules for simulated object types and related object sets. | G21: This parent groups requirements for generating object instances, related object sets, and data-dependent object generation outcomes. | H21: Added parent node because the existing R2.1.x rows are all object-generation rule variants. | I21: BPS:LR-TS1; Direct:OG-01; Direct:OG-01.1; Direct:OG-01.2; Direct:OG-01.3; Direct:OG-01.4; OCPM:OCPM-DR-004
A22: OCPS-R2.1.1 | B22: OCPS-R2.1 | C22: Atomic child | D22: Data/rules | E22: M | F22: The OCPS model shall specify object-generation rules for each simulated object type. | G22: For each object type in scope, the model defines how object instances are created or introduced. | I22: Adapted:OCPS-DR-011; Direct:OG-01; OCPM:OCPM-DR-004 | K22: SUP-003; SUP-006; SUP-007
A23: OCPS-R2.1.2 | B23: OCPS-R2.1 | C23: Atomic child | D23: Data/rules | E23: C | F23: The OCPS model shall generate related object sets according to modelled object relationship multiplicities. | G23: When the simulation creates a set of related objects, the generated objects must satisfy the modeled object-to-object relationship multiplicities. | H23: Reformulated 'parameterizable generation of related objects' into a clearer multiplicity-based requirement. | I23: Adapted:OCPS-DR-012; Direct:OG-01.1; OCPM:OCPM-DR-004 | K23: SUP-003; SUP-006; SUP-007; SUP-001; BPS-018; BPS-037; SUP-008; SUP-013
A24: OCPS-R2.1.3 | B24: OCPS-R2.1 | C24: Atomic child | D24: Data/rules | E24: C | F24: If an object attribute determines how many related objects are generated, the OCPS model shall use that attribute to calculate the number of related objects to generate. | G24: The requirement is satisfied if the object-generation rule identifies the object attribute used and defines how its value determines or constrains the number of related objects generated. For example, an order attribute may determine or constrain the number of item objects generated with the order. | H24: Kept separate to avoid overloading the general generation rule with data-dependent quantity logic. | I24: Direct:OG-01.2 | K24: SUP-007
A25: OCPS-R2.1.4 | B25: OCPS-R2.1 | C25: Atomic child | D25: Data/rules | E25: C | F25: If object attributes determine which object-to-object relations are generated, the OCPS model shall use those attributes as input to the relation-generation rule. | G25: The requirement is satisfied if the relation-generation rule identifies the object attributes used and defines how their values determine which object-to-object relations are generated. These attributes may include product type, customer type, or order configuration. | H25: Kept separate from generated quantities and attribute values. | I25: Direct:OG-01.3 | K25: SUP-007; SUP-003
A26: OCPS-R2.1.5 | B26: OCPS-R2.1 | C26: Atomic child | D26: Data/rules | E26: C | F26: If object attributes influence the attribute values of generated objects, the OCPS model shall use those attributes in the attribute-generation rule. | G26: The requirement is satisfied if the attribute-generation rule identifies the source object attributes and defines how their values influence the attribute values assigned to generated objects. The source attributes may belong to the triggering object or related objects. | H26: Kept separate because it affects attribute values rather than object counts or relations. | I26: Direct:OG-01.4 | K26: SUP-007; SUP-003
A27: OCPS-R2.2 | B27: OCPS-R2 | C27: Parent/decomposed | D27: Temporal/stochastic | F27: The OCPS simulation model shall define arrival and generation timing rules for simulated object types and related object sets. | G27: This parent groups requirements for when objects or related object sets are introduced into the simulation, including independent and interdependent arrival patterns. | H27: Groups external-arrival rules in R2.2.1 and interdependent arrival or generation timing in R2.2.2. | I27: BPS:LR-TS1; Direct:ARR-01; Direct:ARR-01.1; Direct:ARR-01.2; OCPM:OCPM-DR-004; OCPM:OCPM-TS-001
A28: OCPS-R2.2.1 | B28: OCPS-R2.2 | C28: Atomic child | D28: Temporal/stochastic | E28: M | F28: For each object type that enters the simulated system from outside the modelled process, the OCPS model shall specify its arrival rule. | G28: The arrival rule determines when new objects of that type enter the simulated system. It may be expressed using inter-arrival times, an arrival rate, a calendar, an empirical or fitted probability distribution, or a deterministic schedule. Object types that arrive independently may have different arrival rules. | H28: Merged object-type and related-object-set arrival requirements into one parent-level timing child; independent and interdependent cases are decomposed below. | I28: Adapted:OCPS-TS-001; Adapted:OCPS-TS-002; BPS:LR-TS1; Direct:ARR-01; Direct:ARR-01.1; OCPM:OCPM-TS-001 | J28: FND-007; BPS-030; FND-002; BPS-006; BPS-013; FND-001 | K28: SUP-003; SUP-006
A29: OCPS-R2.2.2 | B29: OCPS-R2.2 | C29: Atomic child | D29: Temporal/stochastic | E29: C | F29: If the arrival or generation time of an object instance depends on another object instance, the OCPS model shall specify that temporal dependency. | G29: This requirement covers objects that arrive or are generated together and objects whose arrival or generation time is defined relative to another object. Object quantities, relationships, and multiplicities are specified under the Object/Data perspective. | H29: Merged related-object-set timing with interdependent arrival strategy. | I29: Adapted:OCPS-TS-002; BPS:LR-TS1; Direct:ARR-01.2; OCPM:OCPM-DR-004; OCPM:OCPM-TS-001 | J29: FND-007; BPS-030; FND-002; BPS-006 | K29: SUP-003; SUP-006; SUP-007
A30: OCPS-R3 | C30: Parent | D30: Control-flow | F30: The OCPS simulation model shall define object-centric control-flow and activity-binding behaviour. | G30: This parent groups requirements for event ordering, object-aware routing, split/join behaviour, and executable activity binding selection. | H30: Created to group control-flow and binding requirements while avoiding duplicate routing/synchronization rows. | I30: Adapted:OCPS-CF-002; Adapted:OCPS-CF-003; Direct:BIND-01; Direct:CF-01
A31: OCPS-R3.1 | B31: OCPS-R3 | C31: Parent/decomposed | D31: Control-flow | F31: The OCPS simulation model shall define control-flow constructs between simulated event types. | G31: The model must specify which event types may occur before, after, or in combination with other event types, and which control-flow constructs are supported for simulation. | H31: Retained case-centric baseline and interpreted it as event-type ordering in OCPS. | I31: Adapted:OCPS-CF-002; BPS:LR-CF2; OCPM:OCPM-CF-001
A32: OCPS-R3.1.1 | B32: OCPS-R3.1 | C32: Atomic child | D32: Control-flow | E32: M | F32: The OCPS model shall define ordering relations between simulated event types. | G32: For each ordered relation, the model can identify the predecessor event type and successor event type. The requirement is satisfied if the simulation engine can use these relations to determine which event types are enabled after another event type occurs. | I32: BPS:LR-CF2; OCPM:OCPM-CF-001 | J32: FND-003; BPS-006; FND-001; BPS-034; BPS-028; BPS-030; FND-002 | K32: SUP-004; SUP-011
A33: OCPS-R3.1.2 | B33: OCPS-R3.1 | C33: Atomic child | D33: Control-flow | E33: C | F33: If alternative execution paths exist, the OCPS model shall define the branching structure between simulated event types. | G33: For each branching point, the model identifies the source event type or decision point and its alternative successor paths. The rule that selects a path is specified separately under R3.3.3. | H33: Separates the definition of available alternative paths from the selection rule in R3.3.3. | I33: BPS:LR-CF2; OCPM:OCPM-CF-001 | J33: FND-003; BPS-006; FND-001; BPS-034; BPS-028; BPS-030; FND-002 | K33: SUP-004; SUP-011
A34: OCPS-R3.1.3 | B34: OCPS-R3.1 | C34: Atomic child | D34: Control-flow | E34: C | F34: If execution requires paths to join or synchronise, the OCPS model shall define the corresponding join or synchronisation structure. | G34: Each join or synchronization point identifies the incoming paths or event types and the downstream event type. Object-specific enablement conditions are specified under R3.3.2 and R3.4; temporal readiness is specified under R4.4. | I34: BPS:LR-CF2; OCPM:OCPM-CF-001 | J34: FND-003; BPS-006; FND-001; BPS-034; BPS-028; BPS-030; FND-002 | K34: SUP-004; SUP-011
A35: OCPS-R3.1.4 | B35: OCPS-R3.1 | C35: Atomic child | D35: Control-flow | E35: C | F35: If repeated execution of event types or event sequences exists, the OCPS model shall define loop behaviour between simulated event types. | G35: For each loop, the model can identify the repeated event type or event-type sequence, the loop entry and exit condition, and any maximum iteration rule or stopping condition if applicable. | I35: BPS:LR-CF2; OCPM:OCPM-CF-001 | J35: FND-003; BPS-006; FND-001; BPS-034; BPS-028; BPS-030; FND-002 | K35: SUP-004; SUP-011
A36: OCPS-R3.1.5 | B36: OCPS-R3.1 | C36: Atomic child | D36: Control-flow | E36: C | F36: If parallel or independent event execution exists, the OCPS model shall define concurrent execution relations between simulated event types. | G36: For each concurrency relation, the model can identify event types that may be enabled or executed independently within the same simulation period, and the conditions or object dependencies that restrict their concurrent execution. | I36: BPS:LR-CF2; OCPM:OCPM-CF-001 | J36: FND-003; BPS-006; FND-001; BPS-034; BPS-028; BPS-030; FND-002 | K36: SUP-004; SUP-011
A37: OCPS-R3.2 | B37: OCPS-R3 | C37: Atomic child | D37: Control-flow | E37: M | F37: The OCPS model shall represent the current execution state of each object instance whose lifecycle affects activity enablement. | G37: The current execution state of each applicable object can be determined and matched against activity preconditions. It may be represented by control-flow positions or equivalent state variables. Data-value requirements are specified under R1.9.1. | H37: Merged separate control-flow states and current object position into one runtime state requirement. | I37: Adapted:OCPS-CF-004; BPS:LR-CF2; Direct:CF-01; Direct:CF-02; Direct:STATE-01; OCPM:OCPM-CF-001 | J37: FND-003; BPS-006; FND-001; BPS-034; BPS-028; BPS-030; FND-002 | K37: SUP-004; SUP-011; SUP-006; SUP-003
A38: OCPS-R3.3 | B38: OCPS-R3 | C38: Parent/decomposed | D38: Control-flow | F38: The OCPS simulation model shall define object-aware branching, routing, and synchronization behaviour. | G38: This parent groups requirements for object-aware splits, multi-object synchronization conditions, alternative-path routing, and data-aware routing based on related objects. | H38: Added parent node to group object-aware split, synchronization, and routing requirements.
A39: OCPS-R3.3.1 | B39: OCPS-R3.3 | C39: Atomic child | D39: Control-flow | E39: C | F39: For each split that creates or activates multiple object-specific execution paths, the OCPS model shall specify which related object types or object instances determine the resulting paths. | G39: The requirement is satisfied if each object-aware split identifies the related object type or object attribute used for the split decision, the possible resulting paths, and the rule that assigns affected object instances to those paths. | H39: Kept separate from join/synchronization following supervision guidance because split and join have different complexity. | I39: Adapted:OCPS-CF-008; BPS:LR-CF2; BPS:LR-CF3; Direct:CF-02; OCPM:OCPM-CF-002; OCPM:OCPM-CF-003; OCPM:OCPM-DR-004 | J39: FND-003; BPS-006; FND-001; BPS-034; BPS-028; BPS-030; FND-002; FND-006; FND-004; BPS-038; BPS-042; BPS-013 | K39: SUP-001; SUP-002; SUP-003; SUP-004; SUP-007; SUP-006; SUP-005
A40: OCPS-R3.3.2 | B40: OCPS-R3.3 | C40: Atomic child | D40: Control-flow | E40: C | F40: For each activity that requires multiple related objects before execution, the OCPS model shall specify the object-state or relationship conditions that enable the activity. | G40: Each such activity identifies the required pre-existing objects and the state or relationship conditions for enablement. Objects created by the activity are specified as outputs rather than pre-existing prerequisites. Temporal readiness is specified under R4.4. | H40: Merged inter-object synchronization and join requirements; kept separate from split dependencies. | I40: Adapted:OCPS-CF-009; BPS:LR-CF2; BPS:LR-CF3; Direct:CF-02; Direct:CF-03; OCPM:OCPM-CF-002; OCPM:OCPM-CF-003 | J40: FND-003; BPS-006; FND-001; BPS-034; BPS-028; BPS-030; FND-002; FND-006; FND-004; BPS-038; BPS-042; BPS-013; FND-007; BPS-052; BPS-010 | K40: SUP-001; SUP-002; SUP-003; SUP-004; SUP-007; SUP-006; SUP-005
A41: OCPS-R3.3.3 | B41: OCPS-R3.3 | C41: Atomic child / specialised parent | D41: Control-flow | E41: C | F41: If alternative paths exist, the OCPS model shall specify the routing logic used to select among them. | G41: The requirement is satisfied if, for each set of alternative paths, the model defines how the selected path is determined, for example by probabilities, object data, event data, or rules. | H41: Specifies how a path is selected from the alternatives defined under R3.1.2. R3.3.3.1 adds a conditional multi-object-data refinement. | I41: Adapted:OCPS-CF-003; BPS:LR-CF3; Direct:CF-04; OCPM:OCPM-CF-003 | J41: FND-003; BPS-006; FND-006; FND-002; FND-004; BPS-038; BPS-042; BPS-013; BPS-030 | K41: SUP-003; SUP-005; SUP-007
A42: OCPS-R3.3.3.1 | B42: OCPS-R3.3.3 | C42: Atomic child | D42: Control-flow | E42: C | F42: If routing depends on data from multiple related objects, the OCPS model shall specify decision rules using the required attributes or state variables of those objects. | G42: The requirement is satisfied if the decision rules identify and use attributes or state variables from more than one participating or related object to determine the selected path. | H42: Merged object-aware decision rules and multi-object data-aware routing. | I42: Adapted:OCPS-CF-010; BPS:LR-CF3; Direct:CF-05; OCPM:OCPM-CF-003; OCPM:OCPM-DR-002; OCPM:OCPM-DR-003 | J42: FND-003; BPS-006; FND-006; FND-002; FND-004; BPS-038; BPS-042; BPS-013; BPS-030; BPS-034; BPS-012 | K42: SUP-003; SUP-005; SUP-007; SUP-001; BPS-018; BPS-037; SUP-008; SUP-013; SUP-009
A43: OCPS-R3.4 | B43: OCPS-R3 | C43: Parent/decomposed | D43: Control-flow | F43: The OCPS simulation model shall define activity-binding rules for simulated event execution. | G43: This parent groups runtime binding constraints on object types, cardinalities, relationships, and execution states. Preconditions apply to objects required before execution. Objects produced by an activity follow its generation rules and declared output participation.
A44: OCPS-R3.4.1 | B44: OCPS-R3.4 | C44: Atomic child | D44: Control-flow | E44: M | F44: The OCPS model shall select activity bindings that satisfy the required object types of the activity. | G44: Objects selected before execution match the required input or context object types. Objects created by execution match the declared output types when generated. The input/output distinction follows the participation specification in R1.5.1. | H44: Separated runtime binding selection from static definition of event-object schema. | I44: Adapted:OCPS-CF-006; BPS:LR-CF1; Direct:BIND-01; Direct:BIND-01.1; Direct:CF-02; OCPM:OCPM-CF-002; OCPM:OCPM-DR-001 | J44: FND-003; FND-001; FND-004; BPS-013; FND-002 | K44: SUP-001; SUP-002; SUP-003; SUP-004; SUP-007; SUP-006; SUP-010; SUP-011; SUP-013
A45: OCPS-R3.4.2 | B45: OCPS-R3.4 | C45: Atomic child | D45: Control-flow | E45: C | F45: The OCPS model shall select activity bindings that satisfy the required object cardinalities of the activity. | G45: The selected pre-existing objects satisfy input cardinality constraints before execution. The resulting event participation satisfies any declared output or outcome-dependent cardinality constraints after execution. | H45: Kept as an atomic runtime check for cardinalities. | I45: Direct:BIND-01.2 | K45: SUP-003
A46: OCPS-R3.4.3 | B46: OCPS-R3.4 | C46: Atomic child | D46: Control-flow | E46: C | F46: The OCPS model shall select activity bindings that satisfy the required object-to-object relations among involved objects. | G46: Before execution, selected objects satisfy every relationship declared as an activity prerequisite. Relations created by execution follow their generation or change rules rather than being required to pre-exist. | H46: Kept as an atomic runtime check for relationship constraints. | I46: Direct:BIND-01.3 | K46: SUP-003
A47: OCPS-R3.4.4 | B47: OCPS-R3.4 | C47: Atomic child | D47: Control-flow | E47: M | F47: The OCPS model shall select only activity bindings that are enabled in the current control-flow state. | G47: A binding is executable only if objects required before execution satisfy the relevant control-flow preconditions. Newly created objects receive their execution states through the specified generation or activity rules. | H47: Kept as an atomic runtime check for object-state-enabled execution. | I47: Adapted:OCPS-CF-004; BPS:LR-CF2; Direct:BIND-01.4; Direct:CF-02; OCPM:OCPM-CF-001 | J47: FND-003; BPS-006; FND-001; BPS-034; BPS-028; BPS-030; FND-002 | K47: SUP-004; SUP-011; SUP-003
A48: OCPS-R4 | C48: Parent | D48: Temporal/stochastic | F48: The OCPS simulation model shall define the temporal behavior and simulation-clock settings required for execution. | G48: This parent groups activity duration, non-processing delay, multi-object temporal readiness, time-triggered behavior, time unit, and simulation-run scope. Object arrival and generation timing is specified under R2.2. | H48: Created because timing is a separate simulation perspective and should not be merged into generic 'parameters'. | I48: Adapted:OCPS-TS-003; Adapted:OCPS-TS-007; Direct:TEMP-01
A49: OCPS-R4.1 | B49: OCPS-R4 | C49: Atomic child | D49: Temporal/stochastic | E49: M | F49: The OCPS model shall specify an execution-duration rule for each activity type whose occurrences consume simulated time. | G49: The rule determines elapsed simulated time from activity start to completion and may be fixed, empirical, stochastic, or context-dependent. Instantaneous activities and pre-start waiting are excluded. | H49: Merged activity duration and object-centric event duration requirements. Time trace check: timestamp advancement is retained under delay evidence. Start-to-completion service time uses a separate checked OPerA definition. | I49: Adapted:OCPS-TS-003; BPS:LR-TS2; OCPM:OCPM-TS-003 | J49: FND-006; FND-002; FND-001; BPS-030; BPS-006; BPS-039; BPS-016; BPS-013 | K49: SUP-016
A50: OCPS-R4.2 | B50: OCPS-R4 | C50: Atomic child | D50: Temporal/stochastic | E50: C | F50: If execution duration depends on the objects participating in an activity occurrence, the OCPS model shall specify how those objects affect the duration. | G50: The duration may depend on the number or types of participating objects or on their modelled attributes, states, or relationships. Waiting for the required objects to become ready is not part of execution duration. | I50: BPS:LR-TS2; Direct:TEMP-02 | J50: FND-002 | K50: SUP-007
A51: OCPS-R4.3 | B51: OCPS-R4 | C51: Atomic child | D51: Temporal/stochastic | E51: C | F51: If the model includes an explicit delay outside activity execution, the OCPS model shall specify the delay rule. | G51: The delay may occur before an activity or between activities and may be fixed, calendar-based, empirical, stochastic, or context-dependent. Examples include appointment, handoff, transport, transfer, and external-response delays. Waiting caused by resource unavailability or object readiness is determined separately. | I51: BPS:LR-TS3; Direct:TEMP-01 | J51: FND-006; FND-001; BPS-041; BPS-052; BPS-010; BPS-013 | K51: SUP-003
A52: OCPS-R4.4 | B52: OCPS-R4 | C52: Atomic child | D52: Temporal/stochastic | E52: C | F52: If an activity requires related objects that may become ready at different times, the OCPS model shall specify the temporal-readiness condition for that activity. | G52: The activity cannot start before all required participating objects are ready. Logical object-state, relationship, and binding conditions are specified under R3.3.2. The actual activity start may occur later because of resource unavailability or another explicitly modelled delay. | H52: Separates temporal readiness of required input objects from logical synchronization and resource contention. | I52: Adapted:OCPS-CF-009; Adapted:OCPS-TS-004; Adapted:OCPS-TS-006; BPS:LR-CF2; BPS:LR-TS3; Direct:CF-03; Direct:TEMP-05; OCPM:OCPM-TS-002 | J52: FND-001 | K52: SUP-007; SUP-016; SUP-003
A53: OCPS-R4.5 | B53: OCPS-R4 | C53: Atomic child | D53: Temporal/stochastic | E53: C | F53: If simulated time directly triggers process behavior or an object-state change, the OCPS model shall specify the temporal trigger condition. | G53: This requirement covers timer events, timeouts, deadlines, recurring events, and explicitly modelled time-driven object-state changes. The trigger may be defined by an absolute time, an elapsed duration from a specified reference point, a recurring interval, or another deterministic, empirical, or stochastic timing rule. Activity execution duration and deadlines used only as performance targets are excluded. | H53: Retained for time-triggered behaviour, distinct from execution duration and passive performance targets. | I53: Adapted:OCPS-TS-013; BPS:LR-TS4; OCPM:OCPM-DR-003 | J53: FND-006; FND-001; BPS-007; BPS-005; BPS-028 | K53: SUP-001; SUP-008; SUP-009; SUP-013
A54: OCPS-R4.6 | B54: OCPS-R4 | C54: Atomic child | D54: Temporal/stochastic | E54: M | F54: The OCPS model shall define the simulation time unit. | G54: The simulation time unit defines the default unit used to interpret numeric temporal parameters and simulation-clock values, including inter-arrival times, activity durations, delays, and waiting times, unless another unit is explicitly specified. Absolute calendar datetimes and timestamps may retain a datetime representation. | H54: Kept as a concrete configuration requirement rather than generic parameterization. | I54: Adapted:OCPS-TS-008; BPS:LR-TS5 | J54: FND-006; BPS-026
A55: OCPS-R4.7 | B55: OCPS-R4 | C55: Atomic child | D55: Temporal/stochastic | E55: M | F55: The OCPS model shall specify the start point and stopping criterion of each simulation run. | G55: The start point may be a calendar datetime or a simulation-time origin. The stopping criterion may be an end time, an elapsed simulated duration, a specified number of generated cases or objects, or another explicitly defined termination condition. | H55: Kept as a concrete configuration requirement rather than generic scenario/what-if wording. | I55: Adapted:OCPS-TS-009; BPS:LR-TS6 | J55: FND-001; FND-006; FND-007; BPS-006; BPS-028; BPS-039
A56: OCPS-R5 | C56: Parent | D56: Resource/organization | F56: The OCPS simulation model shall represent resources and organizational constraints that affect execution or performance. | G56: This parent groups requirements about resource requirements, eligibility, allocation, availability, capacity, calendars, and resource-dependent performance. | H56: Created to merge resource-allocation overlaps and separate mandatory from conditional implementation-related resource features. | I56: Adapted:OCPS-RO-001; Adapted:OCPS-RO-004; Direct:RES-01
A57: OCPS-R5.1 | B57: OCPS-R5 | C57: Atomic child | D57: Resource/organization | E57: M | F57: For each activity that requires resources, the OCPS model shall specify the required resource category. | G57: The model states which resource type or role is needed | H57: Specifies the required resource category; required resource quantity is specified separately under R5.2. | I57: Adapted:OCPS-RO-001; BPS:LR-RO1 | J57: FND-006; FND-002; BPS-030; BPS-013; BPS-015; BPS-058; BPS-017; BPS-062; BPS-057
A58: OCPS-R5.2 | B58: OCPS-R5 | C58: Atomic child | D58: Resource/organization | E58: M | F58: For each activity that requires resources, the OCPS model shall specify the number of resource units required. | G58: The model states how many units are required to execute one activity occurrence. | I58: Adapted:OCPS-RO-002; BPS:LR-RO2 | J58: FND-006; BPS-058; FND-002; BPS-062
A59: OCPS-R5.3 | B59: OCPS-R5 | C59: Atomic child | D59: Resource/organization | E59: M | F59: For each activity that requires resources, the OCPS model shall specify which resources are eligible to execute that activity. | G59: Eligibility rules identify the resource categories or resource units that may execute each activity type. | H59: Kept separate from selection among eligible resources. | I59: Adapted:OCPS-RO-004; BPS:LR-RO3 | J59: FND-006; FND-002; BPS-039; BPS-057; BPS-062; BPS-030; BPS-013; BPS-015; BPS-058; BPS-009
A60: OCPS-R5.4 | B60: OCPS-R5 | C60: Atomic child | D60: Resource/organization | E60: M | F60: For each activity that requires resources, the OCPS model shall specify the rule for selecting the required resources from the eligible resources. | G60: The allocation rule defines how one or more eligible resources are selected, such as first available, priority-based, skill-based, or rule-based selection. | H60: Merged with individualized resource-allocation discussion by making the selection rule explicit rather than creating a duplicate allocation requirement. | I60: Adapted:OCPS-RO-005; BPS:LR-RO4 | J60: FND-006; FND-002; BPS-062; BPS-015; BPS-009
A61: OCPS-R5.5 | B61: OCPS-R5 | C61: Atomic child | D61: Resource/organization | E61: C | F61: If a resource or resource pool has time-varying availability, the OCPS model shall specify the time periods during which it is available for execution. | G61: Each relevant resource or pool has a defined availability schedule, such as working hours, shifts, breaks, maintenance windows, or unavailable periods. Available resource quantities are specified under R5.6. | I61: Adapted:OCPS-RO-006; BPS:LR-RO5; Direct:RES-02 | J61: FND-006; FND-002; BPS-006; BPS-013; BPS-015; BPS-057; BPS-030; BPS-032; BPS-009; FND-005 | K61: SUP-007; SUP-017
A62: OCPS-R5.6 | B62: OCPS-R5 | C62: Atomic child | D62: Resource/organization | E62: C | F62: If resource capacity constrains activity execution, the OCPS model shall specify the available capacity of each relevant resource or resource pool over simulation time. | G62: Each relevant resource or pool has a specified available capacity, expressed in resource units, over simulation time. Capacity may be constant or time-varying. Availability schedules are specified under R5.5; shared capacity is specified under R5.6.1. | H62: Retained as the capacity-quantity requirement, separate from availability schedules in R5.5 and refined by shared capacity in R5.6.1. | I62: Adapted:OCPS-RO-007; BPS:LR-RO6; Direct:RES-02 | J62: FND-006; BPS-030; BPS-015; BPS-013; FND-005; BPS-058; BPS-032; BPS-057
A63: OCPS-R5.6.1 | B63: OCPS-R5.6 | C63: Atomic child | D63: Resource/organization | E63: C | F63: If activities involving different object types or object sets use the same limited resource or resource pool, the OCPS model shall represent the capacity of that resource or pool as shared across those activities. | G63: The shared resource or resource pool is represented as a single shared capacity rather than as separate capacities for different object types or process views, so that all relevant activity occurrences compete for the same available capacity. | H63: Kept as conditional implementation-related requirement rather than a mandatory core requirement. | I63: BPS:LR-RO6; Direct:RES-03 | J63: BPS-015 | K63: SUP-006; SUP-007; SUP-017
A64: OCPS-R5.7 | B64: OCPS-R5 | C64: Atomic child | D64: Resource/organization | E64: C | F64: If the execution duration of an activity depends on the executing resource or resource profile, the OCPS model shall specify the corresponding resource-dependent duration rule. | G64: The same activity may have different durations depending on the selected resource category, unit, skill, or profile. This requirement complements OCPS-R4.1, which specifies the general execution-duration rule, but does not introduce a separate notion of duration. Resource eligibility, resource selection, availability, queueing, and non-processing waiting are outside its scope. | H64: Kept as conditional resource-performance requirement. | I64: Adapted:OCPS-RO-008; BPS:LR-RO7 | J64: FND-002; BPS-017; BPS-013; BPS-015; BPS-009
A65: OCPS-R5.8 | B65: OCPS-R5 | C65: Atomic child | D65: Resource/organization | E65: C | F65: If activity occurrences wait for limited resources, the OCPS model shall specify the queue-ordering rule for those activity occurrences. | G65: The rule determines which waiting activity occurrence receives an available resource next. It applies to competing occurrences of the same or different activity types and may be based on FIFO, priority, earliest due date, shortest processing time, an explicitly defined randomized policy, or a custom rule. It concerns resource contention rather than control-flow precedence. | H65: Specifies ordering under resource contention. Explicit non-processing delays are specified under R4.3 and object temporal readiness under R4.4. | I65: Adapted:OCPS-RO-009; Adapted:OCPS-TS-005; BPS:LR-RO8; OCPM:OCPM-RO-003 | J65: FND-002; FND-006; BPS-030; BPS-015; BPS-013 | K65: SUP-017
A66: OCPS-R5.9 | B66: OCPS-R5 | C66: Atomic child | D66: Resource/organization | E66: C | F66: If a resource unit can execute multiple activity occurrences simultaneously, the OCPS model shall specify the concurrent-execution limit of that resource unit. | G66: The model states the maximum simultaneous activity occurrences for each relevant resource unit or category. | H66: Classified as conditional implementation-related feature. | I66: Adapted:OCPS-RO-010; BPS:LR-RO9 | J66: BPS-009; FND-002
A67: OCPS-R5.10 | B67: OCPS-R5 | C67: Atomic child | D67: Resource/organization | E67: C | F67: If an activity-execution rule depends on resource attributes, the OCPS model shall represent those resource attributes. | G67: Resource attributes such as skill, experience, location, or reliability can be linked to duration, availability, or routing assumptions. | H67: Classified as conditional implementation-related feature. | I67: Adapted:OCPS-RO-011; BPS:LR-RO10 | J67: FND-002; BPS-017; BPS-015; BPS-013; BPS-058; BPS-009
A68: OCPS-R5.11 | B68: OCPS-R5 | C68: Atomic child | D68: Resource/organization | E68: C | F68: If queue abandonment is modelled, the OCPS model shall specify the queue-leaving condition. | G68: For each queue with abandonment, the model identifies the condition under which an occurrence leaves without service and its resulting queue-membership status. Any subsequent process path is specified by the applicable routing rules. | H68: Retained as a conditional queue-behaviour requirement; absence of abandonment makes it inapplicable rather than optional. | I68: Adapted:OCPS-RO-012; BPS:LR-RO11 | J68: FND-002; BPS-058
A69: OCPS-R5.12 | B69: OCPS-R5 | C69: Atomic child | D69: Resource/organization | E69: C | F69: If batch execution is modelled, the OCPS model shall specify the batch execution condition. | G69: For each modelled batch, the model identifies eligible members and the condition that starts joint processing, such as a specified size or waiting-time threshold. These rules determine which objects or activity occurrences execute together. | H69: Retained as a conditional batch-behaviour requirement; batch rules are required whenever batching is in scope. | I69: Adapted:OCPS-RO-013; BPS:LR-RO12 | J69: FND-002; BPS-013; FND-005

Sheet Candidates
A1: Candidate node | B1: Stage | C1: Original ID | D1: Candidate statement | E1: Description / scope | F1: Input BPS IDs | G1: Input OCPM IDs | H1: Reference text | I1: Matched Literature Codes | J1: Linked Evidence IDs | K1: Transformation type | L1: Transformation reason | M1: Transformation judgement | N1: Candidate evidence synthesis | O1: Use decision | P1: Decision reason | Q1: Final requirement IDs | R1: Verification Evidence IDs | S1: Input route | T1: Direct source IDs
A2: BPS:LR-CF1 | B2: BPS | C2: LR-CF1 | D2: The simulation model shall explicitly define activities. | E2: The model must identify the executable units of behavior whose occurrences are simulated. | H2: Aalst 2010, Business Process Simulation Revisited; Dumas et al. 2018, Fundamentals of Business Process Management; Aalst 2015, Business Process Simulation Survival Guide; Chapela-Campa et al. 2025, SIMOD: Automated Discovery of Business Process Simulation Models; Martin et al. 2016, The Use of Process Mining in Business Process Simulation Model Construction: Structuring the Field | I2: BPS-013; FND-001; FND-002; FND-003; FND-004 | J2: EV-F-0002; EV-F-0003; EV-F-0004; EV-F-0005; EV-S-0002 | O2: Include in final synthesis | P2: Retained concept: The simulation model shall explicitly define activities. Final path: OCPS-R1.1; OCPS-R1.2; OCPS-R1.3; OCPS-R1.4; OCPS-R1.5.1; OCPS-R1.5.2; OCPS-R3.4.1. Recorded catalogue synthesis: Merged the case-centric activity requirement with OCEL/OCED event-type terminology. Direct source-to-candidate inputs: BPS-013; FND-001; FND-002; FND-003; FND-004. This route is retained independently of any intermediate Evidence record; source-specific strength and scope are not inferred from the route alone. | Q2: OCPS-R1.1; OCPS-R1.2; OCPS-R1.3; OCPS-R1.4; OCPS-R1.5; OCPS-R1.5.1; OCPS-R1.5.2; OCPS-R3.4.1 | S2: Source -> Candidate (direct recorded source use); Source -> Evidence -> Candidate | T2: BPS-013; FND-001; FND-002; FND-003; FND-004
A3: BPS:LR-CF2 | B3: BPS | C3: LR-CF2 | D3: The simulation model shall define activity ordering and control-flow constructs. | E3: The model must specify possible execution paths, including sequence, branching, concurrency, loops, splits, and joins. | H3: Aalst 2010, Business Process Simulation Revisited; Rosenthal et al. 2021, Business Process Simulation on Procedural Graphical Process Models: Structuring Overview and Paths for Future Research; Dumas et al. 2018, Fundamentals of Business Process Management; Jadrić et al. 2020, Process Mining Contributions to Discrete-Event Simulation Modelling; Tsinarakis et al. 2022, A Discrete Process Modelling and Simulation Methodology for Industrial Systems within the Concept of Digital Twins; Camargo et al. 2020, Automated Discovery of Business Process Simulation Models from Event Logs; Martin et al. 2016, The Use of Process Mining in Business Process Simulation Model Construction: Structuring the Field | I3: BPS-006; BPS-028; BPS-030; BPS-034; FND-001; FND-002; FND-003 | J3: EV-F-0006; EV-F-0007; EV-F-0008; EV-S-0003; EV-S-0004; EV-S-0005; EV-S-0006 | O3: Include in final synthesis | P3: Retained concept: The simulation model shall define activity ordering and control-flow constructs. Final path: OCPS-R3.1.1; OCPS-R3.1.2; OCPS-R3.1.3; OCPS-R3.1.4; OCPS-R3.1.5; OCPS-R3.2; OCPS-R3.3.1; OCPS-R3.3.2; OCPS-R3.4.4; OCPS-R4.4. Recorded catalogue synthesis: Retained case-centric baseline and interpreted it as event-type ordering in OCPS. Direct source-to-candidate inputs: BPS-006; BPS-028; BPS-030; BPS-034; FND-001; FND-002; FND-003. This route is retained independently of any intermediate Evidence record; source-specific strength and scope are not inferred from the route alone. | Q3: OCPS-R3; OCPS-R3.1; OCPS-R3.1.1; OCPS-R3.1.2; OCPS-R3.1.3; OCPS-R3.1.4; OCPS-R3.1.5; OCPS-R3.2; OCPS-R3.3.1; OCPS-R3.3.2; OCPS-R3.4.4; OCPS-R4.4 | S3: Source -> Candidate (direct recorded source use); Source -> Evidence -> Candidate | T3: BPS-006; BPS-028; BPS-030; BPS-034; FND-001; FND-002; FND-003
A4: BPS:LR-CF3 | B4: BPS | C4: LR-CF3 | D4: The simulation model shall specify routing logic. | E4: The model must specify how alternative paths are selected, for example through probabilities, conditions, or rules. | H4: Aalst 2010, Business Process Simulation Revisited; Rosenthal et al. 2021, Business Process Simulation on Procedural Graphical Process Models: Structuring Overview and Paths for Future Research; WfMC 2016, Business Process Simulation Specification, Version 2.0; Martin et al. 2016, The Use of Process Mining in Business Process Simulation Model Construction: Structuring the Field; Aalst 2015, Business Process Simulation Survival Guide; Savickas & Vasilecas 2018, An Approach to Business Process Simulation Using Mined Probabilistic Models; de Leoni et al. 2023, Investigating the Influence of Data-Aware Process States on Activity Probabilities in Simulation Models; Chapela-Campa et al. 2025, SIMOD: Automated Discovery of Business Process Simulation Models; Camargo et al. 2020, Automated Discovery of Business Process Simulation Models from Event Logs | I4: BPS-006; BPS-013; BPS-030; BPS-038; BPS-042; FND-002; FND-003; FND-004; FND-006 | J4: EV-F-0009; EV-F-0010; EV-F-0011; EV-F-0012; EV-S-0007; EV-S-0008; EV-S-0009; EV-S-0010; EV-S-0011 | O4: Include in final synthesis | P4: Retained concept: The simulation model shall specify routing logic. Final path: OCPS-R1.9.1; OCPS-R1.9.2; OCPS-R1.9.3; OCPS-R3.3.1; OCPS-R3.3.2; OCPS-R3.3.3; OCPS-R3.3.3.1; OCPS-R4.4. Recorded catalogue synthesis: Added parent node to group dynamic object-state/value requirements. Direct source-to-candidate inputs: BPS-006; BPS-013; BPS-030; BPS-038; FND-002; FND-003; FND-004; FND-006. This route is retained independently of any intermediate Evidence record; source-specific strength and scope are not inferred from the route alone. | Q4: OCPS-R1.9; OCPS-R1.9.1; OCPS-R1.9.2; OCPS-R1.9.3; OCPS-R3; OCPS-R3.3.1; OCPS-R3.3.2; OCPS-R3.3.3; OCPS-R3.3.3.1; OCPS-R4.4 | S4: Source -> Candidate (direct recorded source use); Source -> Evidence -> Candidate | T4: BPS-006; BPS-013; BPS-030; BPS-038; FND-002; FND-003; FND-004; FND-006
A5: BPS:LR-DR1 | B5: BPS | C5: LR-DR1 | D5: The model shall represent event attribute values relevant to process execution and simulation behaviour. | E5: The model must represent event attributes that influence or describe process execution, such as the location at which it is executed. | H5: Martin et al. 2016, The Use of Process Mining in Business Process Simulation Model Construction: Structuring the Field; Jadrić et al. 2020, Process Mining Contributions to Discrete-Event Simulation Modelling; Savickas & Vasilecas 2018, An Approach to Business Process Simulation Using Mined Probabilistic Models; Pourbafrani & Aalst 2022, Discovering System Dynamics Simulation Models Using Process Mining | I5: BPS-012; BPS-034; BPS-038; FND-002 | J5: EV-F-0013; EV-S-0012; EV-S-0013; EV-S-0014 | O5: Include in final synthesis | P5: Retained concept: The model shall represent event attribute values relevant to process execution and simulation behaviour. Final path: OCPS-R1.3; OCPS-R1.6; OCPS-R1.7.1; OCPS-R1.7.2; OCPS-R1.8; OCPS-R1.9.1; OCPS-R1.9.2; OCPS-R1.9.3; OCPS-R3.3.3.1. Direct source-to-candidate inputs: BPS-012; BPS-034; BPS-038; FND-002. This route is retained independently of any intermediate Evidence record; source-specific strength and scope are not inferred from the route alone. | Q5: OCPS-R1; OCPS-R1.3; OCPS-R1.6; OCPS-R1.7.1; OCPS-R1.7.2; OCPS-R1.8; OCPS-R1.9; OCPS-R1.9.1; OCPS-R1.9.2; OCPS-R1.9.3; OCPS-R3.3.3.1 | S5: Source -> Candidate (direct recorded source use); Source -> Evidence -> Candidate | T5: BPS-012; BPS-034; BPS-038; FND-002
A6: BPS:LR-RO1 | B6: BPS | C6: LR-RO1 | D6: The simulation model shall specify the required resource category for each activity that requires resources. | E6: This requirement states that the model must identify what kind of resource is needed to execute an activity. A resource category may refer to a resource type, role, pool, group, profile, staff category, performer role, organizational position, or another classification used in the model. In models that represent resources at the individual level, the category may be represented by an explicitly defined set of individual resource units that can perform the activity. This requirement only concerns the activity-level resource requirement; it does not specify how many resource units are needed or how a concrete resource unit is selected for a specific activity instance. | H6: WfMC 2016, Business Process Simulation Specification, Version 2.0; Martin et al. 2016, The Use of Process Mining in Business Process Simulation Model Construction: Structuring the Field; Camargo et al. 2020, Automated Discovery of Business Process Simulation Models from Event Logs; Chapela-Campa et al. 2025, SIMOD: Automated Discovery of Business Process Simulation Models; López-Pintado et al. 2024, Discovery, Simulation, and Optimization of Business Processes with Differentiated Resources; Wagner (2023) DPMN; Ougaabal et al. 2020, Visual Workflow Process Modeling and Simulation Approach Based on Non-Functional Properties of Resources; El Kassis et al. 2023, Bridging the Gap Between Business Process and Simulation: Transformation from BPMN to DEVS;Mesabbah et al. 2019, A Hybrid Process Mining Framework for Automated Simulation Modelling for Healthcare | I6: BPS-013; BPS-015; BPS-017; BPS-030; BPS-034; BPS-039; BPS-057; BPS-058; BPS-062; FND-002; FND-006 | J6: EV-F-0014; EV-F-0015; EV-S-0015; EV-S-0016; EV-S-0017; EV-S-0018; EV-S-0019; EV-S-0020; EV-S-0021; EV-S-0022; R5-FE-001; R5-FE-002; R5-FE-003; R5-FE-004; R5-FE-005; R5-FE-006; R5-FE-007; R5-FE-008; R5-FE-009 | M6: Resource source records distinguish current category, demand quantity, eligibility, selection, availability, supply quantity, performance, queue order, concurrency, attributes, abandonment and batching IDs. Superseded older numeric links remain in Lineage. | O6: Include in final synthesis | P6: Retained concept: The simulation model shall specify the required resource category for each activity that requires resources. Final path: OCPS-R5.1. Recorded catalogue synthesis: Specifies the required resource category; required resource quantity is specified separately under R5.2. Direct source-to-candidate inputs: BPS-013; BPS-015; BPS-017; BPS-030; BPS-057; BPS-062; FND-002; FND-006. This route is retained independently of any intermediate Evidence record; source-specific strength and scope are not inferred from the route alone. | Q6: OCPS-R5; OCPS-R5.1 | R6: EV-AUD-0043 | S6: Source -> Candidate (direct recorded source use); Source -> Evidence -> Candidate; Later verification (separate from original input) | T6: BPS-013; BPS-015; BPS-017; BPS-030; BPS-057; BPS-062; FND-002; FND-006
A7: BPS:LR-RO2 | B7: BPS | C7: LR-RO2 | D7: The simulation model shall specify the required number of resource units for each activity that requires resources. | E7: This requirement states that the model must specify the quantity or cardinality of resources needed before an activity instance can start. For example, an activity may require one clerk, two nurses, or one machine and one operator. This requirement concerns the number of required resource units; it does not determine which concrete resource unit is selected. | H7: Martin et al. (2016)、WfMC/BPSim (2016)、Wagner (2023)、El Kassis et al. (2023) | I7: BPS-013; BPS-017; BPS-058; BPS-062; FND-002; FND-006 | J7: EV-F-0016; EV-F-0017; EV-S-0023; EV-S-0024; EV-S-0025; EV-S-0044; R5-FE-010; R5-FE-011; R5-FE-012; R5-FE-013 | M7: Resource source records distinguish current category, demand quantity, eligibility, selection, availability, supply quantity, performance, queue order, concurrency, attributes, abandonment and batching IDs. Superseded older numeric links remain in Lineage. | O7: Include in final synthesis | P7: Retained concept: The simulation model shall specify the required number of resource units for each activity that requires resources. Final path: OCPS-R5.2. | Q7: OCPS-R5.2 | R7: EV-AUD-0044 | S7: Source -> Evidence -> Candidate; Later verification (separate from original input)
A8: BPS:LR-RO3 | B8: BPS | C8: LR-RO3 | D8: The simulation model shall specify which resources are eligible to execute each activity. | E8: This requirement states that the model must define which resources are allowed to execute a given activity. Eligibility criteria may be based on role, pool, profile, skill, permission, organizational group, or other explicitly modelled resource properties. This requirement concerns whether a resource is eligible; it does not define how one eligible resource is selected when several eligible resources are available. | H8: Martin et al. (2016); WfMC/BPSim (2016); Camargo et al. (2020); Chapela-Campa et al. / SIMOD (2025); Wagner (2023); El Kassis et al. (2023); López-Pintado et al. (2024). Mesabbah & McKeever (2018)、Mesabbah et al. (2019)、Ougaabal et al. (2020) López-Pintado & Dumas (2024/2025), 77-Business | I8: BPS-009; BPS-013; BPS-015; BPS-030; BPS-039; BPS-057; BPS-058; BPS-062; FND-002; FND-006 | J8: EV-F-0018; EV-F-0019; EV-S-0026; EV-S-0027; EV-S-0028; EV-S-0029; EV-S-0030; EV-S-0031; EV-S-0032; R5-FE-014; R5-FE-015; R5-FE-016; R5-FE-017; R5-FE-018; R5-FE-019; R5-FE-020; R5-FE-021; R5-FE-022; R5-FE-023 | M8: Resource source records distinguish current category, demand quantity, eligibility, selection, availability, supply quantity, performance, queue order, concurrency, attributes, abandonment and batching IDs. Superseded older numeric links remain in Lineage. | O8: Include in final synthesis | P8: Retained concept: The simulation model shall specify which resources are eligible to execute each activity. Final path: OCPS-R5.3. Recorded catalogue synthesis: Kept separate from selection among eligible resources. | Q8: OCPS-R5; OCPS-R5.3 | R8: EV-AUD-0045 | S8: Source -> Evidence -> Candidate; Later verification (separate from original input)
A9: BPS:LR-RO4 | B9: BPS | C9: LR-RO4 | D9: The simulation model shall specify the rule for selecting a resource from the eligible resources for an activity instance. | E9: This requirement states that the model must define how a concrete resource is assigned to an activity instance when multiple eligible resources exist. Selection rules may be based on availability, workload, random choice, resource name, role, profile, or other explicitly modelled criteria. This requirement concerns resource selection; it is distinct from queue ordering among activity instances waiting for resources. | H9: WfMC/BPSim (2016); Martin et al. (2016); El Kassis et al. (2023); López-Pintado et al. (2024).López-Pintado & Dumas (2024/2025), 77-Business | I9: BPS-009; BPS-015; BPS-062; FND-002; FND-006 | J9: EV-S-0049; EV-S-0050; R5-FE-024; R5-FE-025; R5-FE-026; R5-FE-027; R5-FE-028 | M9: Resource source records distinguish current category, demand quantity, eligibility, selection, availability, supply quantity, performance, queue order, concurrency, attributes, abandonment and batching IDs. Superseded older numeric links remain in Lineage. | O9: Include in final synthesis | P9: Retained concept: The simulation model shall specify the rule for selecting a resource from the eligible resources for an activity instance. Final path: OCPS-R5.4. Recorded catalogue synthesis: Merged with individualized resource-allocation discussion by making the selection rule explicit rather than creating a duplicate allocation requirement. | Q9: OCPS-R5.4 | R9: EV-AUD-0046 | S9: Source -> Evidence -> Candidate; Later verification (separate from original input)
A10: BPS:LR-RO5 | B10: BPS | C10: LR-RO5 | D10: The simulation model shall specify the availability schedule of each represented resource unit or resource category. | E10: This requirement states that the model must represent the temporal availability of resources. Availability may be represented through calendars, schedules, working-time periods, shifts, breaks, or other explicit time-dependent availability specifications. This requirement concerns when resources can be used; it does not define how many resource units are available. | H10: WfMC (2016); Martin et al. (2016); Chapela-Campa et al. (2025); López-Pintado et al. (2024); Mesabbah et al. (2019)；Camargo et al. 2020, Automated Discovery; Chapela-Campa et al. (2025) 396-Aframewor；López-Pintado & Dumas (2024/2025), 77-Business Wagner、El Kassis、Jadrić、Pourbafrani (supporting / weak / future-work / background) | I10: BPS-006; BPS-009; BPS-013; BPS-015; BPS-030; BPS-032; BPS-034; BPS-039; BPS-057; BPS-058; BPS-062; FND-002; FND-005; FND-006 | J10: EV-F-0020; EV-F-0021; EV-S-0033; EV-S-0034; EV-S-0035; EV-S-0037; EV-S-0038; EV-S-0039; EV-S-0040; EV-S-0041; EV-S-0042; R5-FE-029; R5-FE-030; R5-FE-031; R5-FE-032; R5-FE-033; R5-FE-034; R5-FE-035; R5-FE-036; R5-FE-037; R5-FE-038 | M10: Resource source records distinguish current category, demand quantity, eligibility, selection, availability, supply quantity, performance, queue order, concurrency, attributes, abandonment and batching IDs. Superseded older numeric links remain in Lineage. | O10: Include in final synthesis | P10: Retained concept: The simulation model shall specify the availability schedule of each represented resource unit or resource category. Final path: OCPS-R5.5. | Q10: OCPS-R5.5 | R10: EV-AUD-0047 | S10: Source -> Evidence -> Candidate; Later verification (separate from original input)
A11: BPS:LR-RO6 | B11: BPS | C11: LR-RO6 | D11: The simulation model shall specify the number of available resource units for each resource category. | E11: This requirement states that the model must represent the amount of resource capacity available for activity execution. The number of resource units may be specified for a resource pool, role, profile, group, or individual-resource set. This requirement concerns the number of available units; it does not imply multitasking or concurrent execution unless this is separately specified. | H11: WfMC (2016); Camargo et al. (2020); López-Pintado et al. (2024); Chapela-Campa et al. (2025); van der Aalst et al. (2008). Wagner (2023) DPMN; Chapela-Campa et al. (2025) 396-Aframewor； Mesabbah et al. 2019, A Hybrid Process Mining Framework for Automated Simulation Modelling for Healthcare; | I11: BPS-013; BPS-015; BPS-030; BPS-032; BPS-057; BPS-058; FND-005; FND-006 | J11: EV-F-0022; EV-S-0045; R5-FE-041; R5-FE-042; R5-FE-043; R5-FE-044; R5-FE-045; R5-FE-046; R5-FE-047; R5-FE-048; R5-FE-049 | M11: Resource source records distinguish current category, demand quantity, eligibility, selection, availability, supply quantity, performance, queue order, concurrency, attributes, abandonment and batching IDs. Superseded older numeric links remain in Lineage. | O11: Include in final synthesis | P11: Retained concept: The simulation model shall specify the number of available resource units for each resource category. Final path: OCPS-R5.6; OCPS-R5.6.1. Recorded catalogue synthesis: Retained as the capacity-quantity requirement, separate from availability schedules in R5.5 and refined by shared capacity in R5.6.1. Direct source-to-candidate inputs: BPS-057. This route is retained independently of any intermediate Evidence record; source-specific strength and scope are not inferred from the route alone. | Q11: OCPS-R5.6; OCPS-R5.6.1 | R11: EV-AUD-0048 | S11: Source -> Candidate (direct recorded source use); Source -> Evidence -> Candidate; Later verification (separate from original input) | T11: BPS-057
A12: BPS:LR-RO7 | B12: BPS | C12: LR-RO7 | D12: The simulation model shall allow the processing time of an activity instance to depend on the executing resource or resource profile. | E12: This requirement states that the model must support resource-dependent processing-time behaviour when different resources or resource profiles execute the same activity at different speeds. Processing-time parameters may be specified by resource, resource profile, role, pool, or another explicitly modelled resource classification. This requirement concerns processing-time variation; it does not require all possible resource attributes to be modelled unless those attributes are explicitly used to determine performance parameters. | H12: López-Pintado et al. (2024); Chapela-Campa et al. (2025); Ougaabal et al. (2020); Martin et al. (2016)；López-Pintado & Dumas 2024, 77-Business | I12: BPS-009; BPS-013; BPS-015; BPS-017; FND-002; FND-004; FND-005 | J12: EV-F-0023; EV-F-0024; EV-F-0025; EV-S-0046; EV-S-0047; EV-S-0048; R5-FE-053; R5-FE-054; R5-FE-055; R5-FE-056; R5-FE-057 | M12: Resource source records distinguish current category, demand quantity, eligibility, selection, availability, supply quantity, performance, queue order, concurrency, attributes, abandonment and batching IDs. Superseded older numeric links remain in Lineage. | O12: Include in final synthesis | P12: Retained concept: The simulation model shall allow the processing time of an activity instance to depend on the executing resource or resource profile. Final path: OCPS-R5.10; OCPS-R5.7. Recorded catalogue synthesis: Kept as conditional resource-performance requirement. | Q12: OCPS-R5.10; OCPS-R5.7 | R12: EV-AUD-0050 | S12: Source -> Evidence -> Candidate; Later verification (separate from original input)
A13: BPS:LR-RO8 | B13: BPS | C13: LR-RO8 | D13: The simulation model shall specify the queue ordering rule for activity instances waiting for resources. | E13: This requirement states that the model must define how activity instances are ordered when they wait because required resources are unavailable. Queue ordering may follow FIFO, LIFO, priority-based ordering, or another explicitly defined rule. This requirement concerns ordering among waiting activity instances; it is distinct from selecting a concrete resource unit. | H13: Martin et al. (2016); WfMC BPSim (2016); Camargo et al. (2020), Automated Discovery of Business Process Simulation Models from Event Logs; López-Pintado et al. (2024), Discovery, Simulation, and Optimization of Business Processes with Differentiated Resources; Chapela-Campa et al. (2025), SIMOD: Automated Discovery of Business Process Simulation Models; | I13: BPS-009; BPS-013; BPS-015; BPS-030; BPS-058; FND-002; FND-004; FND-006 | J13: EV-F-0026; EV-F-0027; EV-F-0028; EV-S-0050; EV-S-0051; R5-FE-058; R5-FE-059; R5-FE-060; R5-FE-061; R5-FE-062 | M13: Resource source records distinguish current category, demand quantity, eligibility, selection, availability, supply quantity, performance, queue order, concurrency, attributes, abandonment and batching IDs. Superseded older numeric links remain in Lineage. | O13: Include in final synthesis | P13: Retained concept: The simulation model shall specify the queue ordering rule for activity instances waiting for resources. Final path: OCPS-R5.8. Recorded catalogue synthesis: Specifies ordering under resource contention. Explicit non-processing delays are specified under R4.3 and object temporal readiness under R4.4. Direct source-to-candidate inputs: BPS-013; BPS-015; BPS-030. This route is retained independently of any intermediate Evidence record; source-specific strength and scope are not inferred from the route alone. | Q13: OCPS-R5.8 | R13: EV-AUD-0051 | S13: Source -> Candidate (direct recorded source use); Source -> Evidence -> Candidate; Later verification (separate from original input) | T13: BPS-013; BPS-015; BPS-030
A14: BPS:LR-RO9 | B14: BPS | C14: LR-RO9 | D14: The simulation model shall specify the concurrent execution limit of each resource unit that can execute multiple activity instances at the same time. | E14: This requirement applies only when a resource unit can process multiple activity instances concurrently. It requires the model to specify the maximum number of activity instances that a single resource unit can execute at the same time. This requirement should not be used as the general definition of resource capacity, because core resource capacity is already captured by the number of available resource units. | H14: López-Pintado, O., & Dumas, M. (2025), Business Process Simulation: Probabilistic Modeling of Intermittent Resource Availability and Multitasking Behavior; Martin, N., Depaire, B., & Caris, A. (2016), The Use of Process Mining in Business Process Simulation Model Construction: Structuring the Field. | I14: BPS-009; FND-002 | J14: EV-S-0043; R5-FE-064; R5-FE-065 | M14: Resource source records distinguish current category, demand quantity, eligibility, selection, availability, supply quantity, performance, queue order, concurrency, attributes, abandonment and batching IDs. Superseded older numeric links remain in Lineage. | O14: Include in final synthesis | P14: Retained concept: The simulation model shall specify the concurrent execution limit of each resource unit that can execute multiple activity instances at the same time. Final path: OCPS-R5.9. Recorded catalogue synthesis: Classified as conditional implementation-related feature. Direct source-to-candidate inputs: BPS-009; FND-002. This route is retained independently of any intermediate Evidence record; source-specific strength and scope are not inferred from the route alone. | Q14: OCPS-R5.9 | R14: EV-AUD-0052 | S14: Source -> Candidate (direct recorded source use); Source -> Evidence -> Candidate; Later verification (separate from original input) | T14: BPS-009; FND-002
A15: BPS:LR-RO10 | B15: BPS | C15: LR-RO10 | D15: The simulation model shall specify the resource attributes that determine activity performance parameters when such attributes are used in the model. | E15: This requirement applies only when resource attributes affect activity performance. Such attributes may include skill, experience, workload, reliability, throughput, or other explicitly modelled resource properties. This requirement requires the model to identify which resource attributes determine performance parameters; it does not require all such attributes to be modelled in every simulation model. | H15: Martin et al. (2016); Ougaabal et al. (2020)；López-Pintado et al. (2024); Chapela-Campa et al. (2025); Wagner (2023) DPMN; López-Pintado & Dumas 2024, 77-Business； | I15: BPS-009; BPS-013; BPS-015; BPS-017; BPS-058; FND-002 | J15: R5-FE-066; R5-FE-067; R5-FE-068; R5-FE-069; R5-FE-070; R5-FE-071 | M15: Resource source records distinguish current category, demand quantity, eligibility, selection, availability, supply quantity, performance, queue order, concurrency, attributes, abandonment and batching IDs. Superseded older numeric links remain in Lineage. | O15: Include in final synthesis | P15: Retained concept: The simulation model shall specify the resource attributes that determine activity performance parameters when such attributes are used in the model. Final path: OCPS-R5.10. Recorded catalogue synthesis: Classified as conditional implementation-related feature. | Q15: OCPS-R5.10 | R15: EV-AUD-0053 | S15: Source -> Evidence -> Candidate; Later verification (separate from original input)
A16: BPS:LR-RO11 | B16: BPS | C16: LR-RO11 | D16: The simulation model shall specify the queue-leaving condition for activity instances that may leave a queue before receiving service. | E16: This requirement applies only when queue abandonment, reneging, timeout, or queue switching is part of the process domain. It requires the model to specify the condition under which an activity instance leaves a queue before receiving service, such as a waiting-time threshold, queue-length threshold, probability rule, or other explicitly stated condition. This requirement should not be treated as a core requirement for every resource-constrained simulation model. | H16: Martin et al. (2016); Wagner (2023) DPMN; | I16: BPS-058; FND-002 | J16: R5-FE-072; R5-FE-073 | M16: Resource source records distinguish current category, demand quantity, eligibility, selection, availability, supply quantity, performance, queue order, concurrency, attributes, abandonment and batching IDs. Superseded older numeric links remain in Lineage. | O16: Include in final synthesis | P16: Retained concept: The simulation model shall specify the queue-leaving condition for activity instances that may leave a queue before receiving service. Final path: OCPS-R5.11. Recorded catalogue synthesis: Retained as a conditional queue-behaviour requirement; absence of abandonment makes it inapplicable rather than optional. | Q16: OCPS-R5.11 | R16: EV-AUD-0054 | S16: Source -> Evidence -> Candidate; Later verification (separate from original input)
A17: BPS:LR-RO12 | B17: BPS | C17: LR-RO12 | D17: The simulation model shall specify the batch execution condition for activity instances that are executed as a batch. | E17: This requirement applies only when activity instances are processed together as a batch. The batch execution condition may depend on the number of pending activity instances, similarity of work items, entity type, activity type, system state, backlog level, scheduled processing time, or another explicitly stated condition. If maximum waiting time is used as a batch release condition, it should be supported by additional domain evidence or batching-specific literature. | H17: Martin et al. (2016); Chapela-Campa et al. (2025); van der Aalst et al. (2008); Camargo et al. (2020 as gap evidence) | I17: BPS-013; FND-002; FND-005 | J17: R5-FE-074; R5-FE-075; R5-FE-076 | M17: Resource source records distinguish current category, demand quantity, eligibility, selection, availability, supply quantity, performance, queue order, concurrency, attributes, abandonment and batching IDs. Superseded older numeric links remain in Lineage. | O17: Include in final synthesis | P17: Retained concept: The simulation model shall specify the batch execution condition for activity instances that are executed as a batch. Final path: OCPS-R5.12. Recorded catalogue synthesis: Retained as a conditional batch-behaviour requirement; batch rules are required whenever batching is in scope. | Q17: OCPS-R5.12 | R17: EV-AUD-0055 | S17: Source -> Evidence -> Candidate; Later verification (separate from original input)
A18: BPS:LR-TS1 | B18: BPS | C18: LR-TS1 | D18: The simulation model shall specify the arrival process of cases or entities entering the simulated system. | E18: The model must define when and how new cases, process instances, customers, patients, orders, or other entities enter the simulated system. The arrival process may be represented by inter-arrival times, arrival rates, arrival calendars, time windows, empirical histograms, or fitted probability distributions. | H18: Banks et al., Discrete-Event System Simulation; WfMC, Business Process Simulation Specification；Camargo et al., Automated discovery of business process simulation models from event logs;Martin et al., The Use of Process Mining in Business Process Simulation Model Construction; Rosenthal et al., Business Process Simulation on Procedural Graphical Process Models；Mesabbah & McKeever, ASMB（660）；Chapela-Campa et al., SIMOD（92） | I18: BPS-006; BPS-013; BPS-030; BPS-039; FND-001; FND-002; FND-006; FND-007 | J18: EV-F-0029; EV-F-0071; EV-S-0052; EV-S-0053; TP-E005; TP-E011; TP-E015; TP-E018; TP-E020; TP-E023-A; TP-E026 | O18: Include in final synthesis | P18: Retained concept: The simulation model shall specify the arrival process of cases or entities entering the simulated system. Final path: OCPS-R1.2; OCPS-R2.1.1; OCPS-R2.1.2; OCPS-R2.2.1; OCPS-R2.2.2. Recorded catalogue synthesis: Added parent node because the existing R2.1.x rows are all object-generation rule variants. Direct source-to-candidate inputs: BPS-030; FND-006. This route is retained independently of any intermediate Evidence record; source-specific strength and scope are not inferred from the route alone. | Q18: OCPS-R1.2; OCPS-R2; OCPS-R2.1; OCPS-R2.1.1; OCPS-R2.1.2; OCPS-R2.2; OCPS-R2.2.1; OCPS-R2.2.2 | S18: Source -> Candidate (direct recorded source use); Source -> Evidence -> Candidate | T18: BPS-030; FND-006
A19: BPS:LR-TS2 | B19: BPS | C19: LR-TS2 | D19: The simulation model shall specify activity durations. | E19: The model must define the execution time of each activity with non-zero execution time. Activity durations may be specified as deterministic values or as parameterized functions of explicitly modelled factors, such as case attributes, resource characteristics, or system state. Stochastic representations (e.g., empirical or fitted probability distributions) are permitted at the level of activity duration specification. | H19: Banks et al., Discrete-Event System Simulation; WfMC, Business Process Simulation Specification; Martin et al., The Use of Process Mining in Business Process Simulation Model Construction;Camargo et al., Automated discovery of business process simulation models from event logs; Rosenthal et al., Business Process Simulation on Procedural Graphical Process Models；Mesabbah & McKeever, ASMB（660） | I19: BPS-005; BPS-006; BPS-013; BPS-016; BPS-025; BPS-027; BPS-030; BPS-039; BPS-052; FND-001; FND-002; FND-006; FND-007 | J19: EV-F-0030; EV-F-0072; EV-S-0054; EV-S-0060; EV-S-0061; EV-S-0062; EV-S-0063; TP-E006; TP-E012; TP-E016; TP-E019; TP-E021; TP-E023-D; TP-E025; TP-E027 | O19: Include in final synthesis | P19: Retained concept: The simulation model shall specify activity durations. Final path: OCPS-R4.1; OCPS-R4.2. Recorded catalogue synthesis: Merged activity duration and object-centric event duration requirements. Time trace check: timestamp advancement is retained under delay evidence. Start-to-completion service time uses a separate checked OPerA definition. Direct source-to-candidate inputs: BPS-030; FND-006. This route is retained independently of any intermediate Evidence record; source-specific strength and scope are not inferred from the route alone. | Q19: OCPS-R4; OCPS-R4.1; OCPS-R4.2 | R19: EV-AUD-0036 | S19: Source -> Candidate (direct recorded source use); Source -> Evidence -> Candidate; Later verification (separate from original input) | T19: BPS-030; FND-006
A20: BPS:LR-TS3 | B20: BPS | C20: LR-TS3 | D20: When waiting before activity execution is explicitly modelled, the simulation model shall specify the rule or mechanism that determines it. | E20: Waiting may result from resource unavailability, queueing, or an explicitly modelled pre-execution delay. Detailed queue discipline, priority, capacity, and resource-allocation rules are specified under the relevant resource or control-flow requirements. | H20: Banks et al., Discrete-Event System Simulation; WfMC, Business Process Simulation Specification; Martin et al., The Use of Process Mining in Business Process Simulation Model Construction - Structuring the Field; Chapela-Campa et al., Can I Trust My Simulation Model? Measuring the Quality of Business Process Simulation Models; Camargo et al., Learning Accurate Business Process Simulation Models from Event Logs via Automated Process Discovery and Deep Learning; Camargo et al., Learning business process simulation models: A Hybrid process mining and deep learning approach; Camargo et al., Automated discovery of business process simulation models from event logs. | I20: BPS-010; BPS-013; BPS-030; BPS-041; BPS-052; FND-001; FND-002; FND-006; FND-007 | J20: EV-F-0031; EV-F-0032; EV-F-0073; EV-S-0055; EV-S-0056; EV-S-0057; EV-S-0058; EV-S-0061; TP-E007; TP-E014; TP-E017; TP-E028; TP-E030; TP-E031; TP-E033 | O20: Include in final synthesis | P20: Retained concept: When waiting before activity execution is explicitly modelled, the simulation model shall specify the rule or mechanism that determines it. Final path: OCPS-R3.3.2; OCPS-R4.3; OCPS-R4.4; OCPS-R5.8. Direct source-to-candidate inputs: BPS-010; BPS-030; BPS-041; BPS-052; FND-002; FND-006. This route is retained independently of any intermediate Evidence record; source-specific strength and scope are not inferred from the route alone. | Q20: OCPS-R3.3.2; OCPS-R4.3; OCPS-R4.4; OCPS-R5.8 | R20: EV-AUD-0038 | S20: Source -> Candidate (direct recorded source use); Source -> Evidence -> Candidate; Later verification (separate from original input) | T20: BPS-010; BPS-030; BPS-041; BPS-052; FND-002; FND-006
A21: BPS:LR-TS4 | B21: BPS | C21: LR-TS4 | D21: When simulated time directly triggers process behavior, the simulation model shall specify the corresponding trigger condition. | E21: This requirement covers timer events, timeouts, recurring temporal events, deadlines whose expiry triggers modelled behaviour, and explicitly modelled timed transitions or time-driven state changes. The trigger may be defined by an absolute date or time, an elapsed duration measured from a specified reference point, a recurring interval, or a stochastic timing rule from which the trigger time or delay is sampled. Activity execution durations and passive delays are specified separately. | H21: Dumas et al. (2018); WfMC (2016); Kalenkova 2025, Discovering Semi-Markov Models (73); Vitale 2026, Process Mining-driven Modeling and Simulation (63); Tsinarakis et al. 2022, Discrete Process Modelling and DT (312); | I21: BPS-005; BPS-007; BPS-028; FND-001; FND-006 | J21: TP-E008; TP-E014; TP-E014-B; TP-E035; TP-E036; TP-E037 | O21: Include in final synthesis | P21: Retained concept: When simulated time directly triggers process behavior, the simulation model shall specify the corresponding trigger condition. Final path: OCPS-R4.5. Recorded catalogue synthesis: Retained for time-triggered behaviour, distinct from execution duration and passive performance targets. | Q21: OCPS-R4.5 | R21: EV-AUD-0040 | S21: Source -> Evidence -> Candidate; Later verification (separate from original input)
A22: BPS:LR-TS5 | B22: BPS | C22: LR-TS5 | D22: The simulation model shall specify the simulation time unit. | E22: The model must specify the time unit used to interpret temporal parameters and simulated outputs, such as seconds, minutes, hours, days, or another consistent unit. | H22: Banks et al., Discrete-Event System Simulation; Renna, P., & Colonnese, C. (2025). Process transformation at the University of Basilicata: Mapping, digitalization, and enhanced transparenc; Workflow Management Coalition. (2016). Business process simulation specification; | I22: BPS-026; FND-006; FND-007 | J22: EV-F-0033; EV-F-0074; EV-S-0064; TP-E009; TP-E042 | O22: Include in final synthesis | P22: Retained concept: The simulation model shall specify the simulation time unit. Final path: OCPS-R4.6. Recorded catalogue synthesis: Kept as a concrete configuration requirement rather than generic parameterization. Direct source-to-candidate inputs: FND-006. This route is retained independently of any intermediate Evidence record; source-specific strength and scope are not inferred from the route alone. | Q22: OCPS-R4.6 | R22: EV-AUD-0041 | S22: Source -> Candidate (direct recorded source use); Source -> Evidence -> Candidate; Later verification (separate from original input) | T22: FND-006
A23: BPS:LR-TS6 | B23: BPS | C23: LR-TS6 | D23: The simulation model shall define the simulation horizon. | E23: The model must define the temporal scope of a simulation run, including the start point and termination point of the simulated observation period. | H23: Workflow Management Coalition. (2016). Business process simulation specification (Version 2.0); Dumas et al. (2018), p.282；Rosenthal et al. (2021), Sec. 2.1； Aalst 2010, Business Process Simulation Revisited; Banks et al. (2005)，Discrete-event system simulation (4th ed.); Tsinarakis, G., Sarantinoudis, N., & Arampatzis, G. (2022). A discrete process modelling and simulation methodology for industrial systems within the concept of digital twins; Mesabbah, M., & McKeever, S. (2018). Presenting a hybrid processing mining framework for automated simulation model generation | I23: BPS-006; BPS-028; BPS-039; FND-001; FND-003; FND-006; FND-007 | J23: EV-B4-0001; EV-F-0034; EV-F-0035; EV-S-0065; EV-S-0066; TP-E010; TP-E013; TP-E022; TP-E024; TP-E038 | O23: Include in final synthesis | P23: Retained concept: The simulation model shall define the simulation horizon. Final path: OCPS-R4.7. Recorded catalogue synthesis: Kept as a concrete configuration requirement rather than generic scenario/what-if wording. Direct source-to-candidate inputs: BPS-028; BPS-039; FND-003; FND-006. This route is retained independently of any intermediate Evidence record; source-specific strength and scope are not inferred from the route alone. | Q23: OCPS-R4.7 | R23: EV-AUD-0042 | S23: Source -> Candidate (direct recorded source use); Source -> Evidence -> Candidate; Later verification (separate from original input) | T23: BPS-028; BPS-039; FND-003; FND-006
A24: BPS:LR-TS7 | B24: BPS | C24: LR-TS7 | D24: The model shall produce timestamped simulation output. | E24: The model should generate sufficient temporal information, such as object arrival times and activity start and completion times, to calculate performance indicators including waiting time, service time, sojourn time, flow time, synchronization time, pooling time, and lagging time. | H24: Camargo et al., Learning accurate business process simulation models from event logs via automated process discovery and deep learning; Chapela-Campa et al., SIMOD: Automated discovery of business process simulation models; Fairooz et al., Enhancing Process Mining on Sparse Event Logs: A Simulation-Driven Academic Case Study. | I24: BPS-013; BPS-052; BPS-054 | J24: EV-S-0067; EV-S-0068 | O24: Use in adaptation; no final requirement retained | P24: The BPS statement requires timestamped simulation output and names performance measures, but the final catalogue contains no requirement for emitting timestamped output or for calculating that complete indicator set. The adapted TS-010, TS-011 and TS-012 statements are also absent from the final catalogue. R1.9.2/R1.9.3 and the R4 timing rows are adjacent concepts, not faithful absorption of the output obligation. Direct source-to-candidate inputs: BPS-013; BPS-052; BPS-054. This route is retained independently of any intermediate Evidence record; source-specific strength and scope are not inferred from the route alone. | S24: Source -> Candidate (direct recorded source use); Source -> Evidence -> Candidate | T24: BPS-013; BPS-052; BPS-054
A25: OCPM:OCPM-DR-001 | B25: OCPM | C25: OCPM-DR-001 | D25: The simulation model shall use an OCEL/OCED-compatible object-centric event data structure rather than a flattened single-case log. | E25: The model must explicitly represent event types, events, timestamps, object types, object instances, event attributes, object attributes, and event-to-object relations so that simulated process behavior can be traced across multiple interacting objects. | H25: OCEL 2.0 Specification; Towards a Simple and Extensible Standard for Object-Centric Event Data; Object-Centric Process Mining: Unraveling the Fabric of Real Processes; Object-Centric Process Mining: Concepts and Advancements; Multi-Dimensional Event Data in Graph Databases | I25: SUP-001; SUP-002; SUP-008; SUP-010; SUP-011; SUP-013; SUP-014; SUP-015 | J25: EV-O-0002; EV-O-0005; EV-O-0013; EV-O-0016; EV-O-0017; EV-O-0019; EV-O-0036; EV-O-0042; EV-O-0043; EV-O-0044; EV-O-0045; EV-O-0046; EV-O-0049; EV-O-0050; EV-O-0052; EV-O-0053 | M25: Merged the general object-centric data-structure, anti-flattening, graph-compatible event-data, and conceptual OCPM foundation requirements. | O25: Include in final synthesis | P25: Retained concept: The simulation model shall use an OCEL/OCED-compatible object-centric event data structure rather than a flattened single-case log. Final path: OCPS-R1.1; OCPS-R1.2; OCPS-R1.3; OCPS-R1.5.1; OCPS-R1.5.2; OCPS-R1.6; OCPS-R1.7.1; OCPS-R1.7.2; OCPS-R1.9.1; OCPS-R3.4.1. Recorded catalogue synthesis: Merged the case-centric activity requirement with OCEL/OCED event-type terminology. Direct source-to-candidate inputs: SUP-001; SUP-002; SUP-010; SUP-011; SUP-013. This route is retained independently of any intermediate Evidence record; source-specific strength and scope are not inferred from the route alone. | Q25: OCPS-R1; OCPS-R1.1; OCPS-R1.2; OCPS-R1.3; OCPS-R1.5; OCPS-R1.5.1; OCPS-R1.5.2; OCPS-R1.6; OCPS-R1.7.1; OCPS-R1.7.2; OCPS-R1.9.1; OCPS-R3.4.1 | R25: EV-AUD-0002 | S25: Source -> Candidate (direct recorded source use); Source -> Evidence -> Candidate; Later verification (separate from original input) | T25: SUP-001; SUP-002; SUP-010; SUP-011; SUP-013
A26: OCPM:OCPM-DR-002 | B26: OCPM | C26: OCPM-DR-002 | D26: The simulation model shall represent object-to-object relationships and relation types. | E26: The model must define structural relations among object instances, including relation type, cardinality or multiplicity where needed, and how related objects constrain generation, routing, and analysis. | H26: OCEL 2.0 Specification; Automated Digital Twin Generation of Manufacturing Systems with Complex Material Flows; Analyzing Interconnected Processes: Using Object-Centric Process Mining to Analyze Procurement Processes; Dirigo: A Method to Extract Event Logs for Object-Centric Processes; Multi-Dimensional Event Data in Graph Databases; Knopp (2023) - Towards Organizational Digital Twins: Process Enhancement by Object-Centric Simulation | I26: BPS-018; BPS-037; SUP-001; SUP-002; SUP-007; SUP-008; SUP-013 | J26: EV-O-0003; EV-O-0005; EV-O-0013; EV-O-0014; EV-O-0019; EV-O-0021; EV-O-0055; EV-S-0139; EV-S-0141; EV-S-0142 | M26: Merged O2O relationships, material-flow object dependencies, process-scope object relations, graph-style structural relations, and relation-generation evidence. Manufacturing/material-flow evidence is domain-specific and should be used only as supplementary support. 2026-10-14 relation-change trace: Verified source premise: dynamic O2O relations have identifiable expected change situations and activity/lifecycle triggers (Dirigo QC3.b). OCPM-DR-003 retains this dynamic relation concept alongside attributes/state; OCPM-DR-002 supplies the relation structure. OCPS-DR-010 isolates relation changes. Simulation adaptation: to produce a changing relation state, specify the applicable update operation and its event/lifecycle/condition trigger. R1.8.1 retains that governing-rule requirement. This is a source-informed simulation design derivation, not a claim that Dirigo implements a simulation engine. 2026-10-14: the attribute-dependent generation contribution from supplementary ID 22 is an author design extension. General relation/multiplicity generation remains source-backed; R2.1.4 and R2.1.5 are not attributed as explicitly published rules. | N26: Merged O2O relationships, material-flow object dependencies, process-scope object relations, graph-style structural relations, and relation-generation evidence. Manufacturing/material-flow evidence is domain-specific and should be used only as supplementary support. 2026-10-14 relation-change trace: Verified source premise: dynamic O2O relations have identifiable expected change situations and activity/lifecycle triggers (Dirigo QC3.b). OCPM-DR-003 retains this dynamic relation concept alongside attributes/state; OCPM-DR-002 supplies the relation structure. OCPS-DR-010 isolates relation changes. Simulation adaptation: to produce a changing relation state, specify the applicable update operation and its event/lifecycle/condition trigger. R1.8.1 retains that governing-rule requirement. This is a source-informed simulation design derivation, not a claim that Dirigo implements a simulation engine. 2026-10-14: the attribute-dependent generation contribution from supplementary ID 22 is an author design extension. General relation/multiplicity generation remains source-backed; R2.1.4 and R2.1.5 are not attributed as explicitly published rules. | O26: Include in final synthesis | P26: Retained concept: The simulation model shall represent object-to-object relationships and relation types. Final path: OCPS-R1.8; OCPS-R1.8.1; OCPS-R2.1.2; OCPS-R3.3.3.1. Recorded synthesis: Merged O2O relationships, material-flow object dependencies, process-scope object relations, graph-style structural relations, and relation-generation evidence. Manufacturing/material-flow evidence is domain-specific and should be used only as supplementary support. 2026-10-14 relation-change trace: Verified source premise: dynamic O2O relations have identifiable expected change situations and activity/lifecycle triggers (Dirigo QC3.b). OCPM-DR-003 retains this dynamic relation concept alongside attributes/state; OCPM-DR-002 supplies the relation structure. OCPS-DR-010 isolates relation changes. Simulation adaptation: to produce a changing relation state, specify the applicable update operation and its event/lifecycle/condition trigger. R1.8.1 retains that governing-rule requirement. This is a source-informed simulation design derivation, not a claim that Dirigo implements a simulation engine. 2026-10-14: the attribute-dependent generation contribution from supplementary ID 22 is an author design extension. General relation/multiplicity generation remains source-backed; R2.1.4 and R2.1.5 are not attributed as explicitly published rules. Direct source-to-candidate inputs: BPS-037; SUP-001; SUP-007; SUP-008; SUP-013. This route is retained independently of any intermediate Evidence record; source-specific strength and scope are not inferred from the route alone. | Q26: OCPS-R1.8; OCPS-R1.8.1; OCPS-R2.1.2; OCPS-R3.3.3.1 | R26: EV-AUD-0010; EV-AUD-0059; EV-AUD-0065; EV-AUD-0070; EV-AUD-0074 | S26: Source -> Candidate (direct recorded source use); Source -> Evidence -> Candidate; Later verification (separate from original input) | T26: BPS-037; SUP-001; SUP-007; SUP-008; SUP-013
A27: OCPM:OCPM-DR-003 | B27: OCPM | C27: OCPM-DR-003 | D27: The simulation model shall represent time-dependent object attributes, object states, and changing object relationships when required. | E27: The model should support changes in object attribute values, object states, and object-to-object relationships over simulation time, using timestamped values, explicit state-transition events, relation validity intervals, temporal snapshots, or an equivalent OCEL/OCED-compatible encoding. For dynamic O2O relations, identify expected change situations and their activity/lifecycle triggers (Dirigo QC3.b, PDF pp.10–11); the simulation governing rule is made explicit in OCPS-DR-010. | H27: OCEL 2.0 Specification; Dirigo: A Method to Extract Event Logs for Object-Centric Processes; State-Aware Object-Centric Process Mining: Enhancing OCEL 2.0 with Explicit State Transitions; Multi-Dimensional Event Data in Graph Databases | I27: SUP-001; SUP-008; SUP-009; SUP-011; SUP-013; SUP-014 | J27: EV-O-0004; EV-O-0014; EV-O-0015; EV-O-0019; EV-O-0047; EV-O-0057; EV-O-0058; EV-O-0059; EV-O-0060; EV-O-0076; EV-O-0077; EV-O-0078; EV-O-0079 | M27: Kept as an advanced object-centric data requirement. It is relevant for simulation design when the simulated objects or relations evolve over time, but it may be scoped out of implementation if not needed in the case study. 2026-10-14 relation-change trace: Verified source premise: dynamic O2O relations have identifiable expected change situations and activity/lifecycle triggers (Dirigo QC3.b). OCPM-DR-003 retains this dynamic relation concept alongside attributes/state; OCPM-DR-002 supplies the relation structure. OCPS-DR-010 isolates relation changes. Simulation adaptation: to produce a changing relation state, specify the applicable update operation and its event/lifecycle/condition trigger. R1.8.1 retains that governing-rule requirement. This is a source-informed simulation design derivation, not a claim that Dirigo implements a simulation engine. | N27: Kept as an advanced object-centric data requirement. It is relevant for simulation design when the simulated objects or relations evolve over time, but it may be scoped out of implementation if not needed in the case study. 2026-10-14 relation-change trace: Verified source premise: dynamic O2O relations have identifiable expected change situations and activity/lifecycle triggers (Dirigo QC3.b). OCPM-DR-003 retains this dynamic relation concept alongside attributes/state; OCPM-DR-002 supplies the relation structure. OCPS-DR-010 isolates relation changes. Simulation adaptation: to produce a changing relation state, specify the applicable update operation and its event/lifecycle/condition trigger. R1.8.1 retains that governing-rule requirement. This is a source-informed simulation design derivation, not a claim that Dirigo implements a simulation engine. | O27: Include in final synthesis | P27: Retained concept: The simulation model shall represent time-dependent object attributes, object states, and changing object relationships when required. Final path: OCPS-R1.7.2; OCPS-R1.8.1; OCPS-R1.9.1; OCPS-R1.9.2; OCPS-R1.9.3; OCPS-R3.3.3.1; OCPS-R4.5. Recorded synthesis: Kept as an advanced object-centric data requirement. It is relevant for simulation design when the simulated objects or relations evolve over time, but it may be scoped out of implementation if not needed in the case study. 2026-10-14 relation-change trace: Verified source premise: dynamic O2O relations have identifiable expected change situations and activity/lifecycle triggers (Dirigo QC3.b). OCPM-DR-003 retains this dynamic relation concept alongside attributes/state; OCPM-DR-002 supplies the relation structure. OCPS-DR-010 isolates relation changes. Simulation adaptation: to produce a changing relation state, specify the applicable update operation and its event/lifecycle/condition trigger. R1.8.1 retains that governing-rule requirement. This is a source-informed simulation design derivation, not a claim that Dirigo implements a simulation engine. Direct source-to-candidate inputs: SUP-001; SUP-008; SUP-009; SUP-013. This route is retained independently of any intermediate Evidence record; source-specific strength and scope are not inferred from the route alone. | Q27: OCPS-R1.7.2; OCPS-R1.8.1; OCPS-R1.9; OCPS-R1.9.1; OCPS-R1.9.2; OCPS-R1.9.3; OCPS-R3.3.3.1; OCPS-R4; OCPS-R4.5 | R27: EV-AUD-0012; EV-AUD-0014; EV-AUD-0066; EV-AUD-0069; EV-AUD-0071 | S27: Source -> Candidate (direct recorded source use); Source -> Evidence -> Candidate; Later verification (separate from original input) | T27: SUP-001; SUP-008; SUP-009; SUP-013
A28: OCPM:OCPM-DR-004 | B28: OCPM | C28: OCPM-DR-004 | D28: The simulation model shall specify object-generation and object-relation generation rules. | E28: The model must define how object instances are created during simulation, including object types, generation timing, cardinalities or multiplicities, related-object sets, and attribute- or relation-dependent object-to-object relation generation rules. | H28: Discovering Object-Centric Process Simulation Models; Toward More Realistic Simulation Models Using Object-Centric Process Mining; Towards Organizational Digital Twins: Process Enhancement by Object-Centric Simulation; Knopp (2023) - Towards Organizational Digital Twins: Process Enhancement by Object-Centric Simulation | I28: SUP-003; SUP-006; SUP-007 | J28: EV-O-0006; EV-O-0010; EV-O-0012; EV-O-0021; EV-O-0034; EV-O-0035; EV-O-0070 | M28: Merged object-generation and object-to-object relation generation requirements. Timing-specific arrival/generation behavior remains separated under OCPM-TS-001. 2026-10-14: the attribute-dependent generation contribution from supplementary ID 22 is an author design extension. General relation/multiplicity generation remains source-backed; R2.1.4 and R2.1.5 are not attributed as explicitly published rules. | N28: Merged object-generation and object-to-object relation generation requirements. Timing-specific arrival/generation behavior remains separated under OCPM-TS-001. 2026-10-14: the attribute-dependent generation contribution from supplementary ID 22 is an author design extension. General relation/multiplicity generation remains source-backed; R2.1.4 and R2.1.5 are not attributed as explicitly published rules. | O28: Include in final synthesis | P28: Retained concept: The simulation model shall specify object-generation and object-relation generation rules. Final path: OCPS-R2.1.1; OCPS-R2.1.2; OCPS-R2.2.1; OCPS-R2.2.2; OCPS-R3.3.1. Recorded synthesis: Merged object-generation and object-to-object relation generation requirements. Timing-specific arrival/generation behavior remains separated under OCPM-TS-001. 2026-10-14: the attribute-dependent generation contribution from supplementary ID 22 is an author design extension. General relation/multiplicity generation remains source-backed; R2.1.4 and R2.1.5 are not attributed as explicitly published rules. Direct source-to-candidate inputs: SUP-003; SUP-006; SUP-007. This route is retained independently of any intermediate Evidence record; source-specific strength and scope are not inferred from the route alone. | Q28: OCPS-R2; OCPS-R2.1; OCPS-R2.1.1; OCPS-R2.1.2; OCPS-R2.2; OCPS-R2.2.1; OCPS-R2.2.2; OCPS-R3.3.1 | R28: EV-AUD-0015; EV-AUD-0016; EV-AUD-0067 | S28: Source -> Candidate (direct recorded source use); Source -> Evidence -> Candidate; Later verification (separate from original input) | T28: SUP-003; SUP-006; SUP-007
A29: OCPM:OCPM-CF-001 | B29: OCPM | C29: OCPM-CF-001 | D29: The simulation model shall represent object-typed process-control elements. | E29: The process model must distinguish the object types that participate in process behavior, for example through object-typed places, typed tokens, object-centric Petri-net elements, or an equivalent object-aware control-flow representation. | H29: Discovering Object-Centric Petri Nets; Object-Centric Process Mining: Concepts and Advancements | I29: SUP-004; SUP-011 | J29: EV-O-0007; EV-O-0017; EV-O-0025 | M29: Kept atomic by focusing on object-typed control-flow representation, not full behavioral execution semantics. | O29: Include in final synthesis | P29: Retained concept: The simulation model shall represent object-typed process-control elements. Final path: OCPS-R3.1.1; OCPS-R3.1.2; OCPS-R3.1.3; OCPS-R3.1.4; OCPS-R3.1.5; OCPS-R3.2; OCPS-R3.4.4. Recorded catalogue synthesis: Retained case-centric baseline and interpreted it as event-type ordering in OCPS. Direct source-to-candidate inputs: SUP-004; SUP-011. This route is retained independently of any intermediate Evidence record; source-specific strength and scope are not inferred from the route alone. | Q29: OCPS-R3; OCPS-R3.1; OCPS-R3.1.1; OCPS-R3.1.2; OCPS-R3.1.3; OCPS-R3.1.4; OCPS-R3.1.5; OCPS-R3.2; OCPS-R3.4.4 | S29: Source -> Candidate (direct recorded source use); Source -> Evidence -> Candidate | T29: SUP-004; SUP-011
A30: OCPM:OCPM-CF-002 | B30: OCPM | C30: OCPM-CF-002 | D30: The simulation model shall define multi-object activity bindings. | E30: The model must define which object instances and object types participate in each simulated activity execution, including events that involve multiple objects, variable object multiplicities, and bindings constrained by object types or object relations. | H30: OCEL 2.0 Specification; Towards a Simple and Extensible Standard for Object-Centric Event Data; Discovering Object-Centric Process Simulation Models; Discovering Object-Centric Petri Nets; Knopp (2023) - Towards Organizational Digital Twins: Process Enhancement by Object-Centric Simulation; van der Aalst (2023) - Toward More Realistic Simulation Models Using Object-Centric Process Mining | I30: SUP-001; SUP-002; SUP-003; SUP-004; SUP-006; SUP-007 | J30: EV-O-0002; EV-O-0005; EV-O-0006; EV-O-0008; EV-O-0023; EV-O-0024; EV-O-0031; EV-O-0039; EV-O-0040 | M30: Merged event-to-object relations, variable arcs, event-object bindings, and multi-object routing/split evidence. The requirement is phrased as binding rather than vague interaction-based semantics. | O30: Include in final synthesis | P30: Retained concept: The simulation model shall define multi-object activity bindings. Final path: OCPS-R1.4; OCPS-R1.5.1; OCPS-R1.5.2; OCPS-R1.6; OCPS-R3.3.1; OCPS-R3.3.2; OCPS-R3.4.1; OCPS-R4.4. Recorded catalogue synthesis: Retained as the event-to-object association requirement. Activity preconditions and object generation are specified separately under R3.4 and R2.1. Direct source-to-candidate inputs: SUP-001; SUP-002; SUP-003; SUP-004; SUP-006; SUP-007. This route is retained independently of any intermediate Evidence record; source-specific strength and scope are not inferred from the route alone. | Q30: OCPS-R1.4; OCPS-R1.5; OCPS-R1.5.1; OCPS-R1.5.2; OCPS-R1.6; OCPS-R3.3.1; OCPS-R3.3.2; OCPS-R3.4.1; OCPS-R4.4 | R30: EV-AUD-0005; EV-AUD-0006; EV-AUD-0029 | S30: Source -> Candidate (direct recorded source use); Source -> Evidence -> Candidate; Later verification (separate from original input) | T30: SUP-001; SUP-002; SUP-003; SUP-004; SUP-006; SUP-007
A31: OCPM:OCPM-CF-003 | B31: OCPM | C31: OCPM-CF-003 | D31: The simulation model shall represent object-aware behavioral dependencies and routing rules. | E31: The model must define how activity enablement, next-activity selection, routing probabilities, or decision rules depend on object types, object attributes, related-object sets, and relations between objects. | H31: Discovering Object-Centric Process Simulation Models; Object-Centric Causal Nets; Towards Organizational Digital Twins: Process Enhancement by Object-Centric Simulation; Knopp (2023) - Towards Organizational Digital Twins: Process Enhancement by Object-Centric Simulation | I31: SUP-003; SUP-004; SUP-005; SUP-006; SUP-007 | J31: EV-O-0006; EV-O-0009; EV-O-0012; EV-O-0022; EV-O-0023; EV-O-0026; EV-O-0027; EV-O-0028; EV-O-0029; EV-O-0030; EV-O-0033; EV-O-0038; EV-O-0041 | M31: Rephrased from manually configured decision rules to object-feature-dependent routing and behavioral dependencies. Row 8 is retained only as supporting evidence because full text was not available in the uploaded workspace. | O31: Include in final synthesis | P31: Retained concept: The simulation model shall represent object-aware behavioral dependencies and routing rules. Final path: OCPS-R3.3.1; OCPS-R3.3.2; OCPS-R3.3.3; OCPS-R3.3.3.1; OCPS-R4.4. Recorded catalogue synthesis: Kept separate from join/synchronization following supervision guidance because split and join have different complexity. Direct source-to-candidate inputs: SUP-003; SUP-005; SUP-007. This route is retained independently of any intermediate Evidence record; source-specific strength and scope are not inferred from the route alone. | Q31: OCPS-R3; OCPS-R3.3.1; OCPS-R3.3.2; OCPS-R3.3.3; OCPS-R3.3.3.1; OCPS-R4.4 | R31: EV-AUD-0031 | S31: Source -> Candidate (direct recorded source use); Source -> Evidence -> Candidate; Later verification (separate from original input) | T31: SUP-003; SUP-005; SUP-007
A32: OCPM:OCPM-TS-001 | B32: OCPM | C32: OCPM-TS-001 | D32: The simulation model shall specify arrival or generation timing for object instances and related object sets. | E32: The model must define when new object instances or related groups of objects enter the simulation, including object-type-specific arrivals, related-object generation timing, and dependencies between arrivals and object relations. | H32: Discovering Object-Centric Process Simulation Models; Toward More Realistic Simulation Models Using Object-Centric Process Mining; Towards Organizational Digital Twins: Process Enhancement by Object-Centric Simulation | I32: SUP-003; SUP-006; SUP-007; SUP-014 | J32: EV-O-0006; EV-O-0010; EV-O-0012; EV-O-0064; EV-O-0065; EV-O-0068; EV-O-0069 | M32: Kept separate from OCPM-DR-004 because this requirement concerns timing of object arrivals/generation rather than structural object-generation constraints. | O32: Include in final synthesis | P32: Retained concept: The simulation model shall specify arrival or generation timing for object instances and related object sets. Final path: OCPS-R2.2.1; OCPS-R2.2.2. Recorded catalogue synthesis: Groups external-arrival rules in R2.2.1 and interdependent arrival or generation timing in R2.2.2. Direct source-to-candidate inputs: SUP-003; SUP-006; SUP-007. This route is retained independently of any intermediate Evidence record; source-specific strength and scope are not inferred from the route alone. | Q32: OCPS-R2; OCPS-R2.2; OCPS-R2.2.1; OCPS-R2.2.2 | R32: EV-AUD-0020; EV-AUD-0021 | S32: Source -> Candidate (direct recorded source use); Source -> Evidence -> Candidate; Later verification (separate from original input) | T32: SUP-003; SUP-006; SUP-007
A33: OCPM:OCPM-TS-002 | B33: OCPM | C33: OCPM-TS-002 | D33: The simulation model shall represent object-level waiting and queueing time. | E33: The model must capture delays before an object can continue execution, including waiting due to resource constraints, queues, object readiness, or synchronization with related objects. The design should permit object-specific waiting-time calculation from timestamped events and object-event participation. | H33: Knopp (2023) - Towards Organizational Digital Twins: Process Enhancement by Object-Centric Simulation OPerA “Synchronization time is the time spent for synchronizing different objects.” | I33: SUP-007; SUP-016 | J33: EV-O-0020; EV-O-0074; EV-O-0075 | M33: Added because the current first table marks row 21 as usable. The requirement is an object-centric extension of case-centric waiting/queue-time behavior; the support is conceptual and should not be treated as a full queueing-policy requirement. | O33: Include in final synthesis | P33: Retained concept: The simulation model shall represent object-level waiting and queueing time. Final path: OCPS-R3.3.2; OCPS-R4.4; OCPS-R5.8. Recorded catalogue synthesis: Separates temporal readiness of required input objects from logical synchronization and resource contention. Direct source-to-candidate inputs: SUP-007. This route is retained independently of any intermediate Evidence record; source-specific strength and scope are not inferred from the route alone. | Q33: OCPS-R3.3.2; OCPS-R4.4; OCPS-R5.8 | S33: Source -> Candidate (direct recorded source use); Source -> Evidence -> Candidate | T33: SUP-007
A34: OCPM:OCPM-RO-001 | B34: OCPM | C34: OCPM-RO-001 | D34: The simulation model shall represent relevant resources as identifiable object types when their identity, state, or behaviour needs to be distinguished in the object-centric process representation. | E34: Human resources, machines, systems, or other active resources may be represented as identifiable object instances belonging to resource object types when their identity, state, or behaviour is relevant to the object-centric process representation. This representation concerns the resource as a process entity and does not by itself specify resource availability, capacity, allocation, or other execution semantics. | H34: van der Aalst (2023), Toward More Realistic Simulation Models Using Object-Centric Process Mining; Knopp (2023), Towards Organizational Digital Twins: Process Enhancement by Object-Centric Simulation; Seidel et al. (2026), Object-Centric Process Management: A Research Manifesto. | I34: SUP-006; SUP-007; SUP-017 | J34: EV-O-0011; EV-O-0012; EV-O-0061 | M34: This candidate concerns only resource-as-object representation. Resource participation represented as event attributes is captured separately in . Availability, capacity, eligibility, allocation, queueing, and other execution semantics are outside its scope. | O34: Include in final synthesis | P34: Retained concept: The simulation model shall represent relevant resources as identifiable object types when their identity, state, or behaviour needs to be distinguished in the object-centric process representation. Final path: OCPS-R5.1; OCPS-R5.10; OCPS-R5.3. Direct source-to-candidate inputs: SUP-006; SUP-007; SUP-017. This route is retained independently of any intermediate Evidence record; source-specific strength and scope are not inferred from the route alone. | Q34: OCPS-R5; OCPS-R5.1; OCPS-R5.10; OCPS-R5.3 | S34: Source -> Candidate (direct recorded source use); Source -> Evidence -> Candidate | T34: SUP-006; SUP-007; SUP-017
A35: OCPM:OCPM-TS-003 | B35: OCPM | C35: OCPM-TS-003 | D35: Object-centric temporal semantics distinguish the service time of an event occurrence as the interval between its start and completion timestamps. | E35: service time = completion − start [object-centric semantic and analytical corroboration; not direct simulation-input evidence]. | H35: Park et al. (2022), OPerA: Object-Centric Performance Analysis | I35: SUP-016 | J35: EV-TR-0001 | M35: Semantic support only. OPerA is a performance-analysis method and does not itself impose a simulation-input duration rule. | N35: Service time is grounded in the separate OPerA PDF p. 10 definition; TP-E051 is synchronization evidence and is not used for this candidate. | O35: Include in final synthesis | P35: Retained concept: Object-centric temporal semantics distinguish the service time of an event occurrence as the interval between its start and completion timestamps. Final path: OCPS-R4.1. Recorded synthesis: Service time is grounded in the separate OPerA PDF p. 10 definition; TP-E051 is synchronization evidence and is not used for this candidate. Direct source-to-candidate inputs: SUP-016. This route is retained independently of any intermediate Evidence record; source-specific strength and scope are not inferred from the route alone. | Q35: OCPS-R4.1 | S35: Source -> Candidate (direct recorded source use); Source -> Evidence -> Candidate | T35: SUP-016
A36: OCPM:OCPM-RO-003 | B36: OCPM | C36: OCPM-RO-003 | D36: When active resources prioritize cases or objects, the simulation model shall represent the corresponding resource-prioritization rule. | E36: Active resources may exhibit prioritization behaviour across cases or objects. When such behaviour affects execution, the model should represent the priority relation or rule that determines which competing case or object is favoured. This requirement captures object-centric resource-prioritization behaviour and does not by itself prescribe a complete generic queue-discipline taxonomy such as FIFO, LIFO, or randomized ordering. | H36: Seidel et al. (2026), Object-Centric Process Management: A Research Manifesto | I36: SUP-017 | J36: EV-O-0085 | M36: Seidel et al. identify active-resource prioritization across cases/objects and, analogously to queuing theory, prioritization among related objects. This provides qualified conceptual support for priority-based ordering in an object-centric setting, but not for a complete generic queue-discipline requirement. | O36: Include in final synthesis | P36: Retained concept: When active resources prioritize cases or objects, the simulation model shall represent the corresponding resource-prioritization rule. Final path: OCPS-R5.8. Recorded catalogue synthesis: Specifies ordering under resource contention. Explicit non-processing delays are specified under R4.3 and object temporal readiness under R4.4. Direct source-to-candidate inputs: SUP-017. This route is retained independently of any intermediate Evidence record; source-specific strength and scope are not inferred from the route alone. | Q36: OCPS-R5.8 | S36: Source -> Candidate (direct recorded source use); Source -> Evidence -> Candidate | T36: SUP-017
A37: Adapted:OCPS-CF-001 | B37: Adapted | C37: OCPS-CF-001 | D37: The OCPS simulation model shall explicitly define the event types to be simulated. | E37: Every simulated event occurrence can be assigned to exactly one defined event type/activity label. | F37: LR-CF1 | G37: OCPM-DR-001 | H37: OCEL 2.0 Specification; Towards a Simple and Extensible Standard for Object-Centric Event Data; Object-Centric Process Mining: Unraveling the Fabric of Real Processes; Object-Centric Process Mining: Concepts and Advancements; Multi-Dimensional Event Data in Graph Databases | I37: BPS-013; FND-001; FND-002; FND-003; FND-004; SUP-001; SUP-002; SUP-010; SUP-011; SUP-013 | K37: Generalize | L37: Case-centric BPS requires activities; OCEL/OCED represents typed events rather than a single-case activity log. | M37: Reworded LR-CF1 from 'activities' to 'event types' and linked it to the OCEL-compatible event-data structure. | O37: Include in final synthesis | P37: Retained concept: The OCPS simulation model shall explicitly define the event types to be simulated. Final path: OCPS-R1.1. Transformation: Case-centric BPS requires activities; OCEL/OCED represents typed events rather than a single-case activity log. Input candidate premises are BPS:LR-CF1; OCPM:OCPM-DR-001. Their individually scoped evidence is inherited through the adaptation links; no claim of a new direct source passage is made. Direct source-to-candidate inputs: BPS-013; FND-001; FND-002; FND-003; FND-004; SUP-001; SUP-002; SUP-010; SUP-011; SUP-013. This route is retained independently of any intermediate Evidence record; source-specific strength and scope are not inferred from the route alone. | Q37: OCPS-R1.1 | R37: EV-AUD-0001 | S37: Source -> Candidate (direct recorded source use); Input candidates -> Candidate; Later verification (separate from original input) | T37: BPS-013; FND-001; FND-002; FND-003; FND-004; SUP-001; SUP-002; SUP-010; SUP-011; SUP-013
A38: Adapted:OCPS-CF-002 | B38: Adapted | C38: OCPS-CF-002 | D38: The OCPS simulation model shall define ordering and control-flow constructs between simulated event types. | E38: The model defines sequencing, branching, joining, looping, and other execution constraints needed to generate valid event sequences. | F38: LR-CF2 | G38: OCPM-CF-001 | H38: Discovering Object-Centric Petri Nets; Object-Centric Process Mining: Concepts and Advancements | I38: BPS-006; BPS-028; BPS-030; BPS-034; FND-001; FND-002; FND-003; SUP-004; SUP-011 | K38: Generalize | L38: Case-centric control flow remains required, but in OCPS it must be interpreted over object-typed process-control elements. | M38: Kept the baseline control-flow requirement and extended the subject from a single case flow to object-typed control-flow representation. | O38: Use in parent synthesis; no standalone Appendix C clause | P38: The candidate is recorded in parent synthesis OCPS-R3; OCPS-R3.1: The OCPS simulation model shall define ordering and control-flow constructs between simulated event types.. It is not itself retained as a separately stated Appendix C requirement. Parent classification does not pass all supporting evidence to every child. Input candidate premises are BPS:LR-CF2; OCPM:OCPM-CF-001. Their individually scoped evidence is inherited through the adaptation links; no claim of a new direct source passage is made. Direct source-to-candidate inputs: BPS-006; BPS-028; BPS-030; BPS-034; FND-001; FND-002; FND-003; SUP-004; SUP-011. This route is retained independently of any intermediate Evidence record; source-specific strength and scope are not inferred from the route alone. | Q38: OCPS-R3; OCPS-R3.1 | S38: Source -> Candidate (direct recorded source use); Input candidates -> Candidate | T38: BPS-006; BPS-028; BPS-030; BPS-034; FND-001; FND-002; FND-003; SUP-004; SUP-011
A39: Adapted:OCPS-CF-003 | B39: Adapted | C39: OCPS-CF-003 | D39: The OCPS simulation model shall specify routing logic for alternative paths. | E39: For every alternative path, the model defines how the selected path is determined, for example by probability or by a data/object-dependent decision rule. | F39: LR-CF3 | G39: OCPM-CF-003 | H39: Discovering Object-Centric Process Simulation Models; Object-Centric Causal Nets; Towards Organizational Digital Twins: Process Enhancement by Object-Centric Simulation; Knopp (2023) - Towards Organizational Digital Twins: Process Enhancement by Object-Centric Simulation | I39: BPS-006; BPS-013; BPS-030; BPS-038; FND-002; FND-003; FND-004; FND-006; SUP-003; SUP-005; SUP-007 | K39: Generalize | L39: BPS routing logic is still needed, while object-centric behavior may make routing depend on object features and relations. | M39: Retained the case-centric routing requirement and added traceability to the object-aware behavioral-dependency requirement. | O39: Include in final synthesis | P39: Retained concept: The OCPS simulation model shall specify routing logic for alternative paths. Final path: OCPS-R3.3.3. Transformation: BPS routing logic is still needed, while object-centric behavior may make routing depend on object features and relations. Input candidate premises are BPS:LR-CF3; OCPM:OCPM-CF-003. Their individually scoped evidence is inherited through the adaptation links; no claim of a new direct source passage is made. Direct source-to-candidate inputs: BPS-006; BPS-013; BPS-030; BPS-038; FND-002; FND-003; FND-004; FND-006; SUP-003; SUP-005; SUP-007. This route is retained independently of any intermediate Evidence record; source-specific strength and scope are not inferred from the route alone. | Q39: OCPS-R3; OCPS-R3.3.3 | R39: EV-AUD-0030 | S39: Source -> Candidate (direct recorded source use); Input candidates -> Candidate; Later verification (separate from original input) | T39: BPS-006; BPS-013; BPS-030; BPS-038; FND-002; FND-003; FND-004; FND-006; SUP-003; SUP-005; SUP-007
A40: Adapted:OCPS-CF-004 | B40: Adapted | C40: OCPS-CF-004 | D40: The OCPS simulation model shall represent object-typed process-control elements for object types that participate in control flow. | E40: For each control-flow-relevant object type, the model includes an explicit typed representation such as object-typed places, typed tokens, or an equivalent object-aware notation. | F40: LR-CF2 | G40: OCPM-CF-001 | H40: Discovering Object-Centric Petri Nets; Object-Centric Process Mining: Concepts and Advancements | I40: BPS-006; BPS-028; BPS-030; BPS-034; FND-001; FND-002; FND-003; SUP-004; SUP-011 | K40: Add object-centric specialization | L40: A single case token is insufficient when multiple object types move through the process. | M40: Introduced a new atomic OCPS requirement from OCPM-CF-001 and mapped it to the general case-centric control-flow requirement. | O40: Include in final synthesis | P40: Retained concept: The OCPS simulation model shall represent object-typed process-control elements for object types that participate in control flow. Final path: OCPS-R3.2; OCPS-R3.4.4. Transformation: A single case token is insufficient when multiple object types move through the process. Input candidate premises are BPS:LR-CF2; OCPM:OCPM-CF-001. Their individually scoped evidence is inherited through the adaptation links; no claim of a new direct source passage is made. Direct source-to-candidate inputs: BPS-006; BPS-028; BPS-030; BPS-034; FND-001; FND-002; FND-003; SUP-004; SUP-011. This route is retained independently of any intermediate Evidence record; source-specific strength and scope are not inferred from the route alone. | Q40: OCPS-R3.2; OCPS-R3.4.4 | R40: EV-AUD-0027 | S40: Source -> Candidate (direct recorded source use); Input candidates -> Candidate; Later verification (separate from original input) | T40: BPS-006; BPS-028; BPS-030; BPS-034; FND-001; FND-002; FND-003; SUP-004; SUP-011
A41: Adapted:OCPS-CF-005 | B41: Adapted | C41: OCPS-CF-005 | D41: The OCPS simulation model shall bind each simulated activity occurrence to the participating object instance or object instances. | E41: Each event occurrence generated by the simulation records the involved object instance(s) so that event-to-object participation can be reconstructed. | F41: LR-CF1 | G41: OCPM-CF-002 | H41: OCEL 2.0 Specification; Towards a Simple and Extensible Standard for Object-Centric Event Data; Discovering Object-Centric Process Simulation Models; Discovering Object-Centric Petri Nets; Knopp (2023) - Towards Organizational Digital Twins: Process Enhancement by Object-Centric Simulation; van der Aalst (2023) - Toward More Realistic Simulation Models Using Object-Centric Process Mining | I41: BPS-013; FND-001; FND-002; FND-003; FND-004; SUP-001; SUP-002; SUP-003; SUP-004; SUP-006; SUP-007 | J41: EV-O-0052 | K41: Add object-centric specialization | L41: Case-centric activities are implicitly attached to one case; OCPS events may involve multiple object instances. | M41: Split the broader multi-object activity-binding requirement into a single participation-binding requirement. | O41: Include in final synthesis | P41: Retained concept: The OCPS simulation model shall bind each simulated activity occurrence to the participating object instance or object instances. Final path: OCPS-R1.4. Transformation: Case-centric activities are implicitly attached to one case; OCPS events may involve multiple object instances. Input candidate premises are BPS:LR-CF1; OCPM:OCPM-CF-002. Their individually scoped evidence is inherited through the adaptation links; no claim of a new direct source passage is made. Direct source-to-candidate inputs: BPS-013; FND-001; FND-002; FND-003; FND-004; SUP-001; SUP-002; SUP-003; SUP-004; SUP-006; SUP-007. This route is retained independently of any intermediate Evidence record; source-specific strength and scope are not inferred from the route alone. | Q41: OCPS-R1.4 | R41: EV-AUD-0004 | S41: Source -> Candidate (direct recorded source use); Source -> Evidence -> Candidate; Input candidates -> Candidate; Later verification (separate from original input) | T41: BPS-013; FND-001; FND-002; FND-003; FND-004; SUP-001; SUP-002; SUP-003; SUP-004; SUP-006; SUP-007
A42: Adapted:OCPS-CF-006 | B42: Adapted | C42: OCPS-CF-006 | D42: The OCPS simulation model shall define the object types eligible to participate in each event type. | E42: For every event type, the model specifies which object type(s) may or must be bound to occurrences of that event type. | F42: LR-CF1 | G42: OCPM-CF-002; OCPM-DR-001 | H42: OCEL 2.0 Specification; Towards a Simple and Extensible Standard for Object-Centric Event Data; Discovering Object-Centric Process Simulation Models; Discovering Object-Centric Petri Nets; Knopp (2023) - Towards Organizational Digital Twins: Process Enhancement by Object-Centric Simulation; van der Aalst (2023) - Toward More Realistic Simulation Models Using Object-Centric Process Mining; Object-Centric Process Mining: Unraveling the Fabric of Real Processes; Object-Centric Process Mining: Concepts and Advancements; Multi-Dimensional Event Data in Graph Databases | I42: BPS-013; FND-001; FND-002; FND-003; FND-004; SUP-001; SUP-002; SUP-003; SUP-004; SUP-006; SUP-007; SUP-010; SUP-011; SUP-013 | K42: Add object-centric specialization | L42: A simulation cannot generate OCEL-compatible event-to-object records without knowing eligible object types per event type. | M42: Derived from OCPM-CF-002 and OCPM-DR-001 by isolating object-type eligibility from concrete object-instance binding. | O42: Include in final synthesis | P42: Retained concept: The OCPS simulation model shall define the object types eligible to participate in each event type. Final path: OCPS-R3.4.1. Transformation: A simulation cannot generate OCEL-compatible event-to-object records without knowing eligible object types per event type. Input candidate premises are BPS:LR-CF1; OCPM:OCPM-CF-002; OCPM:OCPM-DR-001. Their individually scoped evidence is inherited through the adaptation links; no claim of a new direct source passage is made. Direct source-to-candidate inputs: BPS-013; FND-001; FND-002; FND-003; FND-004; SUP-001; SUP-002; SUP-003; SUP-004; SUP-006; SUP-007; SUP-010; SUP-011; SUP-013. This route is retained independently of any intermediate Evidence record; source-specific strength and scope are not inferred from the route alone. | Q42: OCPS-R1.5; OCPS-R3.4.1 | R42: EV-AUD-0032 | S42: Source -> Candidate (direct recorded source use); Input candidates -> Candidate; Later verification (separate from original input) | T42: BPS-013; FND-001; FND-002; FND-003; FND-004; SUP-001; SUP-002; SUP-003; SUP-004; SUP-006; SUP-007; SUP-010; SUP-011; SUP-013
A43: Adapted:OCPS-CF-007 | B43: Adapted | C43: OCPS-CF-007 | D43: The OCPS simulation model shall specify the qualifier or role of an event-to-object binding when different roles are possible. | E43: If the same event type can relate to objects in different roles, the model defines those roles/qualifiers for the generated event-to-object records. | F43: LR-DR1 | G43: OCPM-DR-001; OCPM-CF-002 | H43: OCEL 2.0 Specification; Towards a Simple and Extensible Standard for Object-Centric Event Data; Object-Centric Process Mining: Unraveling the Fabric of Real Processes; Object-Centric Process Mining: Concepts and Advancements; Multi-Dimensional Event Data in Graph Databases; Discovering Object-Centric Process Simulation Models; Discovering Object-Centric Petri Nets; Knopp (2023) - Towards Organizational Digital Twins: Process Enhancement by Object-Centric Simulation; van der Aalst (2023) - Toward More Realistic Simulation Models Using Object-Centric Process Mining | I43: BPS-012; BPS-034; BPS-038; FND-002; SUP-001; SUP-002; SUP-003; SUP-004; SUP-006; SUP-007; SUP-010; SUP-011; SUP-013 | K43: Add object-centric specialization | L43: OCEL-compatible output can qualify event-to-object relations; this avoids ambiguous multi-object participation. | M43: Separated relation-role information from the general multi-object binding requirement to keep the requirement atomic. | O43: Include in final synthesis | P43: Retained concept: The OCPS simulation model shall specify the qualifier or role of an event-to-object binding when different roles are possible. Final path: OCPS-R1.6. Transformation: OCEL-compatible output can qualify event-to-object relations; this avoids ambiguous multi-object participation. Input candidate premises are BPS:LR-DR1; OCPM:OCPM-CF-002; OCPM:OCPM-DR-001. Their individually scoped evidence is inherited through the adaptation links; no claim of a new direct source passage is made. Direct source-to-candidate inputs: BPS-012; BPS-034; BPS-038; FND-002; SUP-001; SUP-002; SUP-003; SUP-004; SUP-006; SUP-007; SUP-010; SUP-011; SUP-013. This route is retained independently of any intermediate Evidence record; source-specific strength and scope are not inferred from the route alone. | Q43: OCPS-R1.6 | R43: EV-AUD-0007 | S43: Source -> Candidate (direct recorded source use); Input candidates -> Candidate; Later verification (separate from original input) | T43: BPS-012; BPS-034; BPS-038; FND-002; SUP-001; SUP-002; SUP-003; SUP-004; SUP-006; SUP-007; SUP-010; SUP-011; SUP-013
A44: Adapted:OCPS-CF-008 | B44: Adapted | C44: OCPS-CF-008 | D44: The OCPS simulation model shall define object-aware split dependencies. | E44: At split points, the model specifies which existing objects continue, which related objects are generated or activated, and how these choices depend on object types or relations. | F44: LR-CF2; LR-CF3 | G44: OCPM-CF-002; OCPM-CF-003; OCPM-DR-004 | H44: OCEL 2.0 Specification; Towards a Simple and Extensible Standard for Object-Centric Event Data; Discovering Object-Centric Process Simulation Models; Discovering Object-Centric Petri Nets; Knopp (2023) - Towards Organizational Digital Twins: Process Enhancement by Object-Centric Simulation; van der Aalst (2023) - Toward More Realistic Simulation Models Using Object-Centric Process Mining; Object-Centric Causal Nets; Towards Organizational Digital Twins: Process Enhancement by Object-Centric Simulation; Toward More Realistic Simulation Models Using Object-Centric Process Mining | I44: BPS-006; BPS-013; BPS-028; BPS-030; BPS-034; BPS-038; FND-001; FND-002; FND-003; FND-004; FND-006; SUP-001; SUP-002; SUP-003; SUP-004; SUP-005; SUP-006; SUP-007 | J44: EV-O-0028; EV-O-0029 | K44: Refine | L44: Supervisor feedback indicated that split and join/synchronization should be separated when they have different semantics and support. | M44: Split the general routing/control-flow construct requirements into an atomic split dependency requirement using object binding and object-generation requirements. | O44: Include in final synthesis | P44: Retained concept: The OCPS simulation model shall define object-aware split dependencies. Final path: OCPS-R3.3.1. Transformation: Supervisor feedback indicated that split and join/synchronization should be separated when they have different semantics and support. Input candidate premises are BPS:LR-CF2; BPS:LR-CF3; OCPM:OCPM-CF-002; OCPM:OCPM-CF-003; OCPM:OCPM-DR-004. Their individually scoped evidence is inherited through the adaptation links; no claim of a new direct source passage is made. Direct source-to-candidate inputs: BPS-006; BPS-013; BPS-028; BPS-030; BPS-034; BPS-038; FND-001; FND-002; FND-003; FND-004; FND-006; SUP-001; SUP-002; SUP-003; SUP-004; SUP-005; SUP-006; SUP-007. This route is retained independently of any intermediate Evidence record; source-specific strength and scope are not inferred from the route alone. | Q44: OCPS-R3.3.1 | R44: EV-AUD-0028 | S44: Source -> Candidate (direct recorded source use); Source -> Evidence -> Candidate; Input candidates -> Candidate; Later verification (separate from original input) | T44: BPS-006; BPS-013; BPS-028; BPS-030; BPS-034; BPS-038; FND-001; FND-002; FND-003; FND-004; FND-006; SUP-001; SUP-002; SUP-003; SUP-004; SUP-005; SUP-006; SUP-007
A45: Adapted:OCPS-CF-009 | B45: Adapted | C45: OCPS-CF-009 | D45: The OCPS simulation model shall define inter-object synchronization conditions. | E45: Before a join or multi-object activity is enabled, the model specifies which related objects, object states, or prior object events must be present. | F45: LR-CF2; LR-CF3; LR-TS3 | G45: OCPM-CF-002; OCPM-CF-003; OCPM-TS-002 | H45: OCEL 2.0 Specification; Towards a Simple and Extensible Standard for Object-Centric Event Data; Discovering Object-Centric Process Simulation Models; Discovering Object-Centric Petri Nets; Knopp (2023) - Towards Organizational Digital Twins: Process Enhancement by Object-Centric Simulation; van der Aalst (2023) - Toward More Realistic Simulation Models Using Object-Centric Process Mining; Object-Centric Causal Nets; Towards Organizational Digital Twins: Process Enhancement by Object-Centric Simulation | I45: BPS-006; BPS-010; BPS-013; BPS-028; BPS-030; BPS-034; BPS-038; BPS-052; FND-001; FND-002; FND-003; FND-004; FND-006; SUP-001; SUP-002; SUP-003; SUP-004; SUP-005; SUP-006; SUP-007 | J45: EV-O-0031; EV-O-0033 | K45: Refine | L45: Object-centric execution can require one object to wait for related objects; this is not captured by a single-case routing requirement. | M45: Separated join/synchronization from split logic and linked it to object-level waiting to avoid merging distinct requirements. | O45: Include in final synthesis | P45: Retained concept: The OCPS simulation model shall define inter-object synchronization conditions. Final path: OCPS-R3.3.2; OCPS-R4.4. Transformation: Object-centric execution can require one object to wait for related objects; this is not captured by a single-case routing requirement. Input candidate premises are BPS:LR-CF2; BPS:LR-CF3; BPS:LR-TS3; OCPM:OCPM-CF-002; OCPM:OCPM-CF-003; OCPM:OCPM-TS-002. Their individually scoped evidence is inherited through the adaptation links; no claim of a new direct source passage is made. Direct source-to-candidate inputs: BPS-006; BPS-010; BPS-013; BPS-028; BPS-030; BPS-034; BPS-038; BPS-052; FND-001; FND-002; FND-003; FND-004; FND-006; SUP-001; SUP-002; SUP-003; SUP-004; SUP-005; SUP-006; SUP-007. This route is retained independently of any intermediate Evidence record; source-specific strength and scope are not inferred from the route alone. | Q45: OCPS-R3.3.2; OCPS-R4.4 | S45: Source -> Candidate (direct recorded source use); Source -> Evidence -> Candidate; Input candidates -> Candidate | T45: BPS-006; BPS-010; BPS-013; BPS-028; BPS-030; BPS-034; BPS-038; BPS-052; FND-001; FND-002; FND-003; FND-004; FND-006; SUP-001; SUP-002; SUP-003; SUP-004; SUP-005; SUP-006; SUP-007
A46: Adapted:OCPS-CF-010 | B46: Adapted | C46: OCPS-CF-010 | D46: The OCPS simulation model shall define object-aware decision rules for activity enablement or next-activity selection. | E46: The model defines decisions using object types, object attribute values, related-object sets, object-to-object relations, or event attributes when these determine behavior. | F46: LR-CF3; LR-DR1 | G46: OCPM-CF-003; OCPM-DR-002; OCPM-DR-003 | H46: Discovering Object-Centric Process Simulation Models; Object-Centric Causal Nets; Towards Organizational Digital Twins: Process Enhancement by Object-Centric Simulation; Knopp (2023) - Towards Organizational Digital Twins: Process Enhancement by Object-Centric Simulation; OCEL 2.0 Specification; Automated Digital Twin Generation of Manufacturing Systems with Complex Material Flows; Analyzing Interconnected Processes: Using Object-Centric Process Mining to Analyze Procurement Processes; Dirigo: A Method to Extract Event Logs for Object-Centric Processes; Multi-Dimensional Event Data in Graph Databases; State-Aware Object-Centric Process Mining: Enhancing OCEL 2.0 with Explicit State Transitions | I46: BPS-006; BPS-012; BPS-013; BPS-030; BPS-034; BPS-037; BPS-038; FND-002; FND-003; FND-004; FND-006; SUP-001; SUP-003; SUP-005; SUP-007; SUP-008; SUP-009; SUP-013 | K46: Refine | L46: Case-centric routing can use branch probabilities or case data; OCPS routing may depend on multiple objects and their relations. | M46: Combined routing logic with object-centric behavioral dependency evidence and separated it from generic routing. | O46: Include in final synthesis | P46: Retained concept: The OCPS simulation model shall define object-aware decision rules for activity enablement or next-activity selection. Final path: OCPS-R3.3.3.1. Transformation: Case-centric routing can use branch probabilities or case data; OCPS routing may depend on multiple objects and their relations. Input candidate premises are BPS:LR-CF3; BPS:LR-DR1; OCPM:OCPM-CF-003; OCPM:OCPM-DR-002; OCPM:OCPM-DR-003. Their individually scoped evidence is inherited through the adaptation links; no claim of a new direct source passage is made. Direct source-to-candidate inputs: BPS-006; BPS-012; BPS-013; BPS-030; BPS-034; BPS-037; BPS-038; FND-002; FND-003; FND-004; FND-006; SUP-001; SUP-003; SUP-005; SUP-007; SUP-008; SUP-009; SUP-013. This route is retained independently of any intermediate Evidence record; source-specific strength and scope are not inferred from the route alone. | Q46: OCPS-R3.3.3.1 | R46: EV-AUD-0031 | S46: Source -> Candidate (direct recorded source use); Input candidates -> Candidate; Later verification (separate from original input) | T46: BPS-006; BPS-012; BPS-013; BPS-030; BPS-034; BPS-037; BPS-038; FND-002; FND-003; FND-004; FND-006; SUP-001; SUP-003; SUP-005; SUP-007; SUP-008; SUP-009; SUP-013
A47: Adapted:OCPS-DR-001 | B47: Adapted | C47: OCPS-DR-001 | D47: The OCPS simulation model shall use an OCEL/OCED-compatible object-centric event-data structure. | E47: The simulation structure can represent event types, events, timestamps, object types, object instances, event attributes, object attributes, event-to-object relations, and object-to-object relations without requiring a flattened single-case log. | F47: LR-DR1 | G47: OCPM-DR-001 | H47: OCEL 2.0 Specification; Towards a Simple and Extensible Standard for Object-Centric Event Data; Object-Centric Process Mining: Unraveling the Fabric of Real Processes; Object-Centric Process Mining: Concepts and Advancements; Multi-Dimensional Event Data in Graph Databases | I47: BPS-012; BPS-013; BPS-034; BPS-038; BPS-052; BPS-054; FND-002; SUP-001; SUP-002; SUP-010; SUP-011; SUP-013 | K47: Add object-centric foundation | L47: Table A contains event attributes and timestamped output, but OCPS requires a multi-object data structure rather than one case notion. | M47: Used OCPM-DR-001 as the structural extension layer for the case-centric data and output requirements. | O47: Use in parent synthesis; no standalone Appendix C clause | P47: The candidate is recorded in parent synthesis OCPS-R1: The OCPS simulation model shall use an OCEL/OCED-compatible object-centric event-data structure.. It is not itself retained as a separately stated Appendix C requirement. Parent classification does not pass all supporting evidence to every child. Input candidate premises are BPS:LR-DR1; OCPM:OCPM-DR-001. Their individually scoped evidence is inherited through the adaptation links; no claim of a new direct source passage is made. Direct source-to-candidate inputs: BPS-012; BPS-013; BPS-034; BPS-038; BPS-052; BPS-054; FND-002; SUP-001; SUP-002; SUP-010; SUP-011; SUP-013. This route is retained independently of any intermediate Evidence record; source-specific strength and scope are not inferred from the route alone. | Q47: OCPS-R1 | S47: Source -> Candidate (direct recorded source use); Input candidates -> Candidate | T47: BPS-012; BPS-013; BPS-034; BPS-038; BPS-052; BPS-054; FND-002; SUP-001; SUP-002; SUP-010; SUP-011; SUP-013
A48: Adapted:OCPS-DR-002 | B48: Adapted | C48: OCPS-DR-002 | D48: The OCPS simulation model shall represent event attribute values for simulated events. | E48: Generated events include the event attributes needed to describe execution, routing, timing, or analysis results. | F48: LR-DR1 | G48: OCPM-DR-001 | H48: OCEL 2.0 Specification; Towards a Simple and Extensible Standard for Object-Centric Event Data; Object-Centric Process Mining: Unraveling the Fabric of Real Processes; Object-Centric Process Mining: Concepts and Advancements; Multi-Dimensional Event Data in Graph Databases | I48: BPS-012; BPS-034; BPS-038; FND-002; SUP-001; SUP-002; SUP-010; SUP-011; SUP-013 | J48: EV-O-0042 | K48: Keep and align | L48: Event attributes are already required in case-centric BPS and are also part of OCEL/OCED-compatible event records. | M48: Preserved LR-DR1 and aligned its wording with the OCEL/OCED event-data structure. | O48: Include in final synthesis | P48: Retained concept: The OCPS simulation model shall represent event attribute values for simulated events. Final path: OCPS-R1.7.2. Transformation: Event attributes are already required in case-centric BPS and are also part of OCEL/OCED-compatible event records. Input candidate premises are BPS:LR-DR1; OCPM:OCPM-DR-001. Their individually scoped evidence is inherited through the adaptation links; no claim of a new direct source passage is made. Direct source-to-candidate inputs: BPS-012; BPS-034; BPS-038; FND-002; SUP-001; SUP-002; SUP-010; SUP-011; SUP-013. This route is retained independently of any intermediate Evidence record; source-specific strength and scope are not inferred from the route alone. | Q48: OCPS-R1.7.2 | S48: Source -> Candidate (direct recorded source use); Source -> Evidence -> Candidate; Input candidates -> Candidate | T48: BPS-012; BPS-034; BPS-038; FND-002; SUP-001; SUP-002; SUP-010; SUP-011; SUP-013
A49: Adapted:OCPS-DR-003 | B49: Adapted | C49: OCPS-DR-003 | D49: The OCPS simulation model shall represent object types and object instances. | E49: The model defines the set of simulated object types and creates identifiable object instances of those types. | F49: LR-TS1 | G49: OCPM-DR-001 | H49: OCEL 2.0 Specification; Towards a Simple and Extensible Standard for Object-Centric Event Data; Object-Centric Process Mining: Unraveling the Fabric of Real Processes; Object-Centric Process Mining: Concepts and Advancements; Multi-Dimensional Event Data in Graph Databases | I49: BPS-006; BPS-030; FND-002; SUP-001; SUP-002; SUP-010; SUP-011; SUP-013 | K49: Add object-centric specialization | L49: A case-centric entity/case becomes only one object type in OCPS; multiple object types must be represented explicitly. | M49: Generalized the case/entity arrival concept and grounded the object representation in OCPM-DR-001. | O49: Include in final synthesis | P49: Retained concept: The OCPS simulation model shall represent object types and object instances. Final path: OCPS-R1.2. Transformation: A case-centric entity/case becomes only one object type in OCPS; multiple object types must be represented explicitly. Input candidate premises are BPS:LR-TS1; OCPM:OCPM-DR-001. Their individually scoped evidence is inherited through the adaptation links; no claim of a new direct source passage is made. Direct source-to-candidate inputs: BPS-006; BPS-030; FND-002; SUP-001; SUP-002; SUP-010; SUP-011; SUP-013. This route is retained independently of any intermediate Evidence record; source-specific strength and scope are not inferred from the route alone. | Q49: OCPS-R1.2 | R49: EV-AUD-0002; EV-AUD-0056; EV-AUD-0072 | S49: Source -> Candidate (direct recorded source use); Input candidates -> Candidate; Later verification (separate from original input) | T49: BPS-006; BPS-030; FND-002; SUP-001; SUP-002; SUP-010; SUP-011; SUP-013
A50: Adapted:OCPS-DR-004 | B50: Adapted | C50: OCPS-DR-004 | D50: The OCPS simulation model shall represent object attribute values for simulated objects. | E50: Object instances have attribute values that can be used for behavior, routing, performance calculation, or analysis. | F50: LR-DR1 | G50: OCPM-DR-001; OCPM-DR-003 | H50: OCEL 2.0 Specification; Towards a Simple and Extensible Standard for Object-Centric Event Data; Object-Centric Process Mining: Unraveling the Fabric of Real Processes; Object-Centric Process Mining: Concepts and Advancements; Multi-Dimensional Event Data in Graph Databases; Dirigo: A Method to Extract Event Logs for Object-Centric Processes; State-Aware Object-Centric Process Mining: Enhancing OCEL 2.0 with Explicit State Transitions | I50: BPS-012; BPS-034; BPS-038; FND-002; SUP-001; SUP-002; SUP-008; SUP-009; SUP-010; SUP-011; SUP-013 | J50: EV-O-0045; EV-O-0046 | K50: Add object-centric specialization | L50: Case-centric data attributes do not distinguish event attributes from object attributes; OCPS must represent object attributes separately. | M50: Separated object attributes from event attributes to avoid the ambiguity highlighted in supervision feedback. | O50: Include through explicit scoped reconciliation | P50: Partial/refined absorption: object-value representation supplies the premise for value-domain specification and maintenance of current object values. The candidate alone does not establish the full domain constraint. Targets: OCPS-R1.7.2; OCPS-R1.9.1. This mapping was reconstructed in this revision, not reported as an original historical decision. Input candidate premises are BPS:LR-DR1; OCPM:OCPM-DR-001; OCPM:OCPM-DR-003. Their individually scoped evidence is inherited through the adaptation links; no claim of a new direct source passage is made. Direct source-to-candidate inputs: BPS-012; BPS-034; BPS-038; FND-002; SUP-001; SUP-002; SUP-008; SUP-009; SUP-010; SUP-011; SUP-013. This route is retained independently of any intermediate Evidence record; source-specific strength and scope are not inferred from the route alone. | Q50: OCPS-R1.7.2; OCPS-R1.9.1 | R50: EV-AUD-0009; EV-AUD-0058 | S50: Source -> Candidate (direct recorded source use); Source -> Evidence -> Candidate; Input candidates -> Candidate; Later verification (separate from original input) | T50: BPS-012; BPS-034; BPS-038; FND-002; SUP-001; SUP-002; SUP-008; SUP-009; SUP-010; SUP-011; SUP-013
A51: Adapted:OCPS-DR-005 | B51: Adapted | C51: OCPS-DR-005 | D51: When object attribute values change during simulation, the OCPS simulation model shall represent the time-dependent object attribute values. | E51: Changes to object attribute values are recorded with timestamps, state records, or an equivalent OCEL/OCED-compatible encoding. | F51: LR-DR1 | G51: OCPM-DR-003 | H51: OCEL 2.0 Specification; Dirigo: A Method to Extract Event Logs for Object-Centric Processes; State-Aware Object-Centric Process Mining: Enhancing OCEL 2.0 with Explicit State Transitions; Multi-Dimensional Event Data in Graph Databases | I51: BPS-012; BPS-013; BPS-034; BPS-038; BPS-052; BPS-054; FND-002; SUP-001; SUP-008; SUP-009; SUP-013 | K51: Split compound object-centric requirement | L51: OCPM-DR-003 combines time-dependent attributes, states, and changing relations; atomic requirements require separating them. | M51: Extracted the object-attribute-change part of OCPM-DR-003 and linked it to timestamped output. | O51: Include in final synthesis | P51: Retained concept: When object attribute values change during simulation, the OCPS simulation model shall represent the time-dependent object attribute values. Final path: OCPS-R1.9.3. Transformation: OCPM-DR-003 combines time-dependent attributes, states, and changing relations; atomic requirements require separating them. Input candidate premises are BPS:LR-DR1; OCPM:OCPM-DR-003. Their individually scoped evidence is inherited through the adaptation links; no claim of a new direct source passage is made. Direct source-to-candidate inputs: BPS-012; BPS-013; BPS-034; BPS-038; BPS-052; BPS-054; FND-002; SUP-001; SUP-008; SUP-009; SUP-013. This route is retained independently of any intermediate Evidence record; source-specific strength and scope are not inferred from the route alone. | Q51: OCPS-R1.9.3 | R51: EV-AUD-0014 | S51: Source -> Candidate (direct recorded source use); Input candidates -> Candidate; Later verification (separate from original input) | T51: BPS-012; BPS-013; BPS-034; BPS-038; BPS-052; BPS-054; FND-002; SUP-001; SUP-008; SUP-009; SUP-013
A52: Adapted:OCPS-DR-006 | B52: Adapted | C52: OCPS-DR-006 | D52: When object state affects behavior or analysis, the OCPS simulation model shall represent object states. | E52: The model defines relevant object states and makes them available for activity enablement, routing, waiting, or output analysis. | F52: LR-CF3; LR-DR1 | G52: OCPM-DR-003 | H52: OCEL 2.0 Specification; Dirigo: A Method to Extract Event Logs for Object-Centric Processes; State-Aware Object-Centric Process Mining: Enhancing OCEL 2.0 with Explicit State Transitions; Multi-Dimensional Event Data in Graph Databases | I52: BPS-006; BPS-012; BPS-013; BPS-030; BPS-034; BPS-038; FND-002; FND-003; FND-004; FND-006; SUP-001; SUP-008; SUP-009; SUP-013 | K52: Split compound object-centric requirement | L52: Object state can influence object-centric behavior independently from attribute changes or relation changes. | M52: Extracted object-state representation from OCPM-DR-003 and tied it to routing/data usage in Table A. | O52: Include in final synthesis | P52: Retained concept: When object state affects behavior or analysis, the OCPS simulation model shall represent object states. Final path: OCPS-R1.9.1. Transformation: Object state can influence object-centric behavior independently from attribute changes or relation changes. Input candidate premises are BPS:LR-CF3; BPS:LR-DR1; OCPM:OCPM-DR-003. Their individually scoped evidence is inherited through the adaptation links; no claim of a new direct source passage is made. Direct source-to-candidate inputs: BPS-006; BPS-012; BPS-013; BPS-030; BPS-034; BPS-038; FND-002; FND-003; FND-004; FND-006; SUP-001; SUP-008; SUP-009; SUP-013. This route is retained independently of any intermediate Evidence record; source-specific strength and scope are not inferred from the route alone. | Q52: OCPS-R1.9.1 | R52: EV-AUD-0060 | S52: Source -> Candidate (direct recorded source use); Input candidates -> Candidate; Later verification (separate from original input) | T52: BPS-006; BPS-012; BPS-013; BPS-030; BPS-034; BPS-038; FND-002; FND-003; FND-004; FND-006; SUP-001; SUP-008; SUP-009; SUP-013
A53: Adapted:OCPS-DR-007 | B53: Adapted | C53: OCPS-DR-007 | D53: When object states change during simulation, the OCPS simulation model shall represent object state transitions as timestamped records. | E53: Each modeled state change can be traced over simulation time as a generated event, state-transition record, or equivalent timestamped representation. | G53: OCPM-DR-003 | H53: OCEL 2.0 Specification; Dirigo: A Method to Extract Event Logs for Object-Centric Processes; State-Aware Object-Centric Process Mining: Enhancing OCEL 2.0 with Explicit State Transitions; Multi-Dimensional Event Data in Graph Databases | I53: BPS-005; BPS-013; BPS-025; BPS-027; BPS-052; BPS-054; SUP-001; SUP-008; SUP-009; SUP-013 | K53: Split compound object-centric requirement | L53: Timed state transitions are separate from merely holding an object state. | M53: Combined Table A's stochastic timed-transition/output requirements with the state-transition part of OCPM-DR-003. | O53: Include in final synthesis | P53: Retained concept: When object states change during simulation, the OCPS simulation model shall represent object state transitions as timestamped records. Final path: OCPS-R1.9.2. Transformation: Timed state transitions are separate from merely holding an object state. Input candidate premises are OCPM:OCPM-DR-003. Their individually scoped evidence is inherited through the adaptation links; no claim of a new direct source passage is made. Direct source-to-candidate inputs: BPS-005; BPS-013; BPS-025; BPS-027; BPS-052; BPS-054; SUP-001; SUP-008; SUP-009; SUP-013. This route is retained independently of any intermediate Evidence record; source-specific strength and scope are not inferred from the route alone. | Q53: OCPS-R1.9.2 | R53: EV-AUD-0013 | S53: Source -> Candidate (direct recorded source use); Input candidates -> Candidate; Later verification (separate from original input) | T53: BPS-005; BPS-013; BPS-025; BPS-027; BPS-052; BPS-054; SUP-001; SUP-008; SUP-009; SUP-013
A54: Adapted:OCPS-DR-008 | B54: Adapted | C54: OCPS-DR-008 | D54: The OCPS simulation model shall represent object-to-object relationships between object instances. | E54: The model records structural or behavioral relations among object instances, such as composition, containment, derivation, or organizational relations. | F54: LR-DR1 | G54: OCPM-DR-002 | H54: OCEL 2.0 Specification; Automated Digital Twin Generation of Manufacturing Systems with Complex Material Flows; Analyzing Interconnected Processes: Using Object-Centric Process Mining to Analyze Procurement Processes; Dirigo: A Method to Extract Event Logs for Object-Centric Processes; Multi-Dimensional Event Data in Graph Databases; Knopp (2023) - Towards Organizational Digital Twins: Process Enhancement by Object-Centric Simulation | I54: BPS-012; BPS-034; BPS-037; BPS-038; FND-002; SUP-001; SUP-007; SUP-008; SUP-013 | K54: Add object-centric specialization | L54: Case-centric models do not require relationships between multiple object types; OCPS does. | M54: Introduced O2O relations from OCPM-DR-002 as a data/rules requirement. | O54: Include in final synthesis | P54: Retained concept: The OCPS simulation model shall represent object-to-object relationships between object instances. Final path: OCPS-R1.8. Transformation: Case-centric models do not require relationships between multiple object types; OCPS does. Input candidate premises are BPS:LR-DR1; OCPM:OCPM-DR-002. Their individually scoped evidence is inherited through the adaptation links; no claim of a new direct source passage is made. Direct source-to-candidate inputs: BPS-012; BPS-034; BPS-037; BPS-038; FND-002; SUP-001; SUP-007; SUP-008; SUP-013. This route is retained independently of any intermediate Evidence record; source-specific strength and scope are not inferred from the route alone. | Q54: OCPS-R1.8 | R54: EV-AUD-0059; EV-AUD-0074 | S54: Source -> Candidate (direct recorded source use); Input candidates -> Candidate; Later verification (separate from original input) | T54: BPS-012; BPS-034; BPS-037; BPS-038; FND-002; SUP-001; SUP-007; SUP-008; SUP-013
A55: Adapted:OCPS-DR-009 | B55: Adapted | C55: OCPS-DR-009 | D55: The OCPS simulation model shall specify the relation type or qualifier for each modeled object-to-object relationship when relation meaning matters. | E55: The model distinguishes different meanings of O2O relations, for example part-of, belongs-to, created-from, or reports-to. | F55: LR-DR1 | G55: OCPM-DR-002 | H55: OCEL 2.0 Specification; Automated Digital Twin Generation of Manufacturing Systems with Complex Material Flows; Analyzing Interconnected Processes: Using Object-Centric Process Mining to Analyze Procurement Processes; Dirigo: A Method to Extract Event Logs for Object-Centric Processes; Multi-Dimensional Event Data in Graph Databases; Knopp (2023) - Towards Organizational Digital Twins: Process Enhancement by Object-Centric Simulation | I55: BPS-012; BPS-034; BPS-037; BPS-038; FND-002; SUP-001; SUP-007; SUP-008; SUP-013 | K55: Split compound object-centric requirement | L55: A relationship without its type can be ambiguous and may not support routing or analysis. | M55: Separated O2O relation existence from O2O relation typing/qualification to keep each requirement atomic. | O55: Include through explicit scoped reconciliation | P55: Relation meaning/type is retained in the final relation-definition requirement. This link is to static meaning, not the dynamic governing rule in R1.8.1. Targets: OCPS-R1.8. This mapping was reconstructed in this revision, not reported as an original historical decision. Input candidate premises are BPS:LR-DR1; OCPM:OCPM-DR-002. Their individually scoped evidence is inherited through the adaptation links; no claim of a new direct source passage is made. Direct source-to-candidate inputs: BPS-012; BPS-034; BPS-037; BPS-038; FND-002; SUP-001; SUP-007; SUP-008; SUP-013. This route is retained independently of any intermediate Evidence record; source-specific strength and scope are not inferred from the route alone. | Q55: OCPS-R1.8 | R55: EV-AUD-0010 | S55: Source -> Candidate (direct recorded source use); Input candidates -> Candidate; Later verification (separate from original input) | T55: BPS-012; BPS-034; BPS-037; BPS-038; FND-002; SUP-001; SUP-007; SUP-008; SUP-013
A56: Adapted:OCPS-DR-010 | B56: Adapted | C56: OCPS-DR-010 | D56: When object-to-object relationships change during simulation, the OCPS simulation model shall represent those relationship changes over simulation time. | E56: For each dynamic O2O relation in scope, identify the participating object types or instances, the applicable relation-change operation, and the event, lifecycle stage or condition triggering the change. Specify the resulting relation state and when the change takes effect. | G56: OCPM-DR-003; OCPM-DR-002 | H56: OCEL 2.0 Specification; Dirigo: A Method to Extract Event Logs for Object-Centric Processes; State-Aware Object-Centric Process Mining: Enhancing OCEL 2.0 with Explicit State Transitions; Multi-Dimensional Event Data in Graph Databases; Automated Digital Twin Generation of Manufacturing Systems with Complex Material Flows; Analyzing Interconnected Processes: Using Object-Centric Process Mining to Analyze Procurement Processes; Knopp (2023) - Towards Organizational Digital Twins: Process Enhancement by Object-Centric Simulation | I56: BPS-013; BPS-037; BPS-052; BPS-054; SUP-001; SUP-007; SUP-008; SUP-009; SUP-013 | J56: EV-O-0014 | K56: Split compound object-centric requirement | L56: Separate dynamic O2O changes from static relation structure. Dirigo QC3.b explicitly requires identifying when/how relations change and their activity/lifecycle triggers; representing these changes in a simulator requires a governing update rule. | M56: Verified source premise: dynamic O2O relations have identifiable expected change situations and activity/lifecycle triggers (Dirigo QC3.b). OCPM-DR-003 retains this dynamic relation concept alongside attributes/state; OCPM-DR-002 supplies the relation structure. OCPS-DR-010 isolates relation changes. Simulation adaptation: to produce a changing relation state, specify the applicable update operation and its event/lifecycle/condition trigger. R1.8.1 retains that governing-rule requirement. This is a source-informed simulation design derivation, not a claim that Dirigo implements a simulation engine. | O56: Include in final synthesis | P56: Retained concept: When object-to-object relationships change during simulation, the OCPS simulation model shall represent those relationship changes over simulation time. Final path: OCPS-R1.8.1. Transformation: Separate dynamic O2O changes from static relation structure. Dirigo QC3.b explicitly requires identifying when/how relations change and their activity/lifecycle triggers; representing these changes in a simulator requires a governing update rule. Input candidate premises are OCPM:OCPM-DR-002; OCPM:OCPM-DR-003. Their individually scoped evidence is inherited through the adaptation links; no claim of a new direct source passage is made. Direct source-to-candidate inputs: BPS-013; BPS-037; BPS-052; BPS-054; SUP-001; SUP-007; SUP-008; SUP-009; SUP-013. This route is retained independently of any intermediate Evidence record; source-specific strength and scope are not inferred from the route alone. | Q56: OCPS-R1.8.1 | R56: EV-AUD-0066; EV-AUD-0069 | S56: Source -> Candidate (direct recorded source use); Source -> Evidence -> Candidate; Input candidates -> Candidate; Later verification (separate from original input) | T56: BPS-013; BPS-037; BPS-052; BPS-054; SUP-001; SUP-007; SUP-008; SUP-009; SUP-013
A57: Adapted:OCPS-DR-011 | B57: Adapted | C57: OCPS-DR-011 | D57: The OCPS simulation model shall specify object-generation rules for each simulated object type. | E57: For each object type, the model defines how object instances are created, including creation trigger, generation quantity, and initial attribute values when relevant. | F57: LR-TS1 | G57: OCPM-DR-004 | H57: Discovering Object-Centric Process Simulation Models; Toward More Realistic Simulation Models Using Object-Centric Process Mining; Towards Organizational Digital Twins: Process Enhancement by Object-Centric Simulation; Knopp (2023) - Towards Organizational Digital Twins: Process Enhancement by Object-Centric Simulation | I57: BPS-006; BPS-030; FND-002; SUP-003; SUP-006; SUP-007 | K57: Add object-centric specialization | L57: Case arrival only creates one case/entity; OCPS must generate multiple object types. | M57: Rephrased the broad object-generation requirement into an atomic per-object-type generation rule. | O57: Include through explicit scoped reconciliation | P57: Object-generation rules for each type are retained in the final specific generation-rule requirement; the earlier link reached only category R2. Targets: OCPS-R2; OCPS-R2.1.1. This mapping was reconstructed in this revision, not reported as an original historical decision. Input candidate premises are BPS:LR-TS1; OCPM:OCPM-DR-004. Their individually scoped evidence is inherited through the adaptation links; no claim of a new direct source passage is made. Direct source-to-candidate inputs: BPS-006; BPS-030; FND-002; SUP-003; SUP-006; SUP-007. This route is retained independently of any intermediate Evidence record; source-specific strength and scope are not inferred from the route alone. | Q57: OCPS-R2; OCPS-R2.1.1 | R57: EV-AUD-0015 | S57: Source -> Candidate (direct recorded source use); Input candidates -> Candidate; Later verification (separate from original input) | T57: BPS-006; BPS-030; FND-002; SUP-003; SUP-006; SUP-007
A58: Adapted:OCPS-DR-012 | B58: Adapted | C58: OCPS-DR-012 | D58: The OCPS simulation model shall specify related-object-set generation rules. | E58: When objects are generated together, the model defines their relation structure and multiplicities, such as the number of item objects generated for an order object. | F58: LR-TS1 | G58: OCPM-DR-004; OCPM-DR-002 | H58: Discovering Object-Centric Process Simulation Models; Toward More Realistic Simulation Models Using Object-Centric Process Mining; Towards Organizational Digital Twins: Process Enhancement by Object-Centric Simulation; Knopp (2023) - Towards Organizational Digital Twins: Process Enhancement by Object-Centric Simulation; OCEL 2.0 Specification; Automated Digital Twin Generation of Manufacturing Systems with Complex Material Flows; Analyzing Interconnected Processes: Using Object-Centric Process Mining to Analyze Procurement Processes; Dirigo: A Method to Extract Event Logs for Object-Centric Processes; Multi-Dimensional Event Data in Graph Databases | I58: BPS-006; BPS-030; BPS-037; FND-002; SUP-001; SUP-003; SUP-006; SUP-007; SUP-008; SUP-013 | K58: Add object-centric specialization | L58: Object-centric simulation often needs related groups of objects rather than independent case arrivals. | M58: Separated related-object-set generation from general object generation and grounded it in object relation requirements. | O58: Include in final synthesis | P58: Retained concept: The OCPS simulation model shall specify related-object-set generation rules. Final path: OCPS-R2.1.2. Transformation: Object-centric simulation often needs related groups of objects rather than independent case arrivals. Input candidate premises are BPS:LR-TS1; OCPM:OCPM-DR-002; OCPM:OCPM-DR-004. Their individually scoped evidence is inherited through the adaptation links; no claim of a new direct source passage is made. Direct source-to-candidate inputs: BPS-006; BPS-030; BPS-037; FND-002; SUP-001; SUP-003; SUP-006; SUP-007; SUP-008; SUP-013. This route is retained independently of any intermediate Evidence record; source-specific strength and scope are not inferred from the route alone. | Q58: OCPS-R2.1.2 | R58: EV-AUD-0016; EV-AUD-0067 | S58: Source -> Candidate (direct recorded source use); Input candidates -> Candidate; Later verification (separate from original input) | T58: BPS-006; BPS-030; BPS-037; FND-002; SUP-001; SUP-003; SUP-006; SUP-007; SUP-008; SUP-013
A59: Adapted:OCPS-RO-001 | B59: Adapted | C59: OCPS-RO-001 | D59: The OCPS simulation model shall specify the required resource category for each activity that requires resources. | E59: For every resource-dependent activity, the model defines the resource category needed to execute it. | F59: LR-RO1 | G59: OCPM-RO-001 | H59: Toward More Realistic Simulation Models Using Object-Centric Process Mining; Towards Organizational Digital Twins: Process Enhancement by Object-Centric Simulation | I59: BPS-013; BPS-017; BPS-030; BPS-034; BPS-057; BPS-062; FND-002; FND-006; SUP-006; SUP-007 | K59: Keep and align | L59: Resource categories are a standard BPS requirement; OCPS may represent resources as objects when they participate in events. | M59: Preserved LR-RO1 and added object-centric traceability only for the representation of resources as OCED-compatible entities. | O59: Include in final synthesis | P59: Retained concept: The OCPS simulation model shall specify the required resource category for each activity that requires resources. Final path: OCPS-R5.1. Transformation: Resource categories are a standard BPS requirement; OCPS may represent resources as objects when they participate in events. Input candidate premises are BPS:LR-RO1; OCPM:OCPM-RO-001. Their individually scoped evidence is inherited through the adaptation links; no claim of a new direct source passage is made. Direct source-to-candidate inputs: BPS-013; BPS-017; BPS-030; BPS-034; BPS-057; BPS-062; FND-002; FND-006; SUP-006; SUP-007. This route is retained independently of any intermediate Evidence record; source-specific strength and scope are not inferred from the route alone. | Q59: OCPS-R5; OCPS-R5.1 | R59: EV-AUD-0043 | S59: Source -> Candidate (direct recorded source use); Input candidates -> Candidate; Later verification (separate from original input) | T59: BPS-013; BPS-017; BPS-030; BPS-034; BPS-057; BPS-062; FND-002; FND-006; SUP-006; SUP-007
A60: Adapted:OCPS-RO-002 | B60: Adapted | C60: OCPS-RO-002 | D60: The OCPS simulation model shall specify the required number of resource units for each activity that requires resources. | E60: For every resource-dependent activity, the model defines how many resource units of each required category are consumed during execution. | F60: LR-RO2 | I60: BPS-062; FND-002; FND-006 | K60: Carry over | L60: The second table does not add a specific object-centric change for this capacity requirement, but OCPS still needs it for executable simulation. | M60: Carried over the case-centric requirement without adding unsupported object-centric content. | O60: Include in final synthesis | P60: Retained concept: The OCPS simulation model shall specify the required number of resource units for each activity that requires resources. Final path: OCPS-R5.2. Transformation: The second table does not add a specific object-centric change for this capacity requirement, but OCPS still needs it for executable simulation. Input candidate premises are BPS:LR-RO2. Their individually scoped evidence is inherited through the adaptation links; no claim of a new direct source passage is made. Direct source-to-candidate inputs: BPS-062; FND-002; FND-006. This route is retained independently of any intermediate Evidence record; source-specific strength and scope are not inferred from the route alone. | Q60: OCPS-R5.2 | R60: EV-AUD-0044 | S60: Source -> Candidate (direct recorded source use); Input candidates -> Candidate; Later verification (separate from original input) | T60: BPS-062; FND-002; FND-006
A61: Adapted:OCPS-RO-003 | B61: Adapted | C61: OCPS-RO-003 | D61: When resources participate in or constrain events as process entities, the OCPS simulation model shall represent those resources in an OCEL/OCED-compatible form. | E61: Human resources, machines, organizational units, locations, or environmental entities are modeled as object types or event attributes when they are part of the object-centric process data. | F61: LR-RO1; LR-RO3 | G61: OCPM-RO-001 | H61: Toward More Realistic Simulation Models Using Object-Centric Process Mining; Towards Organizational Digital Twins: Process Enhancement by Object-Centric Simulation | I61: BPS-013; BPS-015; BPS-017; BPS-030; BPS-034; BPS-057; BPS-062; FND-002; FND-006; SUP-006; SUP-007 | K61: Add object-centric specialization | L61: Ordinary resource modeling is insufficient when resources are themselves objects that participate in event-object relations. | M61: Derived from OCPM-RO-001 and linked it to the baseline resource category/eligibility requirements. | O61: Not carried to final catalogue | P61: The candidate requires resources to be represented as OCEL/OCED process entities when they participate in events. The final resource rows specify category, quantity, eligibility and allocation, while the general object rows apply when any resource is modelled as an object; none states this conditional resource-as-object representation obligation. There is therefore no faithful recorded final target. Input candidate premises are BPS:LR-RO1; BPS:LR-RO3; OCPM:OCPM-RO-001. Their individually scoped evidence is inherited through the adaptation links; no claim of a new direct source passage is made. Direct source-to-candidate inputs: BPS-013; BPS-015; BPS-017; BPS-030; BPS-034; BPS-057; BPS-062; FND-002; FND-006; SUP-006; SUP-007. This route is retained independently of any intermediate Evidence record; source-specific strength and scope are not inferred from the route alone. | S61: Source -> Candidate (direct recorded source use); Input candidates -> Candidate | T61: BPS-013; BPS-015; BPS-017; BPS-030; BPS-034; BPS-057; BPS-062; FND-002; FND-006; SUP-006; SUP-007
A62: Adapted:OCPS-RO-004 | B62: Adapted | C62: OCPS-RO-004 | D62: The OCPS simulation model shall specify which resources are eligible to execute each activity. | E62: The model defines eligible resource units, resource categories, roles, or object-represented resources for each activity occurrence. | F62: LR-RO3 | G62: OCPM-RO-001 | H62: Toward More Realistic Simulation Models Using Object-Centric Process Mining; Towards Organizational Digital Twins: Process Enhancement by Object-Centric Simulation | I62: BPS-013; BPS-015; BPS-030; BPS-057; BPS-062; FND-002; FND-006; SUP-006; SUP-007 | K62: Keep and align | L62: Eligibility rules remain a BPS requirement; OCPS may express eligibility using object-centric resource representation. | M62: Preserved LR-RO3 and added object-centric alignment for resources represented as OCED elements. | O62: Include in final synthesis | P62: Retained concept: The OCPS simulation model shall specify which resources are eligible to execute each activity. Final path: OCPS-R5.3. Transformation: Eligibility rules remain a BPS requirement; OCPS may express eligibility using object-centric resource representation. Input candidate premises are BPS:LR-RO3; OCPM:OCPM-RO-001. Their individually scoped evidence is inherited through the adaptation links; no claim of a new direct source passage is made. Direct source-to-candidate inputs: BPS-013; BPS-015; BPS-030; BPS-057; BPS-062; FND-002; FND-006; SUP-006; SUP-007. This route is retained independently of any intermediate Evidence record; source-specific strength and scope are not inferred from the route alone. | Q62: OCPS-R5; OCPS-R5.3 | R62: EV-AUD-0045 | S62: Source -> Candidate (direct recorded source use); Input candidates -> Candidate; Later verification (separate from original input) | T62: BPS-013; BPS-015; BPS-030; BPS-057; BPS-062; FND-002; FND-006; SUP-006; SUP-007
A63: Adapted:OCPS-RO-005 | B63: Adapted | C63: OCPS-RO-005 | D63: The OCPS simulation model shall specify the rule for selecting a resource from the eligible resources for an activity occurrence. | E63: When multiple eligible resources exist, the model defines the selection rule, priority, probability, schedule, or policy used to assign one or more resources. | F63: LR-RO4 | I63: BPS-009; BPS-013; BPS-015; BPS-030; BPS-034; BPS-056; BPS-057; BPS-062; FND-002; FND-006 | K63: Carry over | L63: No additional object-centric requirement in the second table changes the resource-selection rule itself. | M63: Carried over LR-RO4 without unsupported extension. | O63: Include in final synthesis | P63: Retained concept: The OCPS simulation model shall specify the rule for selecting a resource from the eligible resources for an activity occurrence. Final path: OCPS-R5.4. Transformation: No additional object-centric requirement in the second table changes the resource-selection rule itself. Input candidate premises are BPS:LR-RO4. Their individually scoped evidence is inherited through the adaptation links; no claim of a new direct source passage is made. Direct source-to-candidate inputs: BPS-009; BPS-013; BPS-015; BPS-030; BPS-034; BPS-056; BPS-057; BPS-062; FND-002; FND-006. This route is retained independently of any intermediate Evidence record; source-specific strength and scope are not inferred from the route alone. | Q63: OCPS-R5.4 | R63: EV-AUD-0046 | S63: Source -> Candidate (direct recorded source use); Input candidates -> Candidate; Later verification (separate from original input) | T63: BPS-009; BPS-013; BPS-015; BPS-030; BPS-034; BPS-056; BPS-057; BPS-062; FND-002; FND-006
